Workbook
Name \0: #REF!
Name \A: #REF!
Name \B: #REF!
Name \C: #REF!
Name \D: #REF!
Name \F: #REF!
Name \G: #REF!
Name \H: #REF!
Name \I: #REF!
Name \J: #REF!
Name \K: #REF!
Name \L: #REF!
Name \M: #REF!
Name \N: #REF!
Name \new: #REF!
Name \P: #REF!
Name \Q: #REF!
Name \U: #REF!
Name \V: #REF!
Name \Z: #REF!
Name ______________________tax1: #REF!
Name ______________________tax2: #REF!
Name ______________________tax3: #REF!
Name ______________________tax4: #REF!
Name _____________________tax1: #REF!
Name _____________________tax2: #REF!
Name _____________________tax3: #REF!
Name _____________________tax4: #REF!
Name ____________________tax1: #REF!
Name ____________________tax2: #REF!
Name ____________________tax3: #REF!
Name ____________________tax4: #REF!
Name ___________________tax1: #REF!
Name ___________________tax2: #REF!
Name ___________________tax3: #REF!
Name ___________________tax4: #REF!
Name __________________tax1: #REF!
Name __________________tax2: #REF!
Name __________________tax3: #REF!
Name __________________tax4: #REF!
Name _________________tax1: #REF!
Name _________________tax2: #REF!
Name _________________tax3: #REF!
Name _________________tax4: #REF!
Name ________________tax1: #REF!
Name ________________tax2: #REF!
Name ________________tax3: #REF!
Name ________________tax4: #REF!
Name _______________tax1: #REF!
Name _______________tax2: #REF!
Name _______________tax3: #REF!
Name _______________tax4: #REF!
Name ______________tax1: #REF!
Name ______________tax2: #REF!
Name ______________tax3: #REF!
Name ______________tax4: #REF!
Name _____________tax1: #REF!
Name _____________tax2: #REF!
Name _____________tax3: #REF!
Name _____________tax4: #REF!

Sheet STOC Accounting Diligence Datab
A1: =Project&" - "&City&", "&State -> OPEN - OPEN, OPEN
A2: =MID(CELL("filename",A1),FIND("]",CELL("filename",A1))+1,255) -> STOC Accounting Diligence Datab
B4: Input Tab
A6: Tab delineation
B7: Tab is completed and ready to be sent to the Client
B8: Tab has been completed by junior staff and is ready for review
B9: Tab has been started, but awaiting information from Client
B10: Tab has not been started
B11: Source file
A13: Project:
A14: Project Name | B14: OPEN
A15: Location of Practice (City) | B15: OPEN
A16: Location of Practice (State) | B16: OPEN
A18: Financial / reporting period:
A19: External Financial Statement | B19: Tax Return
A21: Calendar Year / Fiscal Year | B21: Calendar
A22: Stub Period | B22: 45565 | D22: =IF($B$21="Fiscal", "Hardkey (i) stub period date and (ii) second full year date","")
A23: Financial Reporting Period 2 | B23: =IF($B$21="Calendar",EOMONTH(B22,-MONTH(B22)),0) -> 45291 | D23: =IF($B$21="Fiscal", "Hardkey (i) stub period date and (ii) second full year date","")
A24: Financial Reporting Period 1 | B24: 44926 | D24: =IF($B$21="Fiscal", "Hardkey (i) stub period date and (ii) second full year date","")
A26: Tab checks:
A27: QE Summary | B27: =IFERROR(ROUND(SUM('QE Summary'!$D$50:$G$50),0),"")
A28: Recast Reported | B28: =IFERROR(ROUND(SUM('Recast Reported'!$C$46:$AN$46),0),"") -> 0
A29: Recast Mgmt. Adjusted | B29: =IFERROR(ROUND(SUM('Recast Mgmt. Adjusted'!$C$46:$AN$46),0),"") -> 0
A30: Other Recast | B30: =IFERROR(ROUND(SUM(#REF!)+SUM(#REF!),0),"")
A31: Lead Profit and Loss | B31: =IFERROR(ROUND(SUM('Lead PL'!$B$25:$H$25),0),"") -> 0
A32: Monthly Profit and Loss | B32: =IFERROR(ROUND(SUM(PL!$L$84:$AM$84),0),"") -> 0
A66: States
A67: AL
A68: AK
A69: AZ
A70: AR
A71: CA
A72: CO
A73: CT
A74: DE
A75: FL
A76: GA
A77: HI
... A116: WY

Sheet Cover >>>
B12: Quality of Earnings Analysis [DRAFT]
B14: =Project&" - "&City&", "&State -> OPEN - OPEN, OPEN
B15: =TODAY() -> 45819
A31: CONFIDENTIAL

Sheet QE Summary
A1: =Project&" - "&City&", "&State -> OPEN - OPEN, OPEN
A2: =MID(CELL("filename",A1),FIND("]",CELL("filename",A1))+1,255) -> QE Summary
A4: QE Summary
D5: QE Summary
D6: =First_Reporting_Year -> 44926 | E6: =Second_Reporting_Year -> 45291 | F6: =Stub_Period -> 45565 | I6: FY22 to FY23 | K6: FY23 to TTM24
C7: Revenue | I7: =+E7-D7 -> 0 | K7: =+F7-E7 -> 0
C8: YoY Change | D8: n/a | E8: =+((E7-D$7)/D$7)*100 -> #DIV/0! | F8: =+((F7-E$7)/E$7)*100 -> #DIV/0!
C10: Dental supplies | I10: =+E10-D10 -> 0 | K10: =+F10-E10 -> 0
C11: Ortho supplies | I11: =+E11-D11 -> 0 | K11: =+F11-E11 -> 0
C12: Lab fees | I12: =+E12-D12 -> 0 | K12: =+F12-E12 -> 0
C13: Gross Profit | D13: =D7-SUM(D10:D12) -> 0 | E13: =E7-SUM(E10:E12) -> 0 | F13: =F7-SUM(F10:F12) -> 0 | I13: =I7-SUM(I10:I12) -> 0 | J13: =J7-SUM(J10:J12) -> 0 | K13: =K7-SUM(K10:K12) -> 0 | L13: =L7-SUM(L10:L12) -> 0
C14: Gross Margin | D14: =+IFERROR(D13/D$7*100,0) -> 0 | E14: =+IFERROR(E13/E$7*100,0) -> 0 | F14: =+IFERROR(F13/F$7*100,0) -> 0
C16: Doctor wages | I16: =+E16-D16 -> 0 | K16: =+F16-E16 -> 0
C17: Clinic wages | I17: =+E17-D17 -> 0 | K17: =+F17-E17 -> 0
C18: Admin wages | I18: =+E18-D18 -> 0 | K18: =+F18-E18 -> 0
C19: Gross wages | I19: =+E19-D19 -> 0 | K19: =+F19-E19 -> 0
C20: Payroll taxes | I20: =+E20-D20 -> 0 | K20: =+F20-E20 -> 0
C21: Insurance | I21: =+E21-D21 -> 0 | K21: =+F21-E21 -> 0
C22: Employee 401(k) | I22: =+E22-D22 -> 0 | K22: =+F22-E22 -> 0
C23: Salary, payroll taxes, and benefits, total | D23: =SUM(D19:D22) -> 0 | E23: =SUM(E19:E22) -> 0 | F23: =SUM(F19:F22) -> 0 | I23: =+E23-D23 -> 0 | K23: =+F23-E23 -> 0
C24: Rent - real property | I24: =+E24-D24 -> 0 | K24: =+F24-E24 -> 0
C25: Property tax expense | I25: =+E25-D25 -> 0 | K25: =+F25-E25 -> 0
C26: Repairs and maintenance | I26: =+E26-D26 -> 0 | K26: =+F26-E26 -> 0
C27: Utilities expense | I27: =+E27-D27 -> 0 | K27: =+F27-E27 -> 0
C28: Rent and building expenses, total | D28: =SUM(D24:D27) -> 0 | E28: =SUM(E24:E27) -> 0 | F28: =SUM(F24:F27) -> 0 | I28: =+E28-D28 -> 0 | K28: =+F28-E28 -> 0
C29: Advertising | I29: =+E29-D29 -> 0 | K29: =+F29-E29 -> 0
C30: Other | I30: =+E30-D30 -> 0 | K30: =+F30-E30 -> 0
C31: Adjusted EBITDA | D31: =D13-SUM(D23,D28:D30) -> 0 | E31: =E13-SUM(E23,E28:E30) -> 0 | F31: =F13-SUM(F23,F28:F30) -> 0 | I31: =I13-SUM(I23,I28:I30) -> 0 | J31: =J13-SUM(J23,J28:J30) -> 0 | K31: =K13-SUM(K23,K28:K30) -> 0 | L31: =L13-SUM(L23,L28:L30) -> 0
C32: Adjusted EBITDA % | D32: =+IFERROR(D31/D$7*100,0) -> 0 | E32: =+IFERROR(E31/E$7*100,0) -> 0 | F32: =+IFERROR(F31/F$7*100,0) -> 0
C34: =C10 -> Dental supplies | D34: =+IFERROR(D10/D$7*100,0) -> 0 | E34: =+IFERROR(E10/E$7*100,0) -> 0 | F34: =+IFERROR(F10/F$7*100,0) -> 0
C35: =C11 -> Ortho supplies | D35: =+IFERROR(D11/D$7*100,0) -> 0 | E35: =+IFERROR(E11/E$7*100,0) -> 0 | F35: =+IFERROR(F11/F$7*100,0) -> 0
C36: =C12 -> Lab fees | D36: =+IFERROR(D12/D$7*100,0) -> 0 | E36: =+IFERROR(E12/E$7*100,0) -> 0 | F36: =+IFERROR(F12/F$7*100,0) -> 0
C37: =C16 -> Doctor wages | D37: =+IFERROR(D16/D$7*100,0) -> 0 | E37: =+IFERROR(E16/E$7*100,0) -> 0 | F37: =+IFERROR(F16/F$7*100,0) -> 0
C38: =C17 -> Clinic wages | D38: =+IFERROR(D17/D$7*100,0) -> 0 | E38: =+IFERROR(E17/E$7*100,0) -> 0 | F38: =+IFERROR(F17/F$7*100,0) -> 0
C39: =C18 -> Admin wages | D39: =+IFERROR(D18/D$7*100,0) -> 0 | E39: =+IFERROR(E18/E$7*100,0) -> 0 | F39: =+IFERROR(F18/F$7*100,0) -> 0
C40: =C20 -> Payroll taxes | D40: =+IFERROR(D20/D$7*100,0) -> 0 | E40: =+IFERROR(E20/E$7*100,0) -> 0 | F40: =+IFERROR(F20/F$7*100,0) -> 0
C41: =C21 -> Insurance | D41: =+IFERROR(D21/D$7*100,0) -> 0 | E41: =+IFERROR(E21/E$7*100,0) -> 0 | F41: =+IFERROR(F21/F$7*100,0) -> 0
C42: =C22 -> Employee 401(k) | D42: =+IFERROR(D22/D$7*100,0) -> 0 | E42: =+IFERROR(E22/E$7*100,0) -> 0 | F42: =+IFERROR(F22/F$7*100,0) -> 0
C43: =C24 -> Rent - real property | D43: =+IFERROR(D24/D$7*100,0) -> 0 | E43: =+IFERROR(E24/E$7*100,0) -> 0 | F43: =+IFERROR(F24/F$7*100,0) -> 0
C44: =C25 -> Property tax expense | D44: =+IFERROR(D25/D$7*100,0) -> 0 | E44: =+IFERROR(E25/E$7*100,0) -> 0 | F44: =+IFERROR(F25/F$7*100,0) -> 0
C45: =C26 -> Repairs and maintenance | D45: =+IFERROR(D26/D$7*100,0) -> 0 | E45: =+IFERROR(E26/E$7*100,0) -> 0 | F45: =+IFERROR(F26/F$7*100,0) -> 0
C46: =C27 -> Utilities expense | D46: =+IFERROR(D27/D$7*100,0) -> 0 | E46: =+IFERROR(E27/E$7*100,0) -> 0 | F46: =+IFERROR(F27/F$7*100,0) -> 0
C47: =C29 -> Advertising | D47: =+IFERROR(D29/D$7*100,0) -> 0 | E47: =+IFERROR(E29/E$7*100,0) -> 0 | F47: =+IFERROR(F29/F$7*100,0) -> 0
C48: =C30 -> Other | D48: =+IFERROR(D30/D$7*100,0) -> 0 | E48: =+IFERROR(E30/E$7*100,0) -> 0 | F48: =+IFERROR(F30/F$7*100,0) -> 0
C50: Check | D50: ='Lead QE'!#REF!*1000-D31 -> #REF! | E50: ='Lead QE'!#REF!*1000-E31 -> #REF! | F50: ='Lead QE'!#REF!*1000-F31 -> #REF!
B51: Key Issue(s)
B52: 1
B54: =B52+1 -> 2

Sheet QE & Support >>>
A10: =RIGHT(CELL("filename",A1),LEN(CELL("filename",A1))-FIND("]",CELL("filename",A1))) -> QE & Support >>>

Sheet Lead QE
B1: =Project&" - "&City&", "&State -> OPEN - OPEN, OPEN
B2: =MID(CELL("filename",B1),FIND("]",CELL("filename",B1))+1,255) -> Lead QE
B4: Quality of Earnings Table
A5: LOI Mapping | B5: In $000's | C5: Ref | D5: =First_Reporting_Year -> 44926 | E5: =Second_Reporting_Year -> 45291 | F5: =Stub_Period -> 45565 | G5: 45199 | H5: 45565 | J5: =EOMONTH(D5,-11) -> 44592 | K5: =EOMONTH(J5,1) -> 44620 | L5: =EOMONTH(K5,1) -> 44651 | M5: =EOMONTH(L5,1) -> 44681 | N5: =EOMONTH(M5,1) -> 44712 | O5: =EOMONTH(N5,1) -> 44742 | P5: =EOMONTH(O5,1) -> 44773 | Q5: =EOMONTH(P5,1) -> 44804 | R5: =EOMONTH(Q5,1) -> 44834 | ... AP5: =EOMONTH(AO5,1) -> 45565
B6: Reported revenue | D6: =SUMIFS($J6:$AP6,$J$5:$AP$5,">"&EOMONTH(D$5,-12),$J$5:$AP$5,"<="&D$5) -> 0 | E6: =SUMIFS($J6:$AP6,$J$5:$AP$5,">"&EOMONTH(E$5,-12),$J$5:$AP$5,"<="&E$5) -> 0 | F6: =SUMIFS($J6:$AP6,$J$5:$AP$5,">"&EOMONTH(F$5,-12),$J$5:$AP$5,"<="&F$5) -> 0 | G6: =SUMIFS($J6:$AS6,$J$5:$AS$5,">"&EOMONTH(G$5,-9),$J$5:$AS$5,"<="&G$5) -> 0 | H6: =SUMIFS($J6:$AS6,$J$5:$AS$5,">"&EOMONTH(H$5,-9),$J$5:$AS$5,"<="&H$5) -> 0 | J6: =PL!L15 -> 0 | K6: =PL!M15 -> 0 | L6: =PL!N15 -> 0 | M6: =PL!O15 -> 0 | N6: =PL!P15 -> 0 | O6: =PL!Q15 -> 0 | P6: =PL!R15 -> 0 | Q6: =PL!S15 -> 0 | ... AK6: =PL!AM15 -> 0 | AL6: =PL!AS15 -> 0 | AM6: =PL!AT15 -> 0 | AN6: =PL!AU15 -> 0 | AO6: =PL!AV15 -> 0 | AP6: =PL!AW15 -> 0
B8: Net income | D8: =SUMIFS($J8:$AP8,$J$5:$AP$5,">"&EOMONTH(D$5,-12),$J$5:$AP$5,"<="&D$5) -> 0 | E8: =SUMIFS($J8:$AP8,$J$5:$AP$5,">"&EOMONTH(E$5,-12),$J$5:$AP$5,"<="&E$5) -> 0 | F8: =SUMIFS($J8:$AP8,$J$5:$AP$5,">"&EOMONTH(F$5,-12),$J$5:$AP$5,"<="&F$5) -> 0 | G8: =SUMIFS($J8:$AS8,$J$5:$AS$5,">"&EOMONTH(G$5,-9),$J$5:$AS$5,"<="&G$5) -> 0 | H8: =SUMIFS($J8:$AS8,$J$5:$AS$5,">"&EOMONTH(H$5,-9),$J$5:$AS$5,"<="&H$5) -> 0 | J8: =PL!L73 -> 0 | K8: =PL!M73 -> 0 | L8: =PL!N73 -> 0 | M8: =PL!O73 -> 0 | N8: =PL!P73 -> 0 | O8: =PL!Q73 -> 0 | P8: =PL!R73 -> 0 | Q8: =PL!S73 -> 0 | ... AK8: =PL!AM73 -> 0 | AL8: =PL!AS73 -> 0 | AM8: =PL!AT73 -> 0 | AN8: =PL!AU73 -> 0 | AO8: =PL!AV73 -> 0 | AP8: =PL!AW73 -> 0
B9: Depreciation and amortization | D9: =SUMIFS($J9:$AP9,$J$5:$AP$5,">"&EOMONTH(D$5,-12),$J$5:$AP$5,"<="&D$5) -> 0 | E9: =SUMIFS($J9:$AP9,$J$5:$AP$5,">"&EOMONTH(E$5,-12),$J$5:$AP$5,"<="&E$5) -> 0 | F9: =SUMIFS($J9:$AP9,$J$5:$AP$5,">"&EOMONTH(F$5,-12),$J$5:$AP$5,"<="&F$5) -> 0 | G9: =SUMIFS($J9:$AS9,$J$5:$AS$5,">"&EOMONTH(G$5,-9),$J$5:$AS$5,"<="&G$5) -> 0 | H9: =SUMIFS($J9:$AS9,$J$5:$AS$5,">"&EOMONTH(H$5,-9),$J$5:$AS$5,"<="&H$5) -> 0 | J9: =PL!L75 -> 0 | K9: =PL!M75 -> 0 | L9: =PL!N75 -> 0 | M9: =PL!O75 -> 0 | N9: =PL!P75 -> 0 | O9: =PL!Q75 -> 0 | P9: =PL!R75 -> 0 | Q9: =PL!S75 -> 0 | ... AK9: =PL!AM75 -> 0 | AL9: =PL!AS75 -> 0 | AM9: =PL!AT75 -> 0 | AN9: =PL!AU75 -> 0 | AO9: =PL!AV75 -> 0 | AP9: =PL!AW75 -> 0
B10: Interest expense | D10: =SUMIFS($J10:$AP10,$J$5:$AP$5,">"&EOMONTH(D$5,-12),$J$5:$AP$5,"<="&D$5) -> 0 | E10: =SUMIFS($J10:$AP10,$J$5:$AP$5,">"&EOMONTH(E$5,-12),$J$5:$AP$5,"<="&E$5) -> 0 | F10: =SUMIFS($J10:$AP10,$J$5:$AP$5,">"&EOMONTH(F$5,-12),$J$5:$AP$5,"<="&F$5) -> 0 | G10: =SUMIFS($J10:$AS10,$J$5:$AS$5,">"&EOMONTH(G$5,-9),$J$5:$AS$5,"<="&G$5) -> 0 | H10: =SUMIFS($J10:$AS10,$J$5:$AS$5,">"&EOMONTH(H$5,-9),$J$5:$AS$5,"<="&H$5) -> 0 | J10: =PL!L76 -> 0 | K10: =PL!M76 -> 0 | L10: =PL!N76 -> 0 | M10: =PL!O76 -> 0 | N10: =PL!P76 -> 0 | O10: =PL!Q76 -> 0 | P10: =PL!R76 -> 0 | Q10: =PL!S76 -> 0 | ... AK10: =PL!AM76 -> 0 | AL10: =PL!AS76 -> 0 | AM10: =PL!AT76 -> 0 | AN10: =PL!AU76 -> 0 | AO10: =PL!AV76 -> 0 | AP10: =PL!AW76 -> 0
B11: Income tax | D11: =SUMIFS($J11:$AP11,$J$5:$AP$5,">"&EOMONTH(D$5,-12),$J$5:$AP$5,"<="&D$5) -> 0 | E11: =SUMIFS($J11:$AP11,$J$5:$AP$5,">"&EOMONTH(E$5,-12),$J$5:$AP$5,"<="&E$5) -> 0 | F11: =SUMIFS($J11:$AP11,$J$5:$AP$5,">"&EOMONTH(F$5,-12),$J$5:$AP$5,"<="&F$5) -> 0 | G11: =SUMIFS($J11:$AS11,$J$5:$AS$5,">"&EOMONTH(G$5,-9),$J$5:$AS$5,"<="&G$5) -> 0 | H11: =SUMIFS($J11:$AS11,$J$5:$AS$5,">"&EOMONTH(H$5,-9),$J$5:$AS$5,"<="&H$5) -> 0 | J11: =PL!L77 -> 0 | K11: =PL!M77 -> 0 | L11: =PL!N77 -> 0 | M11: =PL!O77 -> 0 | N11: =PL!P77 -> 0 | O11: =PL!Q77 -> 0 | P11: =PL!R77 -> 0 | Q11: =PL!S77 -> 0 | ... AK11: =PL!AM77 -> 0 | AL11: =PL!AS77 -> 0 | AM11: =PL!AT77 -> 0 | AN11: =PL!AU77 -> 0 | AO11: =PL!AV77 -> 0 | AP11: =PL!AW77 -> 0
B12: Reported EBITDA | D12: =SUM(D8:D11) -> 0 | E12: =SUM(E8:E11) -> 0 | F12: =SUM(F8:F11) -> 0 | G12: =SUMIFS($J12:$AS12,$J$5:$AS$5,">"&EOMONTH(G$5,-9),$J$5:$AS$5,"<="&G$5) -> 0 | H12: =SUMIFS($J12:$AS12,$J$5:$AS$5,">"&EOMONTH(H$5,-9),$J$5:$AS$5,"<="&H$5) -> 0 | J12: =SUM(J8:J11) -> 0 | K12: =SUM(K8:K11) -> 0 | L12: =SUM(L8:L11) -> 0 | M12: =SUM(M8:M11) -> 0 | N12: =SUM(N8:N11) -> 0 | O12: =SUM(O8:O11) -> 0 | P12: =SUM(P8:P11) -> 0 | Q12: =SUM(Q8:Q11) -> 0 | ... AP12: =SUM(AP8:AP11) -> 0
B13: % margin | D13: =(D12/D6)*100 -> #DIV/0! | E13: =(E12/E6)*100 -> #DIV/0! | F13: =(F12/F6)*100 -> #DIV/0! | G13: =(G12/G6)*100 -> #DIV/0! | H13: =(H12/H6)*100 -> #DIV/0! | J13: =(J12/J6)*100 -> #DIV/0! | K13: =(K12/K6)*100 -> #DIV/0! | L13: =(L12/L6)*100 -> #DIV/0! | M13: =(M12/M6)*100 -> #DIV/0! | N13: =(N12/N6)*100 -> #DIV/0! | O13: =(O12/O6)*100 -> #DIV/0! | P13: =(P12/P6)*100 -> #DIV/0! | Q13: =(Q12/Q6)*100 -> #DIV/0! | ... AP13: =(AP12/AP6)*100 -> #DIV/0!
B15: Management adjustments
A16: =B16 -> [Input adjustment] | B16: [Input adjustment] | C16: 1 | D16: =SUMIFS($J16:$AP16,$J$5:$AP$5,">"&EOMONTH(D$5,-12),$J$5:$AP$5,"<="&D$5) -> 0 | E16: =SUMIFS($J16:$AP16,$J$5:$AP$5,">"&EOMONTH(E$5,-12),$J$5:$AP$5,"<="&E$5) -> 0 | F16: =SUMIFS($J16:$AP16,$J$5:$AP$5,">"&EOMONTH(F$5,-12),$J$5:$AP$5,"<="&F$5) -> 0 | G16: =SUMIFS($J16:$AS16,$J$5:$AS$5,">"&EOMONTH(G$5,-9),$J$5:$AS$5,"<="&G$5) -> 0 | H16: =SUMIFS($J16:$AS16,$J$5:$AS$5,">"&EOMONTH(H$5,-9),$J$5:$AS$5,"<="&H$5) -> 0 | J16: ='QE Detail - MGMT.'!H16 -> 0 | K16: ='QE Detail - MGMT.'!I16 -> 0 | L16: ='QE Detail - MGMT.'!J16 -> 0 | M16: ='QE Detail - MGMT.'!K16 -> 0 | N16: ='QE Detail - MGMT.'!L16 -> 0 | O16: ='QE Detail - MGMT.'!M16 -> 0 | P16: ='QE Detail - MGMT.'!N16 -> 0 | Q16: ='QE Detail - MGMT.'!O16 -> 0 | ... AK16: ='QE Detail - MGMT.'!AI16 -> 0 | AL16: ='QE Detail - MGMT.'!AO16 -> 0 | AM16: ='QE Detail - MGMT.'!AP16 -> 0 | AN16: ='QE Detail - MGMT.'!AQ16 -> 0 | AO16: ='QE Detail - MGMT.'!AR16 -> 0 | AP16: ='QE Detail - MGMT.'!AS16 -> 0
A17: =B17 -> [Input adjustment] | B17: [Input adjustment] | C17: =+C16+1 -> 2 | D17: =SUMIFS($J17:$AP17,$J$5:$AP$5,">"&EOMONTH(D$5,-12),$J$5:$AP$5,"<="&D$5) -> 0 | E17: =SUMIFS($J17:$AP17,$J$5:$AP$5,">"&EOMONTH(E$5,-12),$J$5:$AP$5,"<="&E$5) -> 0 | F17: =SUMIFS($J17:$AP17,$J$5:$AP$5,">"&EOMONTH(F$5,-12),$J$5:$AP$5,"<="&F$5) -> 0 | G17: =SUMIFS($J17:$AS17,$J$5:$AS$5,">"&EOMONTH(G$5,-9),$J$5:$AS$5,"<="&G$5) -> 0 | H17: =SUMIFS($J17:$AS17,$J$5:$AS$5,">"&EOMONTH(H$5,-9),$J$5:$AS$5,"<="&H$5) -> 0 | J17: ='QE Detail - MGMT.'!H22 -> 0 | K17: ='QE Detail - MGMT.'!I22 -> 0 | L17: ='QE Detail - MGMT.'!J22 -> 0 | M17: ='QE Detail - MGMT.'!K22 -> 0 | N17: ='QE Detail - MGMT.'!L22 -> 0 | O17: ='QE Detail - MGMT.'!M22 -> 0 | P17: ='QE Detail - MGMT.'!N22 -> 0 | Q17: ='QE Detail - MGMT.'!O22 -> 0 | ... AK17: ='QE Detail - MGMT.'!AI22 -> 0 | AL17: ='QE Detail - MGMT.'!AO22 -> 0 | AM17: ='QE Detail - MGMT.'!AP22 -> 0 | AN17: ='QE Detail - MGMT.'!AQ22 -> 0 | AO17: ='QE Detail - MGMT.'!AR22 -> 0 | AP17: ='QE Detail - MGMT.'!AS22 -> 0
A18: =B18 -> [Input adjustment] | B18: [Input adjustment] | C18: =+C17+1 -> 3 | D18: =SUMIFS($J18:$AP18,$J$5:$AP$5,">"&EOMONTH(D$5,-12),$J$5:$AP$5,"<="&D$5) -> 0 | E18: =SUMIFS($J18:$AP18,$J$5:$AP$5,">"&EOMONTH(E$5,-12),$J$5:$AP$5,"<="&E$5) -> 0 | F18: =SUMIFS($J18:$AP18,$J$5:$AP$5,">"&EOMONTH(F$5,-12),$J$5:$AP$5,"<="&F$5) -> 0 | G18: =SUMIFS($J18:$AS18,$J$5:$AS$5,">"&EOMONTH(G$5,-9),$J$5:$AS$5,"<="&G$5) -> 0 | H18: =SUMIFS($J18:$AS18,$J$5:$AS$5,">"&EOMONTH(H$5,-9),$J$5:$AS$5,"<="&H$5) -> 0 | J18: ='QE Detail - MGMT.'!H37 -> 0 | K18: ='QE Detail - MGMT.'!I37 -> 0 | L18: ='QE Detail - MGMT.'!J37 -> 0 | M18: ='QE Detail - MGMT.'!K37 -> 0 | N18: ='QE Detail - MGMT.'!L37 -> 0 | O18: ='QE Detail - MGMT.'!M37 -> 0 | P18: ='QE Detail - MGMT.'!N37 -> 0 | Q18: ='QE Detail - MGMT.'!O37 -> 0 | ... AK18: ='QE Detail - MGMT.'!AI37 -> 0 | AL18: ='QE Detail - MGMT.'!AO37 -> 0 | AM18: ='QE Detail - MGMT.'!AP37 -> 0 | AN18: ='QE Detail - MGMT.'!AQ37 -> 0 | AO18: ='QE Detail - MGMT.'!AR37 -> 0 | AP18: ='QE Detail - MGMT.'!AS37 -> 0
A19: =B19 -> [Input adjustment] | B19: [Input adjustment] | C19: =+C18+1 -> 4 | D19: =SUMIFS($J19:$AP19,$J$5:$AP$5,">"&EOMONTH(D$5,-12),$J$5:$AP$5,"<="&D$5) -> 0 | E19: =SUMIFS($J19:$AP19,$J$5:$AP$5,">"&EOMONTH(E$5,-12),$J$5:$AP$5,"<="&E$5) -> 0 | F19: =SUMIFS($J19:$AP19,$J$5:$AP$5,">"&EOMONTH(F$5,-12),$J$5:$AP$5,"<="&F$5) -> 0 | G19: =SUMIFS($J19:$AS19,$J$5:$AS$5,">"&EOMONTH(G$5,-9),$J$5:$AS$5,"<="&G$5) -> 0 | H19: =SUMIFS($J19:$AS19,$J$5:$AS$5,">"&EOMONTH(H$5,-9),$J$5:$AS$5,"<="&H$5) -> 0 | J19: ='QE Detail - MGMT.'!H46 -> 0 | K19: ='QE Detail - MGMT.'!I46 -> 0 | L19: ='QE Detail - MGMT.'!J46 -> 0 | M19: ='QE Detail - MGMT.'!K46 -> 0 | N19: ='QE Detail - MGMT.'!L46 -> 0 | O19: ='QE Detail - MGMT.'!M46 -> 0 | P19: ='QE Detail - MGMT.'!N46 -> 0 | Q19: ='QE Detail - MGMT.'!O46 -> 0 | ... AK19: ='QE Detail - MGMT.'!AI46 -> 0 | AL19: ='QE Detail - MGMT.'!AO46 -> 0 | AM19: ='QE Detail - MGMT.'!AP46 -> 0 | AN19: ='QE Detail - MGMT.'!AQ46 -> 0 | AO19: ='QE Detail - MGMT.'!AR46 -> 0 | AP19: ='QE Detail - MGMT.'!AS46 -> 0
A20: =B20 -> [Input adjustment] | B20: [Input adjustment] | C20: =+C19+1 -> 5 | D20: =SUMIFS($J20:$AP20,$J$5:$AP$5,">"&EOMONTH(D$5,-12),$J$5:$AP$5,"<="&D$5) -> 0 | E20: =SUMIFS($J20:$AP20,$J$5:$AP$5,">"&EOMONTH(E$5,-12),$J$5:$AP$5,"<="&E$5) -> 0 | F20: =SUMIFS($J20:$AP20,$J$5:$AP$5,">"&EOMONTH(F$5,-12),$J$5:$AP$5,"<="&F$5) -> 0 | G20: =SUMIFS($J20:$AS20,$J$5:$AS$5,">"&EOMONTH(G$5,-9),$J$5:$AS$5,"<="&G$5) -> 0 | H20: =SUMIFS($J20:$AS20,$J$5:$AS$5,">"&EOMONTH(H$5,-9),$J$5:$AS$5,"<="&H$5) -> 0 | J20: ='QE Detail - MGMT.'!H57 -> 0 | K20: ='QE Detail - MGMT.'!I57 -> 0 | L20: ='QE Detail - MGMT.'!J57 -> 0 | M20: ='QE Detail - MGMT.'!K57 -> 0 | N20: ='QE Detail - MGMT.'!L57 -> 0 | O20: ='QE Detail - MGMT.'!M57 -> 0 | P20: ='QE Detail - MGMT.'!N57 -> 0 | Q20: ='QE Detail - MGMT.'!O57 -> 0 | ... AK20: ='QE Detail - MGMT.'!AI57 -> 0 | AL20: ='QE Detail - MGMT.'!AO57 -> 0 | AM20: ='QE Detail - MGMT.'!AP57 -> 0 | AN20: ='QE Detail - MGMT.'!AQ57 -> 0 | AO20: ='QE Detail - MGMT.'!AR57 -> 0 | AP20: ='QE Detail - MGMT.'!AS57 -> 0
A21: =B21 -> [Input adjustment] | B21: [Input adjustment] | C21: =+C20+1 -> 6 | D21: =SUMIFS($J21:$AP21,$J$5:$AP$5,">"&EOMONTH(D$5,-12),$J$5:$AP$5,"<="&D$5) -> 0 | E21: =SUMIFS($J21:$AP21,$J$5:$AP$5,">"&EOMONTH(E$5,-12),$J$5:$AP$5,"<="&E$5) -> 0 | F21: =SUMIFS($J21:$AP21,$J$5:$AP$5,">"&EOMONTH(F$5,-12),$J$5:$AP$5,"<="&F$5) -> 0 | G21: =SUMIFS($J21:$AS21,$J$5:$AS$5,">"&EOMONTH(G$5,-9),$J$5:$AS$5,"<="&G$5) -> 0 | H21: =SUMIFS($J21:$AS21,$J$5:$AS$5,">"&EOMONTH(H$5,-9),$J$5:$AS$5,"<="&H$5) -> 0 | J21: ='QE Detail - MGMT.'!H64 -> 0 | K21: ='QE Detail - MGMT.'!I64 -> 0 | L21: ='QE Detail - MGMT.'!J64 -> 0 | M21: ='QE Detail - MGMT.'!K64 -> 0 | N21: ='QE Detail - MGMT.'!L64 -> 0 | O21: ='QE Detail - MGMT.'!M64 -> 0 | P21: ='QE Detail - MGMT.'!N64 -> 0 | Q21: ='QE Detail - MGMT.'!O64 -> 0 | ... AK21: ='QE Detail - MGMT.'!AI64 -> 0 | AL21: ='QE Detail - MGMT.'!AO64 -> 0 | AM21: ='QE Detail - MGMT.'!AP64 -> 0 | AN21: ='QE Detail - MGMT.'!AQ64 -> 0 | AO21: ='QE Detail - MGMT.'!AR64 -> 0 | AP21: ='QE Detail - MGMT.'!AS64 -> 0
A22: =B22 -> [Input adjustment] | B22: [Input adjustment] | C22: =+C21+1 -> 7 | D22: =SUMIFS($J22:$AP22,$J$5:$AP$5,">"&EOMONTH(D$5,-12),$J$5:$AP$5,"<="&D$5) -> 0 | E22: =SUMIFS($J22:$AP22,$J$5:$AP$5,">"&EOMONTH(E$5,-12),$J$5:$AP$5,"<="&E$5) -> 0 | F22: =SUMIFS($J22:$AP22,$J$5:$AP$5,">"&EOMONTH(F$5,-12),$J$5:$AP$5,"<="&F$5) -> 0 | G22: =SUMIFS($J22:$AS22,$J$5:$AS$5,">"&EOMONTH(G$5,-9),$J$5:$AS$5,"<="&G$5) -> 0 | H22: =SUMIFS($J22:$AS22,$J$5:$AS$5,">"&EOMONTH(H$5,-9),$J$5:$AS$5,"<="&H$5) -> 0 | J22: ='QE Detail - MGMT.'!H70 -> 0 | K22: ='QE Detail - MGMT.'!I70 -> 0 | L22: ='QE Detail - MGMT.'!J70 -> 0 | M22: ='QE Detail - MGMT.'!K70 -> 0 | N22: ='QE Detail - MGMT.'!L70 -> 0 | O22: ='QE Detail - MGMT.'!M70 -> 0 | P22: ='QE Detail - MGMT.'!N70 -> 0 | Q22: ='QE Detail - MGMT.'!O70 -> 0 | ... AK22: ='QE Detail - MGMT.'!AI70 -> 0 | AL22: ='QE Detail - MGMT.'!AO70 -> 0 | AM22: ='QE Detail - MGMT.'!AP70 -> 0 | AN22: ='QE Detail - MGMT.'!AQ70 -> 0 | AO22: ='QE Detail - MGMT.'!AR70 -> 0 | AP22: ='QE Detail - MGMT.'!AS70 -> 0
A23: =B23 -> [Input adjustment] | B23: [Input adjustment] | C23: =+C22+1 -> 8 | D23: =SUMIFS($J23:$AP23,$J$5:$AP$5,">"&EOMONTH(D$5,-12),$J$5:$AP$5,"<="&D$5) -> 0 | E23: =SUMIFS($J23:$AP23,$J$5:$AP$5,">"&EOMONTH(E$5,-12),$J$5:$AP$5,"<="&E$5) -> 0 | F23: =SUMIFS($J23:$AP23,$J$5:$AP$5,">"&EOMONTH(F$5,-12),$J$5:$AP$5,"<="&F$5) -> 0 | G23: =SUMIFS($J23:$AS23,$J$5:$AS$5,">"&EOMONTH(G$5,-9),$J$5:$AS$5,"<="&G$5) -> 0 | H23: =SUMIFS($J23:$AS23,$J$5:$AS$5,">"&EOMONTH(H$5,-9),$J$5:$AS$5,"<="&H$5) -> 0 | J23: ='QE Detail - MGMT.'!H77 -> 0 | K23: ='QE Detail - MGMT.'!I77 -> 0 | L23: ='QE Detail - MGMT.'!J77 -> 0 | M23: ='QE Detail - MGMT.'!K77 -> 0 | N23: ='QE Detail - MGMT.'!L77 -> 0 | O23: ='QE Detail - MGMT.'!M77 -> 0 | P23: ='QE Detail - MGMT.'!N77 -> 0 | Q23: ='QE Detail - MGMT.'!O77 -> 0 | ... AK23: ='QE Detail - MGMT.'!AI77 -> 0 | AL23: ='QE Detail - MGMT.'!AO77 -> 0 | AM23: ='QE Detail - MGMT.'!AP77 -> 0 | AN23: ='QE Detail - MGMT.'!AQ77 -> 0 | AO23: ='QE Detail - MGMT.'!AR77 -> 0 | AP23: ='QE Detail - MGMT.'!AS77 -> 0
A24: =B24 -> [Input adjustment] | B24: [Input adjustment] | C24: =+C23+1 -> 9 | D24: =SUMIFS($J24:$AP24,$J$5:$AP$5,">"&EOMONTH(D$5,-12),$J$5:$AP$5,"<="&D$5) -> 0 | E24: =SUMIFS($J24:$AP24,$J$5:$AP$5,">"&EOMONTH(E$5,-12),$J$5:$AP$5,"<="&E$5) -> 0 | F24: =SUMIFS($J24:$AP24,$J$5:$AP$5,">"&EOMONTH(F$5,-12),$J$5:$AP$5,"<="&F$5) -> 0 | G24: =SUMIFS($J24:$AS24,$J$5:$AS$5,">"&EOMONTH(G$5,-9),$J$5:$AS$5,"<="&G$5) -> 0 | H24: =SUMIFS($J24:$AS24,$J$5:$AS$5,">"&EOMONTH(H$5,-9),$J$5:$AS$5,"<="&H$5) -> 0 | J24: ='QE Detail - MGMT.'!H83 -> 0 | K24: ='QE Detail - MGMT.'!I83 -> 0 | L24: ='QE Detail - MGMT.'!J83 -> 0 | M24: ='QE Detail - MGMT.'!K83 -> 0 | N24: ='QE Detail - MGMT.'!L83 -> 0 | O24: ='QE Detail - MGMT.'!M83 -> 0 | P24: ='QE Detail - MGMT.'!N83 -> 0 | Q24: ='QE Detail - MGMT.'!O83 -> 0 | ... AK24: ='QE Detail - MGMT.'!AI83 -> 0 | AL24: ='QE Detail - MGMT.'!AO83 -> 0 | AM24: ='QE Detail - MGMT.'!AP83 -> 0 | AN24: ='QE Detail - MGMT.'!AQ83 -> 0 | AO24: ='QE Detail - MGMT.'!AR83 -> 0 | AP24: ='QE Detail - MGMT.'!AS83 -> 0
A25: =B25 -> [Input adjustment] | B25: [Input adjustment] | C25: =+C24+1 -> 10 | D25: =SUMIFS($J25:$AP25,$J$5:$AP$5,">"&EOMONTH(D$5,-12),$J$5:$AP$5,"<="&D$5) -> 0 | E25: =SUMIFS($J25:$AP25,$J$5:$AP$5,">"&EOMONTH(E$5,-12),$J$5:$AP$5,"<="&E$5) -> 0 | F25: =SUMIFS($J25:$AP25,$J$5:$AP$5,">"&EOMONTH(F$5,-12),$J$5:$AP$5,"<="&F$5) -> 0 | G25: =SUMIFS($J25:$AS25,$J$5:$AS$5,">"&EOMONTH(G$5,-9),$J$5:$AS$5,"<="&G$5) -> 0 | H25: =SUMIFS($J25:$AS25,$J$5:$AS$5,">"&EOMONTH(H$5,-9),$J$5:$AS$5,"<="&H$5) -> 0 | J25: ='QE Detail - MGMT.'!H91 -> 0 | K25: ='QE Detail - MGMT.'!I91 -> 0 | L25: ='QE Detail - MGMT.'!J91 -> 0 | M25: ='QE Detail - MGMT.'!K91 -> 0 | N25: ='QE Detail - MGMT.'!L91 -> 0 | O25: ='QE Detail - MGMT.'!M91 -> 0 | P25: ='QE Detail - MGMT.'!N91 -> 0 | Q25: ='QE Detail - MGMT.'!O91 -> 0 | ... AK25: ='QE Detail - MGMT.'!AI91 -> 0 | AL25: ='QE Detail - MGMT.'!AO91 -> 0 | AM25: ='QE Detail - MGMT.'!AP91 -> 0 | AN25: ='QE Detail - MGMT.'!AQ91 -> 0 | AO25: ='QE Detail - MGMT.'!AR91 -> 0 | AP25: ='QE Detail - MGMT.'!AS91 -> 0
B26: Total management adjustments | D26: =SUM(D16:D25) -> 0 | E26: =SUM(E16:E25) -> 0 | F26: =SUM(F16:F25) -> 0 | G26: =SUM(G16:G25) -> 0 | H26: =SUM(H16:H25) -> 0 | J26: =SUM(J16:J25) -> 0 | K26: =SUM(K16:K25) -> 0 | L26: =SUM(L16:L25) -> 0 | M26: =SUM(M16:M25) -> 0 | N26: =SUM(N16:N25) -> 0 | O26: =SUM(O16:O25) -> 0 | P26: =SUM(P16:P25) -> 0 | Q26: =SUM(Q16:Q25) -> 0 | ... AP26: =SUM(AP16:AP25) -> 0
B27: Management adjusted EBITDA | D27: =SUM(D12,D26) -> 0 | E27: =SUM(E12,E26) -> 0 | F27: =SUM(F12,F26) -> 0 | G27: =SUM(G12,G26) -> 0 | H27: =SUM(H12,H26) -> 0 | J27: =SUM(J12,J26) -> 0 | K27: =SUM(K12,K26) -> 0 | L27: =SUM(L12,L26) -> 0 | M27: =SUM(M12,M26) -> 0 | N27: =SUM(N12,N26) -> 0 | O27: =SUM(O12,O26) -> 0 | P27: =SUM(P12,P26) -> 0 | Q27: =SUM(Q12,Q26) -> 0 | ... AP27: =SUM(AP12,AP26) -> 0
B28: % margin | D28: =(D27/'Recast Mgmt. Adjusted'!C6)*100 -> #DIV/0! | E28: =(E27/'Recast Mgmt. Adjusted'!D6)*100 -> #DIV/0! | F28: =(F27/'Recast Mgmt. Adjusted'!E6)*100 -> #DIV/0! | G28: n/a | H28: n/a | J28: =(J27/'Recast Mgmt. Adjusted'!G6)*100 -> #DIV/0! | K28: =(K27/'Recast Mgmt. Adjusted'!H6)*100 -> #DIV/0! | L28: =(L27/'Recast Mgmt. Adjusted'!I6)*100 -> #DIV/0! | M28: =(M27/'Recast Mgmt. Adjusted'!J6)*100 -> #DIV/0! | N28: =(N27/'Recast Mgmt. Adjusted'!K6)*100 -> #DIV/0! | O28: =(O27/'Recast Mgmt. Adjusted'!L6)*100 -> #DIV/0! | P28: =(P27/'Recast Mgmt. Adjusted'!M6)*100 -> #DIV/0! | Q28: =(Q27/'Recast Mgmt. Adjusted'!N6)*100 -> #DIV/0! | ... AK28: =(AK27/'Recast Mgmt. Adjusted'!AH6)*100 -> #DIV/0! | AL28: =(AL27/'Recast Mgmt. Adjusted'!AN6)*100 -> #DIV/0! | AM28: =(AM27/'Recast Mgmt. Adjusted'!AO6)*100 -> #DIV/0! | AN28: =(AN27/'Recast Mgmt. Adjusted'!AP6)*100 -> #DIV/0! | AO28: =(AO27/'Recast Mgmt. Adjusted'!AQ6)*100 -> #DIV/0! | AP28: =(AP27/'Recast Mgmt. Adjusted'!AR6)*100 -> #DIV/0!
B30: Source: Internal financials provided by Management & STOC analysis

Sheet QE Descriptions
A1: =Project&" - "&City&", "&State -> OPEN - OPEN, OPEN
A2: =MID(CELL("filename",A1),FIND("]",CELL("filename",A1))+1,255) -> QE Descriptions
A4: Overview: Reported EBITDA was calculated as net income plus interest expense, amortization, and depreciation expense. Management adjustments consist of the amounts presented in the LOI. Due diligence adjustments consist of various items considered to be one-time, non-recurring, inconsistent with GAAP, out-of-period, go-forward, or otherwise non-operating in nature. Pro forma adjustments relate to anticipated cost structure changes and views of certain financial conditions, as if they were present throughout the entire Historical Period. We analyzed the Company's financial records and held discussions with Management to understand the circumstances of each adjustment. Unless specifically noted, we corroborated these adjustments with detailed trial balance information and other supporting documentation.
A9: Adjustment | B9: Description
A10: =CONCATENATE('Lead QE'!C16,") ",'Lead QE'!B16) -> 1) [Input adjustment]
A11: =CONCATENATE('Lead QE'!C17,") ",'Lead QE'!B17) -> 2) [Input adjustment]
A12: =CONCATENATE('Lead QE'!C18,") ",'Lead QE'!B18) -> 3) [Input adjustment]
A13: =CONCATENATE('Lead QE'!C19,") ",'Lead QE'!B19) -> 4) [Input adjustment]
A14: =CONCATENATE('Lead QE'!C20,") ",'Lead QE'!B20) -> 5) [Input adjustment]
A15: =CONCATENATE('Lead QE'!C21,") ",'Lead QE'!B21) -> 6) [Input adjustment]
A16: =CONCATENATE('Lead QE'!C22,") ",'Lead QE'!B22) -> 7) [Input adjustment]
A17: =CONCATENATE('Lead QE'!C23,") ",'Lead QE'!B23) -> 8) [Input adjustment]
A18: =CONCATENATE('Lead QE'!C24,") ",'Lead QE'!B24) -> 9) [Input adjustment]
A19: =CONCATENATE('Lead QE'!C25,") ",'Lead QE'!B25) -> 10) [Input adjustment]

Sheet QE Detail - MGMT.
C1: =Project&" - "&City&", "&State -> OPEN - OPEN, OPEN
C2: =MID(CELL("filename",C1),FIND("]",CELL("filename",C1))+1,255) -> QE Detail - MGMT.
A4: PnL | B4: Recast PL Account Mapping | C4: =CONCATENATE('Lead QE'!C16,") ",'Lead QE'!B16) -> 1) [Input adjustment]
C5: In $000's | D5: =First_Reporting_Year -> 44926 | E5: =Second_Reporting_Year -> 45291 | F5: =Stub_Period -> 45565 | H5: =EOMONTH(D5,-11) -> 44592 | I5: =EOMONTH(H5,1) -> 44620 | J5: =EOMONTH(I5,1) -> 44651 | K5: =EOMONTH(J5,1) -> 44681 | L5: =EOMONTH(K5,1) -> 44712 | M5: =EOMONTH(L5,1) -> 44742 | N5: =EOMONTH(M5,1) -> 44773 | O5: =EOMONTH(N5,1) -> 44804 | P5: =EOMONTH(O5,1) -> 44834 | ... AN5: =EOMONTH(AM5,1) -> 45565
C16: EBITDA adjustment | D16: =D9+D15 -> 0 | E16: =E9+E15 -> 0 | F16: =F9+F15 -> 0 | H16: =H9+H15 -> 0 | I16: =I9+I15 -> 0 | J16: =J9+J15 -> 0 | K16: =K9+K15 -> 0 | L16: =L9+L15 -> 0 | M16: =M9+M15 -> 0 | N16: =N9+N15 -> 0 | O16: =O9+O15 -> 0 | ... AN16: =AN9+AN15 -> 0
C17: Source: Internal financials provided by Management & STOC analysis
C19: =CONCATENATE('Lead QE'!C17,") ",'Lead QE'!B17) -> 2) [Input adjustment]
C20: In $000's | D20: =First_Reporting_Year -> 44926 | E20: =Second_Reporting_Year -> 45291 | F20: =Stub_Period -> 45565 | H20: =EOMONTH(D20,-11) -> 44592 | I20: =EOMONTH(H20,1) -> 44620 | J20: =EOMONTH(I20,1) -> 44651 | K20: =EOMONTH(J20,1) -> 44681 | L20: =EOMONTH(K20,1) -> 44712 | M20: =EOMONTH(L20,1) -> 44742 | N20: =EOMONTH(M20,1) -> 44773 | O20: =EOMONTH(N20,1) -> 44804 | P20: =EOMONTH(O20,1) -> 44834 | ... AN20: =EOMONTH(AM20,1) -> 45565
B22: Other | C22: EBITDA adjustment | D22: =SUM(D21:D21) -> 0 | E22: =SUM(E21:E21) -> 0 | F22: =SUM(F21:F21) -> 0 | G22: =SUM(G21:G21) -> 0 | H22: =SUM(H21:H21) -> 0 | I22: =SUM(I21:I21) -> 0 | J22: =SUM(J21:J21) -> 0 | K22: =SUM(K21:K21) -> 0 | ... AN22: =SUM(AN21:AN21) -> 0
C23: Source: Internal financials provided by Management & STOC analysis
C25: =CONCATENATE('Lead QE'!C18,") ",'Lead QE'!B18) -> 3) [Input adjustment]
C26: In $000's | D26: =First_Reporting_Year -> 44926 | E26: =Second_Reporting_Year -> 45291 | F26: =Stub_Period -> 45565 | H26: =EOMONTH(D26,-11) -> 44592 | I26: =EOMONTH(H26,1) -> 44620 | J26: =EOMONTH(I26,1) -> 44651 | K26: =EOMONTH(J26,1) -> 44681 | L26: =EOMONTH(K26,1) -> 44712 | M26: =EOMONTH(L26,1) -> 44742 | N26: =EOMONTH(M26,1) -> 44773 | O26: =EOMONTH(N26,1) -> 44804 | P26: =EOMONTH(O26,1) -> 44834 | ... AN26: =EOMONTH(AM26,1) -> 45565
C36: Total go-forward [B] | D36: =SUM(D34:D35) -> 0 | E36: =SUM(E34:E35) -> 0 | F36: =SUM(F34:F35) -> 0 | H36: =SUM(H34:H35) -> 0 | I36: =SUM(I34:I35) -> 0 | J36: =SUM(J34:J35) -> 0 | K36: =SUM(K34:K35) -> 0 | L36: =SUM(L34:L35) -> 0 | M36: =SUM(M34:M35) -> 0 | N36: =SUM(N34:N35) -> 0 | O36: =SUM(O34:O35) -> 0 | ... AN36: =SUM(AN34:AN35) -> 0
C37: EBITDA adjustment [A] - [B] | D37: =D31-D36 -> 0 | E37: =E31-E36 -> 0 | F37: =F31-F36 -> 0 | G37: =G31-G36 -> 0 | H37: =H31-H36 -> 0 | I37: =I31-I36 -> 0 | J37: =J31-J36 -> 0 | K37: =K31-K36 -> 0 | ... AN37: =AN31-AN36 -> 0
C38: Source: Internal financials provided by Management & STOC analysis
B39: Insurance | C39: Insurance | D39: =SUMIFS($H39:$AN39,$H$5:$AN$5,">"&EOMONTH(D$5,-12),$H$5:$AN$5,"<="&D$5) -> 0 | E39: =SUMIFS($H39:$AN39,$H$5:$AN$5,">"&EOMONTH(E$5,-12),$H$5:$AN$5,"<="&E$5) -> 0 | F39: =SUMIFS($H39:$AQ39,$H$5:$AQ$5,">"&EOMONTH(F$5,-12),$H$5:$AQ$5,"<="&F$5) -> 0 | H39: =H29-H34 -> 0 | I39: =I29-I34 -> 0 | J39: =J29-J34 -> 0 | K39: =K29-K34 -> 0 | L39: =L29-L34 -> 0 | M39: =M29-M34 -> 0 | N39: =N29-N34 -> 0 | O39: =O29-O34 -> 0 | ... AN39: =AN29-AN34 -> 0
B40: Employee 401(k) | C40: Employee 401(k) | D40: =SUMIFS($H40:$AN40,$H$5:$AN$5,">"&EOMONTH(D$5,-12),$H$5:$AN$5,"<="&D$5) -> 0 | E40: =SUMIFS($H40:$AN40,$H$5:$AN$5,">"&EOMONTH(E$5,-12),$H$5:$AN$5,"<="&E$5) -> 0 | F40: =SUMIFS($H40:$AQ40,$H$5:$AQ$5,">"&EOMONTH(F$5,-12),$H$5:$AQ$5,"<="&F$5) -> 0 | H40: =H30-H35 -> 0 | I40: =I30-I35 -> 0 | J40: =J30-J35 -> 0 | K40: =K30-K35 -> 0 | L40: =L30-L35 -> 0 | M40: =M30-M35 -> 0 | N40: =N30-N35 -> 0 | O40: =O30-O35 -> 0 | ... AN40: =AN30-AN35 -> 0
C42: =CONCATENATE('Lead QE'!C19,") ",'Lead QE'!B19) -> 4) [Input adjustment]
C43: In $000's | D43: =First_Reporting_Year -> 44926 | E43: =Second_Reporting_Year -> 45291 | F43: =Stub_Period -> 45565 | H43: =EOMONTH(D43,-11) -> 44592 | I43: =EOMONTH(H43,1) -> 44620 | J43: =EOMONTH(I43,1) -> 44651 | K43: =EOMONTH(J43,1) -> 44681 | L43: =EOMONTH(K43,1) -> 44712 | M43: =EOMONTH(L43,1) -> 44742 | N43: =EOMONTH(M43,1) -> 44773 | O43: =EOMONTH(N43,1) -> 44804 | P43: =EOMONTH(O43,1) -> 44834 | ... AN43: =EOMONTH(AM43,1) -> 45565
D44: =SUMIFS($H44:$AN44,$H$5:$AN$5,">"&EOMONTH(D$5,-12),$H$5:$AN$5,"<="&D$5) -> 0 | E44: =SUMIFS($H44:$AN44,$H$5:$AN$5,">"&EOMONTH(E$5,-12),$H$5:$AN$5,"<="&E$5) -> 0 | F44: =SUMIFS($H44:$AQ44,$H$5:$AQ$5,">"&EOMONTH(F$5,-12),$H$5:$AQ$5,"<="&F$5) -> 0
D45: =SUMIFS($H45:$AN45,$H$5:$AN$5,">"&EOMONTH(D$5,-12),$H$5:$AN$5,"<="&D$5) -> 0 | E45: =SUMIFS($H45:$AN45,$H$5:$AN$5,">"&EOMONTH(E$5,-12),$H$5:$AN$5,"<="&E$5) -> 0 | F45: =SUMIFS($H45:$AQ45,$H$5:$AQ$5,">"&EOMONTH(F$5,-12),$H$5:$AQ$5,"<="&F$5) -> 0
B46: Other | C46: EBITDA adjustment | D46: =SUM(D44:D45) -> 0 | E46: =SUM(E44:E45) -> 0 | F46: =SUM(F44:F45) -> 0 | H46: =SUM(H44:H45) -> 0 | I46: =SUM(I44:I45) -> 0 | J46: =SUM(J44:J45) -> 0 | K46: =SUM(K44:K45) -> 0 | L46: =SUM(L44:L45) -> 0 | M46: =SUM(M44:M45) -> 0 | N46: =SUM(N44:N45) -> 0 | O46: =SUM(O44:O45) -> 0 | ... AN46: =SUM(AN44:AN45) -> 0
C47: Source: Internal financials provided by Management & STOC analysis
C49: =CONCATENATE('Lead QE'!C20,") ",'Lead QE'!B20) -> 5) [Input adjustment]
C50: In $000's | D50: =First_Reporting_Year -> 44926 | E50: =Second_Reporting_Year -> 45291 | F50: =Stub_Period -> 45565 | H50: =EOMONTH(D50,-11) -> 44592 | I50: =EOMONTH(H50,1) -> 44620 | J50: =EOMONTH(I50,1) -> 44651 | K50: =EOMONTH(J50,1) -> 44681 | L50: =EOMONTH(K50,1) -> 44712 | M50: =EOMONTH(L50,1) -> 44742 | N50: =EOMONTH(M50,1) -> 44773 | O50: =EOMONTH(N50,1) -> 44804 | P50: =EOMONTH(O50,1) -> 44834 | ... AN50: =EOMONTH(AM50,1) -> 45565
A51: Meals and Entertainment | B51: Other | D51: =SUMIFS($H51:$AN51,$H$5:$AN$5,">"&EOMONTH(D$5,-12),$H$5:$AN$5,"<="&D$5) -> 0 | E51: =SUMIFS($H51:$AN51,$H$5:$AN$5,">"&EOMONTH(E$5,-12),$H$5:$AN$5,"<="&E$5) -> 0 | F51: =SUMIFS($H51:$AQ51,$H$5:$AQ$5,">"&EOMONTH(F$5,-12),$H$5:$AQ$5,"<="&F$5) -> 0
B52: Other | D52: =SUMIFS($H52:$AN52,$H$5:$AN$5,">"&EOMONTH(D$5,-12),$H$5:$AN$5,"<="&D$5) -> 0 | E52: =SUMIFS($H52:$AN52,$H$5:$AN$5,">"&EOMONTH(E$5,-12),$H$5:$AN$5,"<="&E$5) -> 0 | F52: =SUMIFS($H52:$AQ52,$H$5:$AQ$5,">"&EOMONTH(F$5,-12),$H$5:$AQ$5,"<="&F$5) -> 0
B53: Other | D53: =SUMIFS($H53:$AN53,$H$5:$AN$5,">"&EOMONTH(D$5,-12),$H$5:$AN$5,"<="&D$5) -> 0 | E53: =SUMIFS($H53:$AN53,$H$5:$AN$5,">"&EOMONTH(E$5,-12),$H$5:$AN$5,"<="&E$5) -> 0 | F53: =SUMIFS($H53:$AQ53,$H$5:$AQ$5,">"&EOMONTH(F$5,-12),$H$5:$AQ$5,"<="&F$5) -> 0
B54: Other | D54: =SUMIFS($H54:$AN54,$H$5:$AN$5,">"&EOMONTH(D$5,-12),$H$5:$AN$5,"<="&D$5) -> 0 | E54: =SUMIFS($H54:$AN54,$H$5:$AN$5,">"&EOMONTH(E$5,-12),$H$5:$AN$5,"<="&E$5) -> 0 | F54: =SUMIFS($H54:$AQ54,$H$5:$AQ$5,">"&EOMONTH(F$5,-12),$H$5:$AQ$5,"<="&F$5) -> 0
B55: Other | D55: =SUMIFS($H55:$AN55,$H$5:$AN$5,">"&EOMONTH(D$5,-12),$H$5:$AN$5,"<="&D$5) -> 0 | E55: =SUMIFS($H55:$AN55,$H$5:$AN$5,">"&EOMONTH(E$5,-12),$H$5:$AN$5,"<="&E$5) -> 0 | F55: =SUMIFS($H55:$AQ55,$H$5:$AQ$5,">"&EOMONTH(F$5,-12),$H$5:$AQ$5,"<="&F$5) -> 0
B56: Other | D56: =SUMIFS($H56:$AN56,$H$5:$AN$5,">"&EOMONTH(D$5,-12),$H$5:$AN$5,"<="&D$5) -> 0 | E56: =SUMIFS($H56:$AN56,$H$5:$AN$5,">"&EOMONTH(E$5,-12),$H$5:$AN$5,"<="&E$5) -> 0 | F56: =SUMIFS($H56:$AQ56,$H$5:$AQ$5,">"&EOMONTH(F$5,-12),$H$5:$AQ$5,"<="&F$5) -> 0
C57: EBITDA adjustment [A] + [B] | D57: =SUM(D51:D56) -> 0 | E57: =SUM(E51:E56) -> 0 | F57: =SUM(F51:F56) -> 0 | H57: =SUM(H51:H56) -> 0 | I57: =SUM(I51:I56) -> 0 | J57: =SUM(J51:J56) -> 0 | K57: =SUM(K51:K56) -> 0 | L57: =SUM(L51:L56) -> 0 | M57: =SUM(M51:M56) -> 0 | N57: =SUM(N51:N56) -> 0 | O57: =SUM(O51:O56) -> 0 | ... AN57: =SUM(AN51:AN56) -> 0
C58: Source: Internal financials provided by Management & STOC analysis
C60: =CONCATENATE('Lead QE'!C21,") ",'Lead QE'!B21) -> 6) [Input adjustment]
C61: In $000's | D61: =First_Reporting_Year -> 44926 | E61: =Second_Reporting_Year -> 45291 | F61: =Stub_Period -> 45565 | H61: =EOMONTH(D61,-11) -> 44592 | I61: =EOMONTH(H61,1) -> 44620 | J61: =EOMONTH(I61,1) -> 44651 | K61: =EOMONTH(J61,1) -> 44681 | L61: =EOMONTH(K61,1) -> 44712 | M61: =EOMONTH(L61,1) -> 44742 | N61: =EOMONTH(M61,1) -> 44773 | O61: =EOMONTH(N61,1) -> 44804 | P61: =EOMONTH(O61,1) -> 44834 | ... AN61: =EOMONTH(AM61,1) -> 45565
B64: Payroll taxes | C64: EBITDA adjustment | D64: =SUM(D62:D63) -> 0 | E64: =SUM(E62:E63) -> 0 | F64: =SUM(F62:F63) -> 0 | G64: =SUM(G62:G63) -> 0 | H64: =SUM(H62:H63) -> 0 | I64: =SUM(I62:I63) -> 0 | J64: =SUM(J62:J63) -> 0 | K64: =SUM(K62:K63) -> 0 | ... AN64: =SUM(AN62:AN63) -> 0
C65: Source: Internal financials provided by Management & STOC analysis
C67: =CONCATENATE('Lead QE'!C22,") ",'Lead QE'!B22) -> 7) [Input adjustment]
C68: In $000's | D68: =First_Reporting_Year -> 44926 | E68: =Second_Reporting_Year -> 45291 | F68: =Stub_Period -> 45565 | H68: =EOMONTH(D68,-11) -> 44592 | I68: =EOMONTH(H68,1) -> 44620 | J68: =EOMONTH(I68,1) -> 44651 | K68: =EOMONTH(J68,1) -> 44681 | L68: =EOMONTH(K68,1) -> 44712 | M68: =EOMONTH(L68,1) -> 44742 | N68: =EOMONTH(M68,1) -> 44773 | O68: =EOMONTH(N68,1) -> 44804 | P68: =EOMONTH(O68,1) -> 44834 | ... AN68: =EOMONTH(AM68,1) -> 45565
D69: =SUMIFS($H69:$AN69,$H$5:$AN$5,">"&EOMONTH(D$5,-12),$H$5:$AN$5,"<="&D$5) -> 0 | E69: =SUMIFS($H69:$AN69,$H$5:$AN$5,">"&EOMONTH(E$5,-12),$H$5:$AN$5,"<="&E$5) -> 0 | F69: =SUMIFS($H69:$AQ69,$H$5:$AQ$5,">"&EOMONTH(F$5,-12),$H$5:$AQ$5,"<="&F$5) -> 0
B70: Other | C70: EBITDA adjustment [A] + [B] | D70: =SUM(D69:D69) -> 0 | E70: =SUM(E69:E69) -> 0 | F70: =SUM(F69:F69) -> 0 | H70: =SUM(H69:H69) -> 0 | I70: =SUM(I69:I69) -> 0 | J70: =SUM(J69:J69) -> 0 | K70: =SUM(K69:K69) -> 0 | L70: =SUM(L69:L69) -> 0 | M70: =SUM(M69:M69) -> 0 | N70: =SUM(N69:N69) -> 0 | O70: =SUM(O69:O69) -> 0 | ... AN70: =SUM(AN69:AN69) -> 0
C71: Source: Internal financials provided by Management & STOC analysis
C73: =CONCATENATE('Lead QE'!C23,") ",'Lead QE'!B23) -> 8) [Input adjustment]
C74: In $000's | D74: =First_Reporting_Year -> 44926 | E74: =Second_Reporting_Year -> 45291 | F74: =Stub_Period -> 45565 | H74: =EOMONTH(D74,-11) -> 44592 | I74: =EOMONTH(H74,1) -> 44620 | J74: =EOMONTH(I74,1) -> 44651 | K74: =EOMONTH(J74,1) -> 44681 | L74: =EOMONTH(K74,1) -> 44712 | M74: =EOMONTH(L74,1) -> 44742 | N74: =EOMONTH(M74,1) -> 44773 | O74: =EOMONTH(N74,1) -> 44804 | P74: =EOMONTH(O74,1) -> 44834 | ... AN74: =EOMONTH(AM74,1) -> 45565
C77: EBITDA adjustment [A] + [B] | D77: =SUM(D75:D76) -> 0 | E77: =SUM(E75:E76) -> 0 | F77: =SUM(F75:F76) -> 0 | G77: =SUM(G75:G76) -> 0 | H77: =SUM(H75:H76) -> 0 | I77: =SUM(I75:I76) -> 0 | J77: =SUM(J75:J76) -> 0 | K77: =SUM(K75:K76) -> 0 | ... AN77: =SUM(AN75:AN76) -> 0
C78: Source: Internal financials provided by Management & STOC analysis
C80: =CONCATENATE('Lead QE'!C24,") ",'Lead QE'!B24) -> 9) [Input adjustment]
C81: In $000's | D81: =First_Reporting_Year -> 44926 | E81: =Second_Reporting_Year -> 45291 | F81: =Stub_Period -> 45565 | H81: =EOMONTH(D81,-11) -> 44592 | I81: =EOMONTH(H81,1) -> 44620 | J81: =EOMONTH(I81,1) -> 44651 | K81: =EOMONTH(J81,1) -> 44681 | L81: =EOMONTH(K81,1) -> 44712 | M81: =EOMONTH(L81,1) -> 44742 | N81: =EOMONTH(M81,1) -> 44773 | O81: =EOMONTH(N81,1) -> 44804 | P81: =EOMONTH(O81,1) -> 44834 | ... AN81: =EOMONTH(AM81,1) -> 45565
C83: EBITDA adjustment [A] + [B] | D83: =SUM(D82:D82) -> 0 | E83: =SUM(E82:E82) -> 0 | F83: =SUM(F82:F82) -> 0 | G83: =SUM(G82:G82) -> 0 | H83: =SUM(H82:H82) -> 0 | I83: =SUM(I82:I82) -> 0 | J83: =SUM(J82:J82) -> 0 | K83: =SUM(K82:K82) -> 0 | ... AN83: =SUM(AN82:AN82) -> 0
C84: Source: Internal financials provided by Management & STOC analysis
C86: =CONCATENATE('Lead QE'!C25,") ",'Lead QE'!B25) -> 10) [Input adjustment]
C87: In $000's | D87: =First_Reporting_Year -> 44926 | E87: =Second_Reporting_Year -> 45291 | F87: =Stub_Period -> 45565 | H87: =EOMONTH(D87,-11) -> 44592 | I87: =EOMONTH(H87,1) -> 44620 | J87: =EOMONTH(I87,1) -> 44651 | K87: =EOMONTH(J87,1) -> 44681 | L87: =EOMONTH(K87,1) -> 44712 | M87: =EOMONTH(L87,1) -> 44742 | N87: =EOMONTH(M87,1) -> 44773 | O87: =EOMONTH(N87,1) -> 44804 | P87: =EOMONTH(O87,1) -> 44834 | ... AN87: =EOMONTH(AM87,1) -> 45565
D88: =SUMIFS($H88:$AN88,$H$5:$AN$5,">"&EOMONTH(D$5,-12),$H$5:$AN$5,"<="&D$5) -> 0 | E88: =SUMIFS($H88:$AN88,$H$5:$AN$5,">"&EOMONTH(E$5,-12),$H$5:$AN$5,"<="&E$5) -> 0 | F88: =SUMIFS($H88:$AQ88,$H$5:$AQ$5,">"&EOMONTH(F$5,-12),$H$5:$AQ$5,"<="&F$5) -> 0
D89: =SUMIFS($H89:$AN89,$H$5:$AN$5,">"&EOMONTH(D$5,-12),$H$5:$AN$5,"<="&D$5) -> 0 | E89: =SUMIFS($H89:$AN89,$H$5:$AN$5,">"&EOMONTH(E$5,-12),$H$5:$AN$5,"<="&E$5) -> 0 | F89: =SUMIFS($H89:$AQ89,$H$5:$AQ$5,">"&EOMONTH(F$5,-12),$H$5:$AQ$5,"<="&F$5) -> 0
D90: =SUMIFS($H90:$AN90,$H$5:$AN$5,">"&EOMONTH(D$5,-12),$H$5:$AN$5,"<="&D$5) -> 0 | E90: =SUMIFS($H90:$AN90,$H$5:$AN$5,">"&EOMONTH(E$5,-12),$H$5:$AN$5,"<="&E$5) -> 0 | F90: =SUMIFS($H90:$AQ90,$H$5:$AQ$5,">"&EOMONTH(F$5,-12),$H$5:$AQ$5,"<="&F$5) -> 0
B91: Other | C91: EBITDA adjustment [A] + [B] | D91: =SUM(D88:D90) -> 0 | E91: =SUM(E88:E90) -> 0 | F91: =SUM(F88:F90) -> 0 | G91: =SUM(G88:G90) -> 0 | H91: =SUM(H88:H90) -> 0 | I91: =SUM(I88:I90) -> 0 | J91: =SUM(J88:J90) -> 0 | K91: =SUM(K88:K90) -> 0 | ... AN91: =SUM(AN88:AN90) -> 0
C92: Source: Internal financials provided by Management & STOC analysis

Sheet Recast PLs >>>
A10: =RIGHT(CELL("filename",A1),LEN(CELL("filename",A1))-FIND("]",CELL("filename",A1))) -> Recast PLs >>>

Sheet Recast Reported
B1: =Project&" - "&City&", "&State -> OPEN - OPEN, OPEN
B2: =MID(CELL("filename",B1),FIND("]",CELL("filename",B1))+1,255) -> Recast Reported
A4: Recast PL | B4: Summarized Reported P&L
B5: In $000's | C5: =First_Reporting_Year -> 44926 | D5: =Second_Reporting_Year -> 45291 | E5: =Stub_Period -> 45565 | G5: =EOMONTH(C5,-11) -> 44592 | H5: =EOMONTH(G5,1) -> 44620 | I5: =EOMONTH(H5,1) -> 44651 | J5: =EOMONTH(I5,1) -> 44681 | K5: =EOMONTH(J5,1) -> 44712 | L5: =EOMONTH(K5,1) -> 44742 | M5: =EOMONTH(L5,1) -> 44773 | N5: =EOMONTH(M5,1) -> 44804 | O5: =EOMONTH(N5,1) -> 44834 | ... AM5: =EOMONTH(AL5,1) -> 45565
A6: Revenue, net | B6: Revenue, net | C6: =SUMIFS($G6:$BC6,$G$5:$BC$5,"<="&EOMONTH(C$5,0),$G$6:$BC$6,"<="&C$5) -> 0 | D6: =SUMIFS($G6:$AT6,$G$5:$AT$5,">"&EOMONTH(D$5,-12),$G$5:$AT$5,"<="&D$5) -> 0 | E6: =SUMIFS($G6:$AT6,$G$5:$AT$5,">"&EOMONTH(E$5,-12),$G$5:$AT$5,"<="&E$5) -> 0 | G6: =SUMIFS(PL!L:L,PL!$B:$B,$B6) -> 0 | H6: =SUMIFS(PL!M:M,PL!$B:$B,$B6) -> 0 | I6: =SUMIFS(PL!N:N,PL!$B:$B,$B6) -> 0 | J6: =SUMIFS(PL!O:O,PL!$B:$B,$B6) -> 0 | K6: =SUMIFS(PL!P:P,PL!$B:$B,$B6) -> 0 | L6: =SUMIFS(PL!Q:Q,PL!$B:$B,$B6) -> 0 | M6: =SUMIFS(PL!R:R,PL!$B:$B,$B6) -> 0 | N6: =SUMIFS(PL!S:S,PL!$B:$B,$B6) -> 0 | O6: =SUMIFS(PL!T:T,PL!$B:$B,$B6) -> 0 | P6: =SUMIFS(PL!U:U,PL!$B:$B,$B6) -> 0 | Q6: =SUMIFS(PL!V:V,PL!$B:$B,$B6) -> 0 | R6: =SUMIFS(PL!W:W,PL!$B:$B,$B6) -> 0 | S6: =SUMIFS(PL!X:X,PL!$B:$B,$B6) -> 0 | T6: =SUMIFS(PL!Y:Y,PL!$B:$B,$B6) -> 0 | U6: =SUMIFS(PL!Z:Z,PL!$B:$B,$B6) -> 0 | V6: =SUMIFS(PL!AA:AA,PL!$B:$B,$B6) -> 0 | W6: =SUMIFS(PL!AB:AB,PL!$B:$B,$B6) -> 0 | X6: =SUMIFS(PL!AC:AC,PL!$B:$B,$B6) -> 0 | Y6: =SUMIFS(PL!AD:AD,PL!$B:$B,$B6) -> 0 | Z6: =SUMIFS(PL!AE:AE,PL!$B:$B,$B6) -> 0 | AA6: =SUMIFS(PL!AF:AF,PL!$B:$B,$B6) -> 0 | AB6: =SUMIFS(PL!AG:AG,PL!$B:$B,$B6) -> 0 | AC6: =SUMIFS(PL!AH:AH,PL!$B:$B,$B6) -> 0 | AD6: =SUMIFS(PL!AI:AI,PL!$B:$B,$B6) -> 0 | AE6: =SUMIFS(PL!AJ:AJ,PL!$B:$B,$B6) -> 0 | AF6: =SUMIFS(PL!AK:AK,PL!$B:$B,$B6) -> 0 | AG6: =SUMIFS(PL!AL:AL,PL!$B:$B,$B6) -> 0 | AH6: =SUMIFS(PL!AM:AM,PL!$B:$B,$B6) -> 0 | AI6: =SUMIFS(PL!AN:AN,PL!$B:$B,$B6) -> 0 | AJ6: =SUMIFS(PL!AS:AS,PL!$B:$B,$B6) -> 0 | AK6: =SUMIFS(PL!AT:AT,PL!$B:$B,$B6) -> 0 | AL6: =SUMIFS(PL!AU:AU,PL!$B:$B,$B6) -> 0 | AM6: =SUMIFS(PL!AV:AV,PL!$B:$B,$B6) -> 0
A7: Dental supplies | B7: Dental supplies | C7: =SUMIFS($G7:$BC7,$G$5:$BC$5,"<="&EOMONTH(C$5,0),$G$6:$BC$6,"<="&C$5) -> 0 | D7: =SUMIFS($G7:$AT7,$G$5:$AT$5,">"&EOMONTH(D$5,-12),$G$5:$AT$5,"<="&D$5) -> 0 | E7: =SUMIFS($G7:$AT7,$G$5:$AT$5,">"&EOMONTH(E$5,-12),$G$5:$AT$5,"<="&E$5) -> 0 | G7: =SUMIFS(PL!L:L,PL!$B:$B,$B7) -> 0 | H7: =SUMIFS(PL!M:M,PL!$B:$B,$B7) -> 0 | I7: =SUMIFS(PL!N:N,PL!$B:$B,$B7) -> 0 | J7: =SUMIFS(PL!O:O,PL!$B:$B,$B7) -> 0 | K7: =SUMIFS(PL!P:P,PL!$B:$B,$B7) -> 0 | L7: =SUMIFS(PL!Q:Q,PL!$B:$B,$B7) -> 0 | M7: =SUMIFS(PL!R:R,PL!$B:$B,$B7) -> 0 | N7: =SUMIFS(PL!S:S,PL!$B:$B,$B7) -> 0 | O7: =SUMIFS(PL!T:T,PL!$B:$B,$B7) -> 0 | P7: =SUMIFS(PL!U:U,PL!$B:$B,$B7) -> 0 | Q7: =SUMIFS(PL!V:V,PL!$B:$B,$B7) -> 0 | R7: =SUMIFS(PL!W:W,PL!$B:$B,$B7) -> 0 | S7: =SUMIFS(PL!X:X,PL!$B:$B,$B7) -> 0 | T7: =SUMIFS(PL!Y:Y,PL!$B:$B,$B7) -> 0 | U7: =SUMIFS(PL!Z:Z,PL!$B:$B,$B7) -> 0 | V7: =SUMIFS(PL!AA:AA,PL!$B:$B,$B7) -> 0 | W7: =SUMIFS(PL!AB:AB,PL!$B:$B,$B7) -> 0 | X7: =SUMIFS(PL!AC:AC,PL!$B:$B,$B7) -> 0 | Y7: =SUMIFS(PL!AD:AD,PL!$B:$B,$B7) -> 0 | Z7: =SUMIFS(PL!AE:AE,PL!$B:$B,$B7) -> 0 | AA7: =SUMIFS(PL!AF:AF,PL!$B:$B,$B7) -> 0 | AB7: =SUMIFS(PL!AG:AG,PL!$B:$B,$B7) -> 0 | AC7: =SUMIFS(PL!AH:AH,PL!$B:$B,$B7) -> 0 | AD7: =SUMIFS(PL!AI:AI,PL!$B:$B,$B7) -> 0 | AE7: =SUMIFS(PL!AJ:AJ,PL!$B:$B,$B7) -> 0 | AF7: =SUMIFS(PL!AK:AK,PL!$B:$B,$B7) -> 0 | AG7: =SUMIFS(PL!AL:AL,PL!$B:$B,$B7) -> 0 | AH7: =SUMIFS(PL!AM:AM,PL!$B:$B,$B7) -> 0 | AI7: =SUMIFS(PL!AN:AN,PL!$B:$B,$B7) -> 0 | AJ7: =SUMIFS(PL!AS:AS,PL!$B:$B,$B7) -> 0 | AK7: =SUMIFS(PL!AT:AT,PL!$B:$B,$B7) -> 0 | AL7: =SUMIFS(PL!AU:AU,PL!$B:$B,$B7) -> 0 | AM7: =SUMIFS(PL!AV:AV,PL!$B:$B,$B7) -> 0
A8: Ortho supplies | B8: Ortho supplies | C8: =SUMIFS($G8:$BC8,$G$5:$BC$5,"<="&EOMONTH(C$5,0),$G$6:$BC$6,"<="&C$5) -> 0 | D8: =SUMIFS($G8:$AT8,$G$5:$AT$5,">"&EOMONTH(D$5,-12),$G$5:$AT$5,"<="&D$5) -> 0 | E8: =SUMIFS($G8:$AT8,$G$5:$AT$5,">"&EOMONTH(E$5,-12),$G$5:$AT$5,"<="&E$5) -> 0 | G8: =SUMIFS(PL!L:L,PL!$B:$B,$B8) -> 0 | H8: =SUMIFS(PL!M:M,PL!$B:$B,$B8) -> 0 | I8: =SUMIFS(PL!N:N,PL!$B:$B,$B8) -> 0 | J8: =SUMIFS(PL!O:O,PL!$B:$B,$B8) -> 0 | K8: =SUMIFS(PL!P:P,PL!$B:$B,$B8) -> 0 | L8: =SUMIFS(PL!Q:Q,PL!$B:$B,$B8) -> 0 | M8: =SUMIFS(PL!R:R,PL!$B:$B,$B8) -> 0 | N8: =SUMIFS(PL!S:S,PL!$B:$B,$B8) -> 0 | O8: =SUMIFS(PL!T:T,PL!$B:$B,$B8) -> 0 | P8: =SUMIFS(PL!U:U,PL!$B:$B,$B8) -> 0 | Q8: =SUMIFS(PL!V:V,PL!$B:$B,$B8) -> 0 | R8: =SUMIFS(PL!W:W,PL!$B:$B,$B8) -> 0 | S8: =SUMIFS(PL!X:X,PL!$B:$B,$B8) -> 0 | T8: =SUMIFS(PL!Y:Y,PL!$B:$B,$B8) -> 0 | U8: =SUMIFS(PL!Z:Z,PL!$B:$B,$B8) -> 0 | V8: =SUMIFS(PL!AA:AA,PL!$B:$B,$B8) -> 0 | W8: =SUMIFS(PL!AB:AB,PL!$B:$B,$B8) -> 0 | X8: =SUMIFS(PL!AC:AC,PL!$B:$B,$B8) -> 0 | Y8: =SUMIFS(PL!AD:AD,PL!$B:$B,$B8) -> 0 | Z8: =SUMIFS(PL!AE:AE,PL!$B:$B,$B8) -> 0 | AA8: =SUMIFS(PL!AF:AF,PL!$B:$B,$B8) -> 0 | AB8: =SUMIFS(PL!AG:AG,PL!$B:$B,$B8) -> 0 | AC8: =SUMIFS(PL!AH:AH,PL!$B:$B,$B8) -> 0 | AD8: =SUMIFS(PL!AI:AI,PL!$B:$B,$B8) -> 0 | AE8: =SUMIFS(PL!AJ:AJ,PL!$B:$B,$B8) -> 0 | AF8: =SUMIFS(PL!AK:AK,PL!$B:$B,$B8) -> 0 | AG8: =SUMIFS(PL!AL:AL,PL!$B:$B,$B8) -> 0 | AH8: =SUMIFS(PL!AM:AM,PL!$B:$B,$B8) -> 0 | AI8: =SUMIFS(PL!AN:AN,PL!$B:$B,$B8) -> 0 | AJ8: =SUMIFS(PL!AS:AS,PL!$B:$B,$B8) -> 0 | AK8: =SUMIFS(PL!AT:AT,PL!$B:$B,$B8) -> 0 | AL8: =SUMIFS(PL!AU:AU,PL!$B:$B,$B8) -> 0 | AM8: =SUMIFS(PL!AV:AV,PL!$B:$B,$B8) -> 0
A9: Lab fees | B9: Lab fees | C9: =SUMIFS($G9:$BC9,$G$5:$BC$5,"<="&EOMONTH(C$5,0),$G$6:$BC$6,"<="&C$5) -> 0 | D9: =SUMIFS($G9:$AT9,$G$5:$AT$5,">"&EOMONTH(D$5,-12),$G$5:$AT$5,"<="&D$5) -> 0 | E9: =SUMIFS($G9:$AT9,$G$5:$AT$5,">"&EOMONTH(E$5,-12),$G$5:$AT$5,"<="&E$5) -> 0 | G9: =SUMIFS(PL!L:L,PL!$B:$B,$B9) -> 0 | H9: =SUMIFS(PL!M:M,PL!$B:$B,$B9) -> 0 | I9: =SUMIFS(PL!N:N,PL!$B:$B,$B9) -> 0 | J9: =SUMIFS(PL!O:O,PL!$B:$B,$B9) -> 0 | K9: =SUMIFS(PL!P:P,PL!$B:$B,$B9) -> 0 | L9: =SUMIFS(PL!Q:Q,PL!$B:$B,$B9) -> 0 | M9: =SUMIFS(PL!R:R,PL!$B:$B,$B9) -> 0 | N9: =SUMIFS(PL!S:S,PL!$B:$B,$B9) -> 0 | O9: =SUMIFS(PL!T:T,PL!$B:$B,$B9) -> 0 | P9: =SUMIFS(PL!U:U,PL!$B:$B,$B9) -> 0 | Q9: =SUMIFS(PL!V:V,PL!$B:$B,$B9) -> 0 | R9: =SUMIFS(PL!W:W,PL!$B:$B,$B9) -> 0 | S9: =SUMIFS(PL!X:X,PL!$B:$B,$B9) -> 0 | T9: =SUMIFS(PL!Y:Y,PL!$B:$B,$B9) -> 0 | U9: =SUMIFS(PL!Z:Z,PL!$B:$B,$B9) -> 0 | V9: =SUMIFS(PL!AA:AA,PL!$B:$B,$B9) -> 0 | W9: =SUMIFS(PL!AB:AB,PL!$B:$B,$B9) -> 0 | X9: =SUMIFS(PL!AC:AC,PL!$B:$B,$B9) -> 0 | Y9: =SUMIFS(PL!AD:AD,PL!$B:$B,$B9) -> 0 | Z9: =SUMIFS(PL!AE:AE,PL!$B:$B,$B9) -> 0 | AA9: =SUMIFS(PL!AF:AF,PL!$B:$B,$B9) -> 0 | AB9: =SUMIFS(PL!AG:AG,PL!$B:$B,$B9) -> 0 | AC9: =SUMIFS(PL!AH:AH,PL!$B:$B,$B9) -> 0 | AD9: =SUMIFS(PL!AI:AI,PL!$B:$B,$B9) -> 0 | AE9: =SUMIFS(PL!AJ:AJ,PL!$B:$B,$B9) -> 0 | AF9: =SUMIFS(PL!AK:AK,PL!$B:$B,$B9) -> 0 | AG9: =SUMIFS(PL!AL:AL,PL!$B:$B,$B9) -> 0 | AH9: =SUMIFS(PL!AM:AM,PL!$B:$B,$B9) -> 0 | AI9: =SUMIFS(PL!AN:AN,PL!$B:$B,$B9) -> 0 | AJ9: =SUMIFS(PL!AS:AS,PL!$B:$B,$B9) -> 0 | AK9: =SUMIFS(PL!AT:AT,PL!$B:$B,$B9) -> 0 | AL9: =SUMIFS(PL!AU:AU,PL!$B:$B,$B9) -> 0 | AM9: =SUMIFS(PL!AV:AV,PL!$B:$B,$B9) -> 0
B10: Cost of goods sold | C10: =SUM(C7:C9) -> 0 | D10: =SUM(D7:D9) -> 0 | E10: =SUM(E7:E9) -> 0 | G10: =SUM(G7:G9) -> 0 | H10: =SUM(H7:H9) -> 0 | I10: =SUM(I7:I9) -> 0 | J10: =SUM(J7:J9) -> 0 | K10: =SUM(K7:K9) -> 0 | L10: =SUM(L7:L9) -> 0 | M10: =SUM(M7:M9) -> 0 | N10: =SUM(N7:N9) -> 0 | ... AM10: =SUM(AM7:AM9) -> 0
B11: Gross profit | C11: =C6-SUM(C7:C9) -> 0 | D11: =D6-SUM(D7:D9) -> 0 | E11: =E6-SUM(E7:E9) -> 0 | G11: =G6-SUM(G7:G9) -> 0 | H11: =H6-SUM(H7:H9) -> 0 | I11: =I6-SUM(I7:I9) -> 0 | J11: =J6-SUM(J7:J9) -> 0 | K11: =K6-SUM(K7:K9) -> 0 | L11: =L6-SUM(L7:L9) -> 0 | M11: =M6-SUM(M7:M9) -> 0 | N11: =N6-SUM(N7:N9) -> 0 | ... AM11: =AM6-SUM(AM7:AM9) -> 0
A13: Doctor wages | B13: Doctor wages | C13: =SUMIFS($G13:$BC13,$G$5:$BC$5,"<="&EOMONTH(C$5,0),$G$6:$BC$6,"<="&C$5) -> 0 | D13: =SUMIFS($G13:$AT13,$G$5:$AT$5,">"&EOMONTH(D$5,-12),$G$5:$AT$5,"<="&D$5) -> 0 | E13: =SUMIFS($G13:$AT13,$G$5:$AT$5,">"&EOMONTH(E$5,-12),$G$5:$AT$5,"<="&E$5) -> 0 | G13: =SUMIFS(PL!L:L,PL!$B:$B,$B13) -> 0 | H13: =SUMIFS(PL!M:M,PL!$B:$B,$B13) -> 0 | I13: =SUMIFS(PL!N:N,PL!$B:$B,$B13) -> 0 | J13: =SUMIFS(PL!O:O,PL!$B:$B,$B13) -> 0 | K13: =SUMIFS(PL!P:P,PL!$B:$B,$B13) -> 0 | L13: =SUMIFS(PL!Q:Q,PL!$B:$B,$B13) -> 0 | M13: =SUMIFS(PL!R:R,PL!$B:$B,$B13) -> 0 | N13: =SUMIFS(PL!S:S,PL!$B:$B,$B13) -> 0 | O13: =SUMIFS(PL!T:T,PL!$B:$B,$B13) -> 0 | P13: =SUMIFS(PL!U:U,PL!$B:$B,$B13) -> 0 | Q13: =SUMIFS(PL!V:V,PL!$B:$B,$B13) -> 0 | R13: =SUMIFS(PL!W:W,PL!$B:$B,$B13) -> 0 | S13: =SUMIFS(PL!X:X,PL!$B:$B,$B13) -> 0 | T13: =SUMIFS(PL!Y:Y,PL!$B:$B,$B13) -> 0 | U13: =SUMIFS(PL!Z:Z,PL!$B:$B,$B13) -> 0 | V13: =SUMIFS(PL!AA:AA,PL!$B:$B,$B13) -> 0 | W13: =SUMIFS(PL!AB:AB,PL!$B:$B,$B13) -> 0 | X13: =SUMIFS(PL!AC:AC,PL!$B:$B,$B13) -> 0 | Y13: =SUMIFS(PL!AD:AD,PL!$B:$B,$B13) -> 0 | Z13: =SUMIFS(PL!AE:AE,PL!$B:$B,$B13) -> 0 | AA13: =SUMIFS(PL!AF:AF,PL!$B:$B,$B13) -> 0 | AB13: =SUMIFS(PL!AG:AG,PL!$B:$B,$B13) -> 0 | AC13: =SUMIFS(PL!AH:AH,PL!$B:$B,$B13) -> 0 | AD13: =SUMIFS(PL!AI:AI,PL!$B:$B,$B13) -> 0 | AE13: =SUMIFS(PL!AJ:AJ,PL!$B:$B,$B13) -> 0 | AF13: =SUMIFS(PL!AK:AK,PL!$B:$B,$B13) -> 0 | AG13: =SUMIFS(PL!AL:AL,PL!$B:$B,$B13) -> 0 | AH13: =SUMIFS(PL!AM:AM,PL!$B:$B,$B13) -> 0 | AI13: =SUMIFS(PL!AN:AN,PL!$B:$B,$B13) -> 0 | AJ13: =SUMIFS(PL!AS:AS,PL!$B:$B,$B13) -> 0 | AK13: =SUMIFS(PL!AT:AT,PL!$B:$B,$B13) -> 0 | AL13: =SUMIFS(PL!AU:AU,PL!$B:$B,$B13) -> 0 | AM13: =SUMIFS(PL!AV:AV,PL!$B:$B,$B13) -> 0
A14: Clinic wages | B14: Clinic wages | C14: =SUMIFS($G14:$BC14,$G$5:$BC$5,"<="&EOMONTH(C$5,0),$G$6:$BC$6,"<="&C$5) -> 0 | D14: =SUMIFS($G14:$AT14,$G$5:$AT$5,">"&EOMONTH(D$5,-12),$G$5:$AT$5,"<="&D$5) -> 0 | E14: =SUMIFS($G14:$AT14,$G$5:$AT$5,">"&EOMONTH(E$5,-12),$G$5:$AT$5,"<="&E$5) -> 0 | G14: =SUMIFS(PL!L:L,PL!$B:$B,$B14) -> 0 | H14: =SUMIFS(PL!M:M,PL!$B:$B,$B14) -> 0 | I14: =SUMIFS(PL!N:N,PL!$B:$B,$B14) -> 0 | J14: =SUMIFS(PL!O:O,PL!$B:$B,$B14) -> 0 | K14: =SUMIFS(PL!P:P,PL!$B:$B,$B14) -> 0 | L14: =SUMIFS(PL!Q:Q,PL!$B:$B,$B14) -> 0 | M14: =SUMIFS(PL!R:R,PL!$B:$B,$B14) -> 0 | N14: =SUMIFS(PL!S:S,PL!$B:$B,$B14) -> 0 | O14: =SUMIFS(PL!T:T,PL!$B:$B,$B14) -> 0 | P14: =SUMIFS(PL!U:U,PL!$B:$B,$B14) -> 0 | Q14: =SUMIFS(PL!V:V,PL!$B:$B,$B14) -> 0 | R14: =SUMIFS(PL!W:W,PL!$B:$B,$B14) -> 0 | S14: =SUMIFS(PL!X:X,PL!$B:$B,$B14) -> 0 | T14: =SUMIFS(PL!Y:Y,PL!$B:$B,$B14) -> 0 | U14: =SUMIFS(PL!Z:Z,PL!$B:$B,$B14) -> 0 | V14: =SUMIFS(PL!AA:AA,PL!$B:$B,$B14) -> 0 | W14: =SUMIFS(PL!AB:AB,PL!$B:$B,$B14) -> 0 | X14: =SUMIFS(PL!AC:AC,PL!$B:$B,$B14) -> 0 | Y14: =SUMIFS(PL!AD:AD,PL!$B:$B,$B14) -> 0 | Z14: =SUMIFS(PL!AE:AE,PL!$B:$B,$B14) -> 0 | AA14: =SUMIFS(PL!AF:AF,PL!$B:$B,$B14) -> 0 | AB14: =SUMIFS(PL!AG:AG,PL!$B:$B,$B14) -> 0 | AC14: =SUMIFS(PL!AH:AH,PL!$B:$B,$B14) -> 0 | AD14: =SUMIFS(PL!AI:AI,PL!$B:$B,$B14) -> 0 | AE14: =SUMIFS(PL!AJ:AJ,PL!$B:$B,$B14) -> 0 | AF14: =SUMIFS(PL!AK:AK,PL!$B:$B,$B14) -> 0 | AG14: =SUMIFS(PL!AL:AL,PL!$B:$B,$B14) -> 0 | AH14: =SUMIFS(PL!AM:AM,PL!$B:$B,$B14) -> 0 | AI14: =SUMIFS(PL!AN:AN,PL!$B:$B,$B14) -> 0 | AJ14: =SUMIFS(PL!AS:AS,PL!$B:$B,$B14) -> 0 | AK14: =SUMIFS(PL!AT:AT,PL!$B:$B,$B14) -> 0 | AL14: =SUMIFS(PL!AU:AU,PL!$B:$B,$B14) -> 0 | AM14: =SUMIFS(PL!AV:AV,PL!$B:$B,$B14) -> 0
A15: Admin wages | B15: Admin wages | C15: =SUMIFS($G15:$BC15,$G$5:$BC$5,"<="&EOMONTH(C$5,0),$G$6:$BC$6,"<="&C$5) -> 0 | D15: =SUMIFS($G15:$AT15,$G$5:$AT$5,">"&EOMONTH(D$5,-12),$G$5:$AT$5,"<="&D$5) -> 0 | E15: =SUMIFS($G15:$AT15,$G$5:$AT$5,">"&EOMONTH(E$5,-12),$G$5:$AT$5,"<="&E$5) -> 0 | G15: =SUMIFS(PL!L:L,PL!$B:$B,$B15) -> 0 | H15: =SUMIFS(PL!M:M,PL!$B:$B,$B15) -> 0 | I15: =SUMIFS(PL!N:N,PL!$B:$B,$B15) -> 0 | J15: =SUMIFS(PL!O:O,PL!$B:$B,$B15) -> 0 | K15: =SUMIFS(PL!P:P,PL!$B:$B,$B15) -> 0 | L15: =SUMIFS(PL!Q:Q,PL!$B:$B,$B15) -> 0 | M15: =SUMIFS(PL!R:R,PL!$B:$B,$B15) -> 0 | N15: =SUMIFS(PL!S:S,PL!$B:$B,$B15) -> 0 | O15: =SUMIFS(PL!T:T,PL!$B:$B,$B15) -> 0 | P15: =SUMIFS(PL!U:U,PL!$B:$B,$B15) -> 0 | Q15: =SUMIFS(PL!V:V,PL!$B:$B,$B15) -> 0 | R15: =SUMIFS(PL!W:W,PL!$B:$B,$B15) -> 0 | S15: =SUMIFS(PL!X:X,PL!$B:$B,$B15) -> 0 | T15: =SUMIFS(PL!Y:Y,PL!$B:$B,$B15) -> 0 | U15: =SUMIFS(PL!Z:Z,PL!$B:$B,$B15) -> 0 | V15: =SUMIFS(PL!AA:AA,PL!$B:$B,$B15) -> 0 | W15: =SUMIFS(PL!AB:AB,PL!$B:$B,$B15) -> 0 | X15: =SUMIFS(PL!AC:AC,PL!$B:$B,$B15) -> 0 | Y15: =SUMIFS(PL!AD:AD,PL!$B:$B,$B15) -> 0 | Z15: =SUMIFS(PL!AE:AE,PL!$B:$B,$B15) -> 0 | AA15: =SUMIFS(PL!AF:AF,PL!$B:$B,$B15) -> 0 | AB15: =SUMIFS(PL!AG:AG,PL!$B:$B,$B15) -> 0 | AC15: =SUMIFS(PL!AH:AH,PL!$B:$B,$B15) -> 0 | AD15: =SUMIFS(PL!AI:AI,PL!$B:$B,$B15) -> 0 | AE15: =SUMIFS(PL!AJ:AJ,PL!$B:$B,$B15) -> 0 | AF15: =SUMIFS(PL!AK:AK,PL!$B:$B,$B15) -> 0 | AG15: =SUMIFS(PL!AL:AL,PL!$B:$B,$B15) -> 0 | AH15: =SUMIFS(PL!AM:AM,PL!$B:$B,$B15) -> 0 | AI15: =SUMIFS(PL!AN:AN,PL!$B:$B,$B15) -> 0 | AJ15: =SUMIFS(PL!AS:AS,PL!$B:$B,$B15) -> 0 | AK15: =SUMIFS(PL!AT:AT,PL!$B:$B,$B15) -> 0 | AL15: =SUMIFS(PL!AU:AU,PL!$B:$B,$B15) -> 0 | AM15: =SUMIFS(PL!AV:AV,PL!$B:$B,$B15) -> 0
B16: Gross wages, total | C16: =SUBTOTAL(9,C13:C15) -> 0 | D16: =SUBTOTAL(9,D13:D15) -> 0 | E16: =SUBTOTAL(9,E13:E15) -> 0 | G16: =SUBTOTAL(9,G13:G15) -> 0 | H16: =SUBTOTAL(9,H13:H15) -> 0 | I16: =SUBTOTAL(9,I13:I15) -> 0 | J16: =SUBTOTAL(9,J13:J15) -> 0 | K16: =SUBTOTAL(9,K13:K15) -> 0 | L16: =SUBTOTAL(9,L13:L15) -> 0 | M16: =SUBTOTAL(9,M13:M15) -> 0 | N16: =SUBTOTAL(9,N13:N15) -> 0 | ... AM16: =SUBTOTAL(9,AM13:AM15) -> 0
A17: Payroll taxes | B17: Payroll taxes | C17: =SUMIFS($G17:$BC17,$G$5:$BC$5,"<="&EOMONTH(C$5,0),$G$6:$BC$6,"<="&C$5) -> 0 | D17: =SUMIFS($G17:$AT17,$G$5:$AT$5,">"&EOMONTH(D$5,-12),$G$5:$AT$5,"<="&D$5) -> 0 | E17: =SUMIFS($G17:$AT17,$G$5:$AT$5,">"&EOMONTH(E$5,-12),$G$5:$AT$5,"<="&E$5) -> 0 | G17: =SUMIFS(PL!L:L,PL!$B:$B,$B17) -> 0 | H17: =SUMIFS(PL!M:M,PL!$B:$B,$B17) -> 0 | I17: =SUMIFS(PL!N:N,PL!$B:$B,$B17) -> 0 | J17: =SUMIFS(PL!O:O,PL!$B:$B,$B17) -> 0 | K17: =SUMIFS(PL!P:P,PL!$B:$B,$B17) -> 0 | L17: =SUMIFS(PL!Q:Q,PL!$B:$B,$B17) -> 0 | M17: =SUMIFS(PL!R:R,PL!$B:$B,$B17) -> 0 | N17: =SUMIFS(PL!S:S,PL!$B:$B,$B17) -> 0 | O17: =SUMIFS(PL!T:T,PL!$B:$B,$B17) -> 0 | P17: =SUMIFS(PL!U:U,PL!$B:$B,$B17) -> 0 | Q17: =SUMIFS(PL!V:V,PL!$B:$B,$B17) -> 0 | R17: =SUMIFS(PL!W:W,PL!$B:$B,$B17) -> 0 | S17: =SUMIFS(PL!X:X,PL!$B:$B,$B17) -> 0 | T17: =SUMIFS(PL!Y:Y,PL!$B:$B,$B17) -> 0 | U17: =SUMIFS(PL!Z:Z,PL!$B:$B,$B17) -> 0 | V17: =SUMIFS(PL!AA:AA,PL!$B:$B,$B17) -> 0 | W17: =SUMIFS(PL!AB:AB,PL!$B:$B,$B17) -> 0 | X17: =SUMIFS(PL!AC:AC,PL!$B:$B,$B17) -> 0 | Y17: =SUMIFS(PL!AD:AD,PL!$B:$B,$B17) -> 0 | Z17: =SUMIFS(PL!AE:AE,PL!$B:$B,$B17) -> 0 | AA17: =SUMIFS(PL!AF:AF,PL!$B:$B,$B17) -> 0 | AB17: =SUMIFS(PL!AG:AG,PL!$B:$B,$B17) -> 0 | AC17: =SUMIFS(PL!AH:AH,PL!$B:$B,$B17) -> 0 | AD17: =SUMIFS(PL!AI:AI,PL!$B:$B,$B17) -> 0 | AE17: =SUMIFS(PL!AJ:AJ,PL!$B:$B,$B17) -> 0 | AF17: =SUMIFS(PL!AK:AK,PL!$B:$B,$B17) -> 0 | AG17: =SUMIFS(PL!AL:AL,PL!$B:$B,$B17) -> 0 | AH17: =SUMIFS(PL!AM:AM,PL!$B:$B,$B17) -> 0 | AI17: =SUMIFS(PL!AN:AN,PL!$B:$B,$B17) -> 0 | AJ17: =SUMIFS(PL!AS:AS,PL!$B:$B,$B17) -> 0 | AK17: =SUMIFS(PL!AT:AT,PL!$B:$B,$B17) -> 0 | AL17: =SUMIFS(PL!AU:AU,PL!$B:$B,$B17) -> 0 | AM17: =SUMIFS(PL!AV:AV,PL!$B:$B,$B17) -> 0
A18: Insurance | B18: Insurance | C18: =SUMIFS($G18:$BC18,$G$5:$BC$5,"<="&EOMONTH(C$5,0),$G$6:$BC$6,"<="&C$5) -> 0 | D18: =SUMIFS($G18:$AT18,$G$5:$AT$5,">"&EOMONTH(D$5,-12),$G$5:$AT$5,"<="&D$5) -> 0 | E18: =SUMIFS($G18:$AT18,$G$5:$AT$5,">"&EOMONTH(E$5,-12),$G$5:$AT$5,"<="&E$5) -> 0 | G18: =SUMIFS(PL!L:L,PL!$B:$B,$B18) -> 0 | H18: =SUMIFS(PL!M:M,PL!$B:$B,$B18) -> 0 | I18: =SUMIFS(PL!N:N,PL!$B:$B,$B18) -> 0 | J18: =SUMIFS(PL!O:O,PL!$B:$B,$B18) -> 0 | K18: =SUMIFS(PL!P:P,PL!$B:$B,$B18) -> 0 | L18: =SUMIFS(PL!Q:Q,PL!$B:$B,$B18) -> 0 | M18: =SUMIFS(PL!R:R,PL!$B:$B,$B18) -> 0 | N18: =SUMIFS(PL!S:S,PL!$B:$B,$B18) -> 0 | O18: =SUMIFS(PL!T:T,PL!$B:$B,$B18) -> 0 | P18: =SUMIFS(PL!U:U,PL!$B:$B,$B18) -> 0 | Q18: =SUMIFS(PL!V:V,PL!$B:$B,$B18) -> 0 | R18: =SUMIFS(PL!W:W,PL!$B:$B,$B18) -> 0 | S18: =SUMIFS(PL!X:X,PL!$B:$B,$B18) -> 0 | T18: =SUMIFS(PL!Y:Y,PL!$B:$B,$B18) -> 0 | U18: =SUMIFS(PL!Z:Z,PL!$B:$B,$B18) -> 0 | V18: =SUMIFS(PL!AA:AA,PL!$B:$B,$B18) -> 0 | W18: =SUMIFS(PL!AB:AB,PL!$B:$B,$B18) -> 0 | X18: =SUMIFS(PL!AC:AC,PL!$B:$B,$B18) -> 0 | Y18: =SUMIFS(PL!AD:AD,PL!$B:$B,$B18) -> 0 | Z18: =SUMIFS(PL!AE:AE,PL!$B:$B,$B18) -> 0 | AA18: =SUMIFS(PL!AF:AF,PL!$B:$B,$B18) -> 0 | AB18: =SUMIFS(PL!AG:AG,PL!$B:$B,$B18) -> 0 | AC18: =SUMIFS(PL!AH:AH,PL!$B:$B,$B18) -> 0 | AD18: =SUMIFS(PL!AI:AI,PL!$B:$B,$B18) -> 0 | AE18: =SUMIFS(PL!AJ:AJ,PL!$B:$B,$B18) -> 0 | AF18: =SUMIFS(PL!AK:AK,PL!$B:$B,$B18) -> 0 | AG18: =SUMIFS(PL!AL:AL,PL!$B:$B,$B18) -> 0 | AH18: =SUMIFS(PL!AM:AM,PL!$B:$B,$B18) -> 0 | AI18: =SUMIFS(PL!AN:AN,PL!$B:$B,$B18) -> 0 | AJ18: =SUMIFS(PL!AS:AS,PL!$B:$B,$B18) -> 0 | AK18: =SUMIFS(PL!AT:AT,PL!$B:$B,$B18) -> 0 | AL18: =SUMIFS(PL!AU:AU,PL!$B:$B,$B18) -> 0 | AM18: =SUMIFS(PL!AV:AV,PL!$B:$B,$B18) -> 0
A19: Employee 401(k) | B19: Employee 401(k) | C19: =SUMIFS($G19:$BC19,$G$5:$BC$5,"<="&EOMONTH(C$5,0),$G$6:$BC$6,"<="&C$5) -> 0 | D19: =SUMIFS($G19:$AT19,$G$5:$AT$5,">"&EOMONTH(D$5,-12),$G$5:$AT$5,"<="&D$5) -> 0 | E19: =SUMIFS($G19:$AT19,$G$5:$AT$5,">"&EOMONTH(E$5,-12),$G$5:$AT$5,"<="&E$5) -> 0 | G19: =SUMIFS(PL!L:L,PL!$B:$B,$B19) -> 0 | H19: =SUMIFS(PL!M:M,PL!$B:$B,$B19) -> 0 | I19: =SUMIFS(PL!N:N,PL!$B:$B,$B19) -> 0 | J19: =SUMIFS(PL!O:O,PL!$B:$B,$B19) -> 0 | K19: =SUMIFS(PL!P:P,PL!$B:$B,$B19) -> 0 | L19: =SUMIFS(PL!Q:Q,PL!$B:$B,$B19) -> 0 | M19: =SUMIFS(PL!R:R,PL!$B:$B,$B19) -> 0 | N19: =SUMIFS(PL!S:S,PL!$B:$B,$B19) -> 0 | O19: =SUMIFS(PL!T:T,PL!$B:$B,$B19) -> 0 | P19: =SUMIFS(PL!U:U,PL!$B:$B,$B19) -> 0 | Q19: =SUMIFS(PL!V:V,PL!$B:$B,$B19) -> 0 | R19: =SUMIFS(PL!W:W,PL!$B:$B,$B19) -> 0 | S19: =SUMIFS(PL!X:X,PL!$B:$B,$B19) -> 0 | T19: =SUMIFS(PL!Y:Y,PL!$B:$B,$B19) -> 0 | U19: =SUMIFS(PL!Z:Z,PL!$B:$B,$B19) -> 0 | V19: =SUMIFS(PL!AA:AA,PL!$B:$B,$B19) -> 0 | W19: =SUMIFS(PL!AB:AB,PL!$B:$B,$B19) -> 0 | X19: =SUMIFS(PL!AC:AC,PL!$B:$B,$B19) -> 0 | Y19: =SUMIFS(PL!AD:AD,PL!$B:$B,$B19) -> 0 | Z19: =SUMIFS(PL!AE:AE,PL!$B:$B,$B19) -> 0 | AA19: =SUMIFS(PL!AF:AF,PL!$B:$B,$B19) -> 0 | AB19: =SUMIFS(PL!AG:AG,PL!$B:$B,$B19) -> 0 | AC19: =SUMIFS(PL!AH:AH,PL!$B:$B,$B19) -> 0 | AD19: =SUMIFS(PL!AI:AI,PL!$B:$B,$B19) -> 0 | AE19: =SUMIFS(PL!AJ:AJ,PL!$B:$B,$B19) -> 0 | AF19: =SUMIFS(PL!AK:AK,PL!$B:$B,$B19) -> 0 | AG19: =SUMIFS(PL!AL:AL,PL!$B:$B,$B19) -> 0 | AH19: =SUMIFS(PL!AM:AM,PL!$B:$B,$B19) -> 0 | AI19: =SUMIFS(PL!AN:AN,PL!$B:$B,$B19) -> 0 | AJ19: =SUMIFS(PL!AS:AS,PL!$B:$B,$B19) -> 0 | AK19: =SUMIFS(PL!AT:AT,PL!$B:$B,$B19) -> 0 | AL19: =SUMIFS(PL!AU:AU,PL!$B:$B,$B19) -> 0 | AM19: =SUMIFS(PL!AV:AV,PL!$B:$B,$B19) -> 0
B20: Salary, payroll taxes, and benefits, total | C20: =SUM(C16:C19) -> 0 | D20: =SUM(D16:D19) -> 0 | E20: =SUM(E16:E19) -> 0 | G20: =SUM(G16:G19) -> 0 | H20: =SUM(H16:H19) -> 0 | I20: =SUM(I16:I19) -> 0 | J20: =SUM(J16:J19) -> 0 | K20: =SUM(K16:K19) -> 0 | L20: =SUM(L16:L19) -> 0 | M20: =SUM(M16:M19) -> 0 | N20: =SUM(N16:N19) -> 0 | ... AM20: =SUM(AM16:AM19) -> 0
B21: Rent - real property | C21: =SUMIFS($G21:$BC21,$G$5:$BC$5,"<="&EOMONTH(C$5,0),$G$6:$BC$6,"<="&C$5) -> 0 | D21: =SUMIFS($G21:$AT21,$G$5:$AT$5,">"&EOMONTH(D$5,-12),$G$5:$AT$5,"<="&D$5) -> 0 | E21: =SUMIFS($G21:$AT21,$G$5:$AT$5,">"&EOMONTH(E$5,-12),$G$5:$AT$5,"<="&E$5) -> 0 | G21: =SUMIFS(PL!L:L,PL!$B:$B,$B21) -> 0 | H21: =SUMIFS(PL!M:M,PL!$B:$B,$B21) -> 0 | I21: =SUMIFS(PL!N:N,PL!$B:$B,$B21) -> 0 | J21: =SUMIFS(PL!O:O,PL!$B:$B,$B21) -> 0 | K21: =SUMIFS(PL!P:P,PL!$B:$B,$B21) -> 0 | L21: =SUMIFS(PL!Q:Q,PL!$B:$B,$B21) -> 0 | M21: =SUMIFS(PL!R:R,PL!$B:$B,$B21) -> 0 | N21: =SUMIFS(PL!S:S,PL!$B:$B,$B21) -> 0 | O21: =SUMIFS(PL!T:T,PL!$B:$B,$B21) -> 0 | P21: =SUMIFS(PL!U:U,PL!$B:$B,$B21) -> 0 | Q21: =SUMIFS(PL!V:V,PL!$B:$B,$B21) -> 0 | R21: =SUMIFS(PL!W:W,PL!$B:$B,$B21) -> 0 | S21: =SUMIFS(PL!X:X,PL!$B:$B,$B21) -> 0 | T21: =SUMIFS(PL!Y:Y,PL!$B:$B,$B21) -> 0 | U21: =SUMIFS(PL!Z:Z,PL!$B:$B,$B21) -> 0 | V21: =SUMIFS(PL!AA:AA,PL!$B:$B,$B21) -> 0 | W21: =SUMIFS(PL!AB:AB,PL!$B:$B,$B21) -> 0 | X21: =SUMIFS(PL!AC:AC,PL!$B:$B,$B21) -> 0 | Y21: =SUMIFS(PL!AD:AD,PL!$B:$B,$B21) -> 0 | Z21: =SUMIFS(PL!AE:AE,PL!$B:$B,$B21) -> 0 | AA21: =SUMIFS(PL!AF:AF,PL!$B:$B,$B21) -> 0 | AB21: =SUMIFS(PL!AG:AG,PL!$B:$B,$B21) -> 0 | AC21: =SUMIFS(PL!AH:AH,PL!$B:$B,$B21) -> 0 | AD21: =SUMIFS(PL!AI:AI,PL!$B:$B,$B21) -> 0 | AE21: =SUMIFS(PL!AJ:AJ,PL!$B:$B,$B21) -> 0 | AF21: =SUMIFS(PL!AK:AK,PL!$B:$B,$B21) -> 0 | AG21: =SUMIFS(PL!AL:AL,PL!$B:$B,$B21) -> 0 | AH21: =SUMIFS(PL!AM:AM,PL!$B:$B,$B21) -> 0 | AI21: =SUMIFS(PL!AN:AN,PL!$B:$B,$B21) -> 0 | AJ21: =SUMIFS(PL!AS:AS,PL!$B:$B,$B21) -> 0 | AK21: =SUMIFS(PL!AT:AT,PL!$B:$B,$B21) -> 0 | AL21: =SUMIFS(PL!AU:AU,PL!$B:$B,$B21) -> 0 | AM21: =SUMIFS(PL!AV:AV,PL!$B:$B,$B21) -> 0
B22: Property tax expense | C22: =SUMIFS($G22:$BC22,$G$5:$BC$5,"<="&EOMONTH(C$5,0),$G$6:$BC$6,"<="&C$5) -> 0 | D22: =SUMIFS($G22:$AT22,$G$5:$AT$5,">"&EOMONTH(D$5,-12),$G$5:$AT$5,"<="&D$5) -> 0 | E22: =SUMIFS($G22:$AT22,$G$5:$AT$5,">"&EOMONTH(E$5,-12),$G$5:$AT$5,"<="&E$5) -> 0 | G22: =SUMIFS(PL!L:L,PL!$B:$B,$B22) -> 0 | H22: =SUMIFS(PL!M:M,PL!$B:$B,$B22) -> 0 | I22: =SUMIFS(PL!N:N,PL!$B:$B,$B22) -> 0 | J22: =SUMIFS(PL!O:O,PL!$B:$B,$B22) -> 0 | K22: =SUMIFS(PL!P:P,PL!$B:$B,$B22) -> 0 | L22: =SUMIFS(PL!Q:Q,PL!$B:$B,$B22) -> 0 | M22: =SUMIFS(PL!R:R,PL!$B:$B,$B22) -> 0 | N22: =SUMIFS(PL!S:S,PL!$B:$B,$B22) -> 0 | O22: =SUMIFS(PL!T:T,PL!$B:$B,$B22) -> 0 | P22: =SUMIFS(PL!U:U,PL!$B:$B,$B22) -> 0 | Q22: =SUMIFS(PL!V:V,PL!$B:$B,$B22) -> 0 | R22: =SUMIFS(PL!W:W,PL!$B:$B,$B22) -> 0 | S22: =SUMIFS(PL!X:X,PL!$B:$B,$B22) -> 0 | T22: =SUMIFS(PL!Y:Y,PL!$B:$B,$B22) -> 0 | U22: =SUMIFS(PL!Z:Z,PL!$B:$B,$B22) -> 0 | V22: =SUMIFS(PL!AA:AA,PL!$B:$B,$B22) -> 0 | W22: =SUMIFS(PL!AB:AB,PL!$B:$B,$B22) -> 0 | X22: =SUMIFS(PL!AC:AC,PL!$B:$B,$B22) -> 0 | Y22: =SUMIFS(PL!AD:AD,PL!$B:$B,$B22) -> 0 | Z22: =SUMIFS(PL!AE:AE,PL!$B:$B,$B22) -> 0 | AA22: =SUMIFS(PL!AF:AF,PL!$B:$B,$B22) -> 0 | AB22: =SUMIFS(PL!AG:AG,PL!$B:$B,$B22) -> 0 | AC22: =SUMIFS(PL!AH:AH,PL!$B:$B,$B22) -> 0 | AD22: =SUMIFS(PL!AI:AI,PL!$B:$B,$B22) -> 0 | AE22: =SUMIFS(PL!AJ:AJ,PL!$B:$B,$B22) -> 0 | AF22: =SUMIFS(PL!AK:AK,PL!$B:$B,$B22) -> 0 | AG22: =SUMIFS(PL!AL:AL,PL!$B:$B,$B22) -> 0 | AH22: =SUMIFS(PL!AM:AM,PL!$B:$B,$B22) -> 0 | AI22: =SUMIFS(PL!AN:AN,PL!$B:$B,$B22) -> 0 | AJ22: =SUMIFS(PL!AS:AS,PL!$B:$B,$B22) -> 0 | AK22: =SUMIFS(PL!AT:AT,PL!$B:$B,$B22) -> 0 | AL22: =SUMIFS(PL!AU:AU,PL!$B:$B,$B22) -> 0 | AM22: =SUMIFS(PL!AV:AV,PL!$B:$B,$B22) -> 0
B23: Repairs and maintenance | C23: =SUMIFS($G23:$BC23,$G$5:$BC$5,"<="&EOMONTH(C$5,0),$G$6:$BC$6,"<="&C$5) -> 0 | D23: =SUMIFS($G23:$AT23,$G$5:$AT$5,">"&EOMONTH(D$5,-12),$G$5:$AT$5,"<="&D$5) -> 0 | E23: =SUMIFS($G23:$AT23,$G$5:$AT$5,">"&EOMONTH(E$5,-12),$G$5:$AT$5,"<="&E$5) -> 0 | G23: =SUMIFS(PL!L:L,PL!$B:$B,$B23) -> 0 | H23: =SUMIFS(PL!M:M,PL!$B:$B,$B23) -> 0 | I23: =SUMIFS(PL!N:N,PL!$B:$B,$B23) -> 0 | J23: =SUMIFS(PL!O:O,PL!$B:$B,$B23) -> 0 | K23: =SUMIFS(PL!P:P,PL!$B:$B,$B23) -> 0 | L23: =SUMIFS(PL!Q:Q,PL!$B:$B,$B23) -> 0 | M23: =SUMIFS(PL!R:R,PL!$B:$B,$B23) -> 0 | N23: =SUMIFS(PL!S:S,PL!$B:$B,$B23) -> 0 | O23: =SUMIFS(PL!T:T,PL!$B:$B,$B23) -> 0 | P23: =SUMIFS(PL!U:U,PL!$B:$B,$B23) -> 0 | Q23: =SUMIFS(PL!V:V,PL!$B:$B,$B23) -> 0 | R23: =SUMIFS(PL!W:W,PL!$B:$B,$B23) -> 0 | S23: =SUMIFS(PL!X:X,PL!$B:$B,$B23) -> 0 | T23: =SUMIFS(PL!Y:Y,PL!$B:$B,$B23) -> 0 | U23: =SUMIFS(PL!Z:Z,PL!$B:$B,$B23) -> 0 | V23: =SUMIFS(PL!AA:AA,PL!$B:$B,$B23) -> 0 | W23: =SUMIFS(PL!AB:AB,PL!$B:$B,$B23) -> 0 | X23: =SUMIFS(PL!AC:AC,PL!$B:$B,$B23) -> 0 | Y23: =SUMIFS(PL!AD:AD,PL!$B:$B,$B23) -> 0 | Z23: =SUMIFS(PL!AE:AE,PL!$B:$B,$B23) -> 0 | AA23: =SUMIFS(PL!AF:AF,PL!$B:$B,$B23) -> 0 | AB23: =SUMIFS(PL!AG:AG,PL!$B:$B,$B23) -> 0 | AC23: =SUMIFS(PL!AH:AH,PL!$B:$B,$B23) -> 0 | AD23: =SUMIFS(PL!AI:AI,PL!$B:$B,$B23) -> 0 | AE23: =SUMIFS(PL!AJ:AJ,PL!$B:$B,$B23) -> 0 | AF23: =SUMIFS(PL!AK:AK,PL!$B:$B,$B23) -> 0 | AG23: =SUMIFS(PL!AL:AL,PL!$B:$B,$B23) -> 0 | AH23: =SUMIFS(PL!AM:AM,PL!$B:$B,$B23) -> 0 | AI23: =SUMIFS(PL!AN:AN,PL!$B:$B,$B23) -> 0 | AJ23: =SUMIFS(PL!AS:AS,PL!$B:$B,$B23) -> 0 | AK23: =SUMIFS(PL!AT:AT,PL!$B:$B,$B23) -> 0 | AL23: =SUMIFS(PL!AU:AU,PL!$B:$B,$B23) -> 0 | AM23: =SUMIFS(PL!AV:AV,PL!$B:$B,$B23) -> 0
B24: Utilities expense | C24: =SUMIFS($G24:$BC24,$G$5:$BC$5,"<="&EOMONTH(C$5,0),$G$6:$BC$6,"<="&C$5) -> 0 | D24: =SUMIFS($G24:$AT24,$G$5:$AT$5,">"&EOMONTH(D$5,-12),$G$5:$AT$5,"<="&D$5) -> 0 | E24: =SUMIFS($G24:$AT24,$G$5:$AT$5,">"&EOMONTH(E$5,-12),$G$5:$AT$5,"<="&E$5) -> 0 | G24: =SUMIFS(PL!L:L,PL!$B:$B,$B24) -> 0 | H24: =SUMIFS(PL!M:M,PL!$B:$B,$B24) -> 0 | I24: =SUMIFS(PL!N:N,PL!$B:$B,$B24) -> 0 | J24: =SUMIFS(PL!O:O,PL!$B:$B,$B24) -> 0 | K24: =SUMIFS(PL!P:P,PL!$B:$B,$B24) -> 0 | L24: =SUMIFS(PL!Q:Q,PL!$B:$B,$B24) -> 0 | M24: =SUMIFS(PL!R:R,PL!$B:$B,$B24) -> 0 | N24: =SUMIFS(PL!S:S,PL!$B:$B,$B24) -> 0 | O24: =SUMIFS(PL!T:T,PL!$B:$B,$B24) -> 0 | P24: =SUMIFS(PL!U:U,PL!$B:$B,$B24) -> 0 | Q24: =SUMIFS(PL!V:V,PL!$B:$B,$B24) -> 0 | R24: =SUMIFS(PL!W:W,PL!$B:$B,$B24) -> 0 | S24: =SUMIFS(PL!X:X,PL!$B:$B,$B24) -> 0 | T24: =SUMIFS(PL!Y:Y,PL!$B:$B,$B24) -> 0 | U24: =SUMIFS(PL!Z:Z,PL!$B:$B,$B24) -> 0 | V24: =SUMIFS(PL!AA:AA,PL!$B:$B,$B24) -> 0 | W24: =SUMIFS(PL!AB:AB,PL!$B:$B,$B24) -> 0 | X24: =SUMIFS(PL!AC:AC,PL!$B:$B,$B24) -> 0 | Y24: =SUMIFS(PL!AD:AD,PL!$B:$B,$B24) -> 0 | Z24: =SUMIFS(PL!AE:AE,PL!$B:$B,$B24) -> 0 | AA24: =SUMIFS(PL!AF:AF,PL!$B:$B,$B24) -> 0 | AB24: =SUMIFS(PL!AG:AG,PL!$B:$B,$B24) -> 0 | AC24: =SUMIFS(PL!AH:AH,PL!$B:$B,$B24) -> 0 | AD24: =SUMIFS(PL!AI:AI,PL!$B:$B,$B24) -> 0 | AE24: =SUMIFS(PL!AJ:AJ,PL!$B:$B,$B24) -> 0 | AF24: =SUMIFS(PL!AK:AK,PL!$B:$B,$B24) -> 0 | AG24: =SUMIFS(PL!AL:AL,PL!$B:$B,$B24) -> 0 | AH24: =SUMIFS(PL!AM:AM,PL!$B:$B,$B24) -> 0 | AI24: =SUMIFS(PL!AN:AN,PL!$B:$B,$B24) -> 0 | AJ24: =SUMIFS(PL!AS:AS,PL!$B:$B,$B24) -> 0 | AK24: =SUMIFS(PL!AT:AT,PL!$B:$B,$B24) -> 0 | AL24: =SUMIFS(PL!AU:AU,PL!$B:$B,$B24) -> 0 | AM24: =SUMIFS(PL!AV:AV,PL!$B:$B,$B24) -> 0
B25: Rent and building expenses, total | C25: =SUM(C21:C24) -> 0 | D25: =SUM(D21:D24) -> 0 | E25: =SUM(E21:E24) -> 0 | G25: =SUM(G21:G24) -> 0 | H25: =SUM(H21:H24) -> 0 | I25: =SUM(I21:I24) -> 0 | J25: =SUM(J21:J24) -> 0 | K25: =SUM(K21:K24) -> 0 | L25: =SUM(L21:L24) -> 0 | M25: =SUM(M21:M24) -> 0 | N25: =SUM(N21:N24) -> 0 | ... AM25: =SUM(AM21:AM24) -> 0
A26: Advertising | B26: Advertising | C26: =SUMIFS($G26:$BC26,$G$5:$BC$5,"<="&EOMONTH(C$5,0),$G$6:$BC$6,"<="&C$5) -> 0 | D26: =SUMIFS($G26:$AT26,$G$5:$AT$5,">"&EOMONTH(D$5,-12),$G$5:$AT$5,"<="&D$5) -> 0 | E26: =SUMIFS($G26:$AT26,$G$5:$AT$5,">"&EOMONTH(E$5,-12),$G$5:$AT$5,"<="&E$5) -> 0 | G26: =SUMIFS(PL!L:L,PL!$B:$B,$B26) -> 0 | H26: =SUMIFS(PL!M:M,PL!$B:$B,$B26) -> 0 | I26: =SUMIFS(PL!N:N,PL!$B:$B,$B26) -> 0 | J26: =SUMIFS(PL!O:O,PL!$B:$B,$B26) -> 0 | K26: =SUMIFS(PL!P:P,PL!$B:$B,$B26) -> 0 | L26: =SUMIFS(PL!Q:Q,PL!$B:$B,$B26) -> 0 | M26: =SUMIFS(PL!R:R,PL!$B:$B,$B26) -> 0 | N26: =SUMIFS(PL!S:S,PL!$B:$B,$B26) -> 0 | O26: =SUMIFS(PL!T:T,PL!$B:$B,$B26) -> 0 | P26: =SUMIFS(PL!U:U,PL!$B:$B,$B26) -> 0 | Q26: =SUMIFS(PL!V:V,PL!$B:$B,$B26) -> 0 | R26: =SUMIFS(PL!W:W,PL!$B:$B,$B26) -> 0 | S26: =SUMIFS(PL!X:X,PL!$B:$B,$B26) -> 0 | T26: =SUMIFS(PL!Y:Y,PL!$B:$B,$B26) -> 0 | U26: =SUMIFS(PL!Z:Z,PL!$B:$B,$B26) -> 0 | V26: =SUMIFS(PL!AA:AA,PL!$B:$B,$B26) -> 0 | W26: =SUMIFS(PL!AB:AB,PL!$B:$B,$B26) -> 0 | X26: =SUMIFS(PL!AC:AC,PL!$B:$B,$B26) -> 0 | Y26: =SUMIFS(PL!AD:AD,PL!$B:$B,$B26) -> 0 | Z26: =SUMIFS(PL!AE:AE,PL!$B:$B,$B26) -> 0 | AA26: =SUMIFS(PL!AF:AF,PL!$B:$B,$B26) -> 0 | AB26: =SUMIFS(PL!AG:AG,PL!$B:$B,$B26) -> 0 | AC26: =SUMIFS(PL!AH:AH,PL!$B:$B,$B26) -> 0 | AD26: =SUMIFS(PL!AI:AI,PL!$B:$B,$B26) -> 0 | AE26: =SUMIFS(PL!AJ:AJ,PL!$B:$B,$B26) -> 0 | AF26: =SUMIFS(PL!AK:AK,PL!$B:$B,$B26) -> 0 | AG26: =SUMIFS(PL!AL:AL,PL!$B:$B,$B26) -> 0 | AH26: =SUMIFS(PL!AM:AM,PL!$B:$B,$B26) -> 0 | AI26: =SUMIFS(PL!AN:AN,PL!$B:$B,$B26) -> 0 | AJ26: =SUMIFS(PL!AS:AS,PL!$B:$B,$B26) -> 0 | AK26: =SUMIFS(PL!AT:AT,PL!$B:$B,$B26) -> 0 | AL26: =SUMIFS(PL!AU:AU,PL!$B:$B,$B26) -> 0 | AM26: =SUMIFS(PL!AV:AV,PL!$B:$B,$B26) -> 0
B27: Other | C27: =SUBTOTAL(9,C28:C42) -> 0 | D27: =SUBTOTAL(9,D28:D42) -> 0 | E27: =SUBTOTAL(9,E28:E42) -> 0 | G27: =SUBTOTAL(9,G28:G42) -> 0 | H27: =SUBTOTAL(9,H28:H42) -> 0 | I27: =SUBTOTAL(9,I28:I42) -> 0 | J27: =SUBTOTAL(9,J28:J42) -> 0 | K27: =SUBTOTAL(9,K28:K42) -> 0 | L27: =SUBTOTAL(9,L28:L42) -> 0 | M27: =SUBTOTAL(9,M28:M42) -> 0 | N27: =SUBTOTAL(9,N28:N42) -> 0 | ... AM27: =SUBTOTAL(9,AM28:AM42) -> 0
A28: Other | B28: Bank Service Fees | C28: =SUMIFS($G28:$BC28,$G$5:$BC$5,"<="&EOMONTH(C$5,0),$G$6:$BC$6,"<="&C$5) -> 0 | D28: =SUMIFS($G28:$AT28,$G$5:$AT$5,">"&EOMONTH(D$5,-12),$G$5:$AT$5,"<="&D$5) -> 0 | E28: =SUMIFS($G28:$AT28,$G$5:$AT$5,">"&EOMONTH(E$5,-12),$G$5:$AT$5,"<="&E$5) -> 0 | G28: =SUMIFS(PL!L:L,PL!$B:$B,$B28,PL!$A:$A,$A28) -> 0 | H28: =SUMIFS(PL!M:M,PL!$B:$B,$B28,PL!$A:$A,$A28) -> 0 | I28: =SUMIFS(PL!N:N,PL!$B:$B,$B28,PL!$A:$A,$A28) -> 0 | J28: =SUMIFS(PL!O:O,PL!$B:$B,$B28,PL!$A:$A,$A28) -> 0 | K28: =SUMIFS(PL!P:P,PL!$B:$B,$B28,PL!$A:$A,$A28) -> 0 | L28: =SUMIFS(PL!Q:Q,PL!$B:$B,$B28,PL!$A:$A,$A28) -> 0 | M28: =SUMIFS(PL!R:R,PL!$B:$B,$B28,PL!$A:$A,$A28) -> 0 | N28: =SUMIFS(PL!S:S,PL!$B:$B,$B28,PL!$A:$A,$A28) -> 0 | O28: =SUMIFS(PL!T:T,PL!$B:$B,$B28,PL!$A:$A,$A28) -> 0 | P28: =SUMIFS(PL!U:U,PL!$B:$B,$B28,PL!$A:$A,$A28) -> 0 | Q28: =SUMIFS(PL!V:V,PL!$B:$B,$B28,PL!$A:$A,$A28) -> 0 | R28: =SUMIFS(PL!W:W,PL!$B:$B,$B28,PL!$A:$A,$A28) -> 0 | S28: =SUMIFS(PL!X:X,PL!$B:$B,$B28,PL!$A:$A,$A28) -> 0 | T28: =SUMIFS(PL!Y:Y,PL!$B:$B,$B28,PL!$A:$A,$A28) -> 0 | U28: =SUMIFS(PL!Z:Z,PL!$B:$B,$B28,PL!$A:$A,$A28) -> 0 | V28: =SUMIFS(PL!AA:AA,PL!$B:$B,$B28,PL!$A:$A,$A28) -> 0 | W28: =SUMIFS(PL!AB:AB,PL!$B:$B,$B28,PL!$A:$A,$A28) -> 0 | X28: =SUMIFS(PL!AC:AC,PL!$B:$B,$B28,PL!$A:$A,$A28) -> 0 | Y28: =SUMIFS(PL!AD:AD,PL!$B:$B,$B28,PL!$A:$A,$A28) -> 0 | Z28: =SUMIFS(PL!AE:AE,PL!$B:$B,$B28,PL!$A:$A,$A28) -> 0 | AA28: =SUMIFS(PL!AF:AF,PL!$B:$B,$B28,PL!$A:$A,$A28) -> 0 | AB28: =SUMIFS(PL!AG:AG,PL!$B:$B,$B28,PL!$A:$A,$A28) -> 0 | AC28: =SUMIFS(PL!AH:AH,PL!$B:$B,$B28,PL!$A:$A,$A28) -> 0 | AD28: =SUMIFS(PL!AI:AI,PL!$B:$B,$B28,PL!$A:$A,$A28) -> 0 | AE28: =SUMIFS(PL!AJ:AJ,PL!$B:$B,$B28,PL!$A:$A,$A28) -> 0 | AF28: =SUMIFS(PL!AK:AK,PL!$B:$B,$B28,PL!$A:$A,$A28) -> 0 | AG28: =SUMIFS(PL!AL:AL,PL!$B:$B,$B28,PL!$A:$A,$A28) -> 0 | AH28: =SUMIFS(PL!AM:AM,PL!$B:$B,$B28,PL!$A:$A,$A28) -> 0 | AI28: =SUMIFS(PL!AN:AN,PL!$B:$B,$B28,PL!$A:$A,$A28) -> 0 | AJ28: =SUMIFS(PL!AS:AS,PL!$B:$B,$B28,PL!$A:$A,$A28) -> 0 | AK28: =SUMIFS(PL!AT:AT,PL!$B:$B,$B28,PL!$A:$A,$A28) -> 0 | AL28: =SUMIFS(PL!AU:AU,PL!$B:$B,$B28,PL!$A:$A,$A28) -> 0 | AM28: =SUMIFS(PL!AV:AV,PL!$B:$B,$B28,PL!$A:$A,$A28) -> 0
A29: Other | B29: Computer and Software Expense | C29: =SUMIFS($G29:$BC29,$G$5:$BC$5,"<="&EOMONTH(C$5,0),$G$6:$BC$6,"<="&C$5) -> 0 | D29: =SUMIFS($G29:$AT29,$G$5:$AT$5,">"&EOMONTH(D$5,-12),$G$5:$AT$5,"<="&D$5) -> 0 | E29: =SUMIFS($G29:$AT29,$G$5:$AT$5,">"&EOMONTH(E$5,-12),$G$5:$AT$5,"<="&E$5) -> 0 | G29: =SUMIFS(PL!L:L,PL!$B:$B,$B29,PL!$A:$A,$A29) -> 0 | H29: =SUMIFS(PL!M:M,PL!$B:$B,$B29,PL!$A:$A,$A29) -> 0 | I29: =SUMIFS(PL!N:N,PL!$B:$B,$B29,PL!$A:$A,$A29) -> 0 | J29: =SUMIFS(PL!O:O,PL!$B:$B,$B29,PL!$A:$A,$A29) -> 0 | K29: =SUMIFS(PL!P:P,PL!$B:$B,$B29,PL!$A:$A,$A29) -> 0 | L29: =SUMIFS(PL!Q:Q,PL!$B:$B,$B29,PL!$A:$A,$A29) -> 0 | M29: =SUMIFS(PL!R:R,PL!$B:$B,$B29,PL!$A:$A,$A29) -> 0 | N29: =SUMIFS(PL!S:S,PL!$B:$B,$B29,PL!$A:$A,$A29) -> 0 | O29: =SUMIFS(PL!T:T,PL!$B:$B,$B29,PL!$A:$A,$A29) -> 0 | P29: =SUMIFS(PL!U:U,PL!$B:$B,$B29,PL!$A:$A,$A29) -> 0 | Q29: =SUMIFS(PL!V:V,PL!$B:$B,$B29,PL!$A:$A,$A29) -> 0 | R29: =SUMIFS(PL!W:W,PL!$B:$B,$B29,PL!$A:$A,$A29) -> 0 | S29: =SUMIFS(PL!X:X,PL!$B:$B,$B29,PL!$A:$A,$A29) -> 0 | T29: =SUMIFS(PL!Y:Y,PL!$B:$B,$B29,PL!$A:$A,$A29) -> 0 | U29: =SUMIFS(PL!Z:Z,PL!$B:$B,$B29,PL!$A:$A,$A29) -> 0 | V29: =SUMIFS(PL!AA:AA,PL!$B:$B,$B29,PL!$A:$A,$A29) -> 0 | W29: =SUMIFS(PL!AB:AB,PL!$B:$B,$B29,PL!$A:$A,$A29) -> 0 | X29: =SUMIFS(PL!AC:AC,PL!$B:$B,$B29,PL!$A:$A,$A29) -> 0 | Y29: =SUMIFS(PL!AD:AD,PL!$B:$B,$B29,PL!$A:$A,$A29) -> 0 | Z29: =SUMIFS(PL!AE:AE,PL!$B:$B,$B29,PL!$A:$A,$A29) -> 0 | AA29: =SUMIFS(PL!AF:AF,PL!$B:$B,$B29,PL!$A:$A,$A29) -> 0 | AB29: =SUMIFS(PL!AG:AG,PL!$B:$B,$B29,PL!$A:$A,$A29) -> 0 | AC29: =SUMIFS(PL!AH:AH,PL!$B:$B,$B29,PL!$A:$A,$A29) -> 0 | AD29: =SUMIFS(PL!AI:AI,PL!$B:$B,$B29,PL!$A:$A,$A29) -> 0 | AE29: =SUMIFS(PL!AJ:AJ,PL!$B:$B,$B29,PL!$A:$A,$A29) -> 0 | AF29: =SUMIFS(PL!AK:AK,PL!$B:$B,$B29,PL!$A:$A,$A29) -> 0 | AG29: =SUMIFS(PL!AL:AL,PL!$B:$B,$B29,PL!$A:$A,$A29) -> 0 | AH29: =SUMIFS(PL!AM:AM,PL!$B:$B,$B29,PL!$A:$A,$A29) -> 0 | AI29: =SUMIFS(PL!AN:AN,PL!$B:$B,$B29,PL!$A:$A,$A29) -> 0 | AJ29: =SUMIFS(PL!AS:AS,PL!$B:$B,$B29,PL!$A:$A,$A29) -> 0 | AK29: =SUMIFS(PL!AT:AT,PL!$B:$B,$B29,PL!$A:$A,$A29) -> 0 | AL29: =SUMIFS(PL!AU:AU,PL!$B:$B,$B29,PL!$A:$A,$A29) -> 0 | AM29: =SUMIFS(PL!AV:AV,PL!$B:$B,$B29,PL!$A:$A,$A29) -> 0
A30: Other | B30: Continuing Education | C30: =SUMIFS($G30:$BC30,$G$5:$BC$5,"<="&EOMONTH(C$5,0),$G$6:$BC$6,"<="&C$5) -> 0 | D30: =SUMIFS($G30:$AT30,$G$5:$AT$5,">"&EOMONTH(D$5,-12),$G$5:$AT$5,"<="&D$5) -> 0 | E30: =SUMIFS($G30:$AT30,$G$5:$AT$5,">"&EOMONTH(E$5,-12),$G$5:$AT$5,"<="&E$5) -> 0 | G30: =SUMIFS(PL!L:L,PL!$B:$B,$B30,PL!$A:$A,$A30) -> 0 | H30: =SUMIFS(PL!M:M,PL!$B:$B,$B30,PL!$A:$A,$A30) -> 0 | I30: =SUMIFS(PL!N:N,PL!$B:$B,$B30,PL!$A:$A,$A30) -> 0 | J30: =SUMIFS(PL!O:O,PL!$B:$B,$B30,PL!$A:$A,$A30) -> 0 | K30: =SUMIFS(PL!P:P,PL!$B:$B,$B30,PL!$A:$A,$A30) -> 0 | L30: =SUMIFS(PL!Q:Q,PL!$B:$B,$B30,PL!$A:$A,$A30) -> 0 | M30: =SUMIFS(PL!R:R,PL!$B:$B,$B30,PL!$A:$A,$A30) -> 0 | N30: =SUMIFS(PL!S:S,PL!$B:$B,$B30,PL!$A:$A,$A30) -> 0 | O30: =SUMIFS(PL!T:T,PL!$B:$B,$B30,PL!$A:$A,$A30) -> 0 | P30: =SUMIFS(PL!U:U,PL!$B:$B,$B30,PL!$A:$A,$A30) -> 0 | Q30: =SUMIFS(PL!V:V,PL!$B:$B,$B30,PL!$A:$A,$A30) -> 0 | R30: =SUMIFS(PL!W:W,PL!$B:$B,$B30,PL!$A:$A,$A30) -> 0 | S30: =SUMIFS(PL!X:X,PL!$B:$B,$B30,PL!$A:$A,$A30) -> 0 | T30: =SUMIFS(PL!Y:Y,PL!$B:$B,$B30,PL!$A:$A,$A30) -> 0 | U30: =SUMIFS(PL!Z:Z,PL!$B:$B,$B30,PL!$A:$A,$A30) -> 0 | V30: =SUMIFS(PL!AA:AA,PL!$B:$B,$B30,PL!$A:$A,$A30) -> 0 | W30: =SUMIFS(PL!AB:AB,PL!$B:$B,$B30,PL!$A:$A,$A30) -> 0 | X30: =SUMIFS(PL!AC:AC,PL!$B:$B,$B30,PL!$A:$A,$A30) -> 0 | Y30: =SUMIFS(PL!AD:AD,PL!$B:$B,$B30,PL!$A:$A,$A30) -> 0 | Z30: =SUMIFS(PL!AE:AE,PL!$B:$B,$B30,PL!$A:$A,$A30) -> 0 | AA30: =SUMIFS(PL!AF:AF,PL!$B:$B,$B30,PL!$A:$A,$A30) -> 0 | AB30: =SUMIFS(PL!AG:AG,PL!$B:$B,$B30,PL!$A:$A,$A30) -> 0 | AC30: =SUMIFS(PL!AH:AH,PL!$B:$B,$B30,PL!$A:$A,$A30) -> 0 | AD30: =SUMIFS(PL!AI:AI,PL!$B:$B,$B30,PL!$A:$A,$A30) -> 0 | AE30: =SUMIFS(PL!AJ:AJ,PL!$B:$B,$B30,PL!$A:$A,$A30) -> 0 | AF30: =SUMIFS(PL!AK:AK,PL!$B:$B,$B30,PL!$A:$A,$A30) -> 0 | AG30: =SUMIFS(PL!AL:AL,PL!$B:$B,$B30,PL!$A:$A,$A30) -> 0 | AH30: =SUMIFS(PL!AM:AM,PL!$B:$B,$B30,PL!$A:$A,$A30) -> 0 | AI30: =SUMIFS(PL!AN:AN,PL!$B:$B,$B30,PL!$A:$A,$A30) -> 0 | AJ30: =SUMIFS(PL!AS:AS,PL!$B:$B,$B30,PL!$A:$A,$A30) -> 0 | AK30: =SUMIFS(PL!AT:AT,PL!$B:$B,$B30,PL!$A:$A,$A30) -> 0 | AL30: =SUMIFS(PL!AU:AU,PL!$B:$B,$B30,PL!$A:$A,$A30) -> 0 | AM30: =SUMIFS(PL!AV:AV,PL!$B:$B,$B30,PL!$A:$A,$A30) -> 0
A31: Other | B31: Donations and Contributions | C31: =SUMIFS($G31:$BC31,$G$5:$BC$5,"<="&EOMONTH(C$5,0),$G$6:$BC$6,"<="&C$5) -> 0 | D31: =SUMIFS($G31:$AT31,$G$5:$AT$5,">"&EOMONTH(D$5,-12),$G$5:$AT$5,"<="&D$5) -> 0 | E31: =SUMIFS($G31:$AT31,$G$5:$AT$5,">"&EOMONTH(E$5,-12),$G$5:$AT$5,"<="&E$5) -> 0 | G31: =SUMIFS(PL!L:L,PL!$B:$B,$B31,PL!$A:$A,$A31) -> 0 | H31: =SUMIFS(PL!M:M,PL!$B:$B,$B31,PL!$A:$A,$A31) -> 0 | I31: =SUMIFS(PL!N:N,PL!$B:$B,$B31,PL!$A:$A,$A31) -> 0 | J31: =SUMIFS(PL!O:O,PL!$B:$B,$B31,PL!$A:$A,$A31) -> 0 | K31: =SUMIFS(PL!P:P,PL!$B:$B,$B31,PL!$A:$A,$A31) -> 0 | L31: =SUMIFS(PL!Q:Q,PL!$B:$B,$B31,PL!$A:$A,$A31) -> 0 | M31: =SUMIFS(PL!R:R,PL!$B:$B,$B31,PL!$A:$A,$A31) -> 0 | N31: =SUMIFS(PL!S:S,PL!$B:$B,$B31,PL!$A:$A,$A31) -> 0 | O31: =SUMIFS(PL!T:T,PL!$B:$B,$B31,PL!$A:$A,$A31) -> 0 | P31: =SUMIFS(PL!U:U,PL!$B:$B,$B31,PL!$A:$A,$A31) -> 0 | Q31: =SUMIFS(PL!V:V,PL!$B:$B,$B31,PL!$A:$A,$A31) -> 0 | R31: =SUMIFS(PL!W:W,PL!$B:$B,$B31,PL!$A:$A,$A31) -> 0 | S31: =SUMIFS(PL!X:X,PL!$B:$B,$B31,PL!$A:$A,$A31) -> 0 | T31: =SUMIFS(PL!Y:Y,PL!$B:$B,$B31,PL!$A:$A,$A31) -> 0 | U31: =SUMIFS(PL!Z:Z,PL!$B:$B,$B31,PL!$A:$A,$A31) -> 0 | V31: =SUMIFS(PL!AA:AA,PL!$B:$B,$B31,PL!$A:$A,$A31) -> 0 | W31: =SUMIFS(PL!AB:AB,PL!$B:$B,$B31,PL!$A:$A,$A31) -> 0 | X31: =SUMIFS(PL!AC:AC,PL!$B:$B,$B31,PL!$A:$A,$A31) -> 0 | Y31: =SUMIFS(PL!AD:AD,PL!$B:$B,$B31,PL!$A:$A,$A31) -> 0 | Z31: =SUMIFS(PL!AE:AE,PL!$B:$B,$B31,PL!$A:$A,$A31) -> 0 | AA31: =SUMIFS(PL!AF:AF,PL!$B:$B,$B31,PL!$A:$A,$A31) -> 0 | AB31: =SUMIFS(PL!AG:AG,PL!$B:$B,$B31,PL!$A:$A,$A31) -> 0 | AC31: =SUMIFS(PL!AH:AH,PL!$B:$B,$B31,PL!$A:$A,$A31) -> 0 | AD31: =SUMIFS(PL!AI:AI,PL!$B:$B,$B31,PL!$A:$A,$A31) -> 0 | AE31: =SUMIFS(PL!AJ:AJ,PL!$B:$B,$B31,PL!$A:$A,$A31) -> 0 | AF31: =SUMIFS(PL!AK:AK,PL!$B:$B,$B31,PL!$A:$A,$A31) -> 0 | AG31: =SUMIFS(PL!AL:AL,PL!$B:$B,$B31,PL!$A:$A,$A31) -> 0 | AH31: =SUMIFS(PL!AM:AM,PL!$B:$B,$B31,PL!$A:$A,$A31) -> 0 | AI31: =SUMIFS(PL!AN:AN,PL!$B:$B,$B31,PL!$A:$A,$A31) -> 0 | AJ31: =SUMIFS(PL!AS:AS,PL!$B:$B,$B31,PL!$A:$A,$A31) -> 0 | AK31: =SUMIFS(PL!AT:AT,PL!$B:$B,$B31,PL!$A:$A,$A31) -> 0 | AL31: =SUMIFS(PL!AU:AU,PL!$B:$B,$B31,PL!$A:$A,$A31) -> 0 | AM31: =SUMIFS(PL!AV:AV,PL!$B:$B,$B31,PL!$A:$A,$A31) -> 0
A32: Other | B32: Dues and Subscriptions | C32: =SUMIFS($G32:$BC32,$G$5:$BC$5,"<="&EOMONTH(C$5,0),$G$6:$BC$6,"<="&C$5) -> 0 | D32: =SUMIFS($G32:$AT32,$G$5:$AT$5,">"&EOMONTH(D$5,-12),$G$5:$AT$5,"<="&D$5) -> 0 | E32: =SUMIFS($G32:$AT32,$G$5:$AT$5,">"&EOMONTH(E$5,-12),$G$5:$AT$5,"<="&E$5) -> 0 | G32: =SUMIFS(PL!L:L,PL!$B:$B,$B32,PL!$A:$A,$A32) -> 0 | H32: =SUMIFS(PL!M:M,PL!$B:$B,$B32,PL!$A:$A,$A32) -> 0 | I32: =SUMIFS(PL!N:N,PL!$B:$B,$B32,PL!$A:$A,$A32) -> 0 | J32: =SUMIFS(PL!O:O,PL!$B:$B,$B32,PL!$A:$A,$A32) -> 0 | K32: =SUMIFS(PL!P:P,PL!$B:$B,$B32,PL!$A:$A,$A32) -> 0 | L32: =SUMIFS(PL!Q:Q,PL!$B:$B,$B32,PL!$A:$A,$A32) -> 0 | M32: =SUMIFS(PL!R:R,PL!$B:$B,$B32,PL!$A:$A,$A32) -> 0 | N32: =SUMIFS(PL!S:S,PL!$B:$B,$B32,PL!$A:$A,$A32) -> 0 | O32: =SUMIFS(PL!T:T,PL!$B:$B,$B32,PL!$A:$A,$A32) -> 0 | P32: =SUMIFS(PL!U:U,PL!$B:$B,$B32,PL!$A:$A,$A32) -> 0 | Q32: =SUMIFS(PL!V:V,PL!$B:$B,$B32,PL!$A:$A,$A32) -> 0 | R32: =SUMIFS(PL!W:W,PL!$B:$B,$B32,PL!$A:$A,$A32) -> 0 | S32: =SUMIFS(PL!X:X,PL!$B:$B,$B32,PL!$A:$A,$A32) -> 0 | T32: =SUMIFS(PL!Y:Y,PL!$B:$B,$B32,PL!$A:$A,$A32) -> 0 | U32: =SUMIFS(PL!Z:Z,PL!$B:$B,$B32,PL!$A:$A,$A32) -> 0 | V32: =SUMIFS(PL!AA:AA,PL!$B:$B,$B32,PL!$A:$A,$A32) -> 0 | W32: =SUMIFS(PL!AB:AB,PL!$B:$B,$B32,PL!$A:$A,$A32) -> 0 | X32: =SUMIFS(PL!AC:AC,PL!$B:$B,$B32,PL!$A:$A,$A32) -> 0 | Y32: =SUMIFS(PL!AD:AD,PL!$B:$B,$B32,PL!$A:$A,$A32) -> 0 | Z32: =SUMIFS(PL!AE:AE,PL!$B:$B,$B32,PL!$A:$A,$A32) -> 0 | AA32: =SUMIFS(PL!AF:AF,PL!$B:$B,$B32,PL!$A:$A,$A32) -> 0 | AB32: =SUMIFS(PL!AG:AG,PL!$B:$B,$B32,PL!$A:$A,$A32) -> 0 | AC32: =SUMIFS(PL!AH:AH,PL!$B:$B,$B32,PL!$A:$A,$A32) -> 0 | AD32: =SUMIFS(PL!AI:AI,PL!$B:$B,$B32,PL!$A:$A,$A32) -> 0 | AE32: =SUMIFS(PL!AJ:AJ,PL!$B:$B,$B32,PL!$A:$A,$A32) -> 0 | AF32: =SUMIFS(PL!AK:AK,PL!$B:$B,$B32,PL!$A:$A,$A32) -> 0 | AG32: =SUMIFS(PL!AL:AL,PL!$B:$B,$B32,PL!$A:$A,$A32) -> 0 | AH32: =SUMIFS(PL!AM:AM,PL!$B:$B,$B32,PL!$A:$A,$A32) -> 0 | AI32: =SUMIFS(PL!AN:AN,PL!$B:$B,$B32,PL!$A:$A,$A32) -> 0 | AJ32: =SUMIFS(PL!AS:AS,PL!$B:$B,$B32,PL!$A:$A,$A32) -> 0 | AK32: =SUMIFS(PL!AT:AT,PL!$B:$B,$B32,PL!$A:$A,$A32) -> 0 | AL32: =SUMIFS(PL!AU:AU,PL!$B:$B,$B32,PL!$A:$A,$A32) -> 0 | AM32: =SUMIFS(PL!AV:AV,PL!$B:$B,$B32,PL!$A:$A,$A32) -> 0
A33: Other | B33: Licenses and Permits | C33: =SUMIFS($G33:$BC33,$G$5:$BC$5,"<="&EOMONTH(C$5,0),$G$6:$BC$6,"<="&C$5) -> 0 | D33: =SUMIFS($G33:$AT33,$G$5:$AT$5,">"&EOMONTH(D$5,-12),$G$5:$AT$5,"<="&D$5) -> 0 | E33: =SUMIFS($G33:$AT33,$G$5:$AT$5,">"&EOMONTH(E$5,-12),$G$5:$AT$5,"<="&E$5) -> 0 | G33: =SUMIFS(PL!L:L,PL!$B:$B,$B33,PL!$A:$A,$A33) -> 0 | H33: =SUMIFS(PL!M:M,PL!$B:$B,$B33,PL!$A:$A,$A33) -> 0 | I33: =SUMIFS(PL!N:N,PL!$B:$B,$B33,PL!$A:$A,$A33) -> 0 | J33: =SUMIFS(PL!O:O,PL!$B:$B,$B33,PL!$A:$A,$A33) -> 0 | K33: =SUMIFS(PL!P:P,PL!$B:$B,$B33,PL!$A:$A,$A33) -> 0 | L33: =SUMIFS(PL!Q:Q,PL!$B:$B,$B33,PL!$A:$A,$A33) -> 0 | M33: =SUMIFS(PL!R:R,PL!$B:$B,$B33,PL!$A:$A,$A33) -> 0 | N33: =SUMIFS(PL!S:S,PL!$B:$B,$B33,PL!$A:$A,$A33) -> 0 | O33: =SUMIFS(PL!T:T,PL!$B:$B,$B33,PL!$A:$A,$A33) -> 0 | P33: =SUMIFS(PL!U:U,PL!$B:$B,$B33,PL!$A:$A,$A33) -> 0 | Q33: =SUMIFS(PL!V:V,PL!$B:$B,$B33,PL!$A:$A,$A33) -> 0 | R33: =SUMIFS(PL!W:W,PL!$B:$B,$B33,PL!$A:$A,$A33) -> 0 | S33: =SUMIFS(PL!X:X,PL!$B:$B,$B33,PL!$A:$A,$A33) -> 0 | T33: =SUMIFS(PL!Y:Y,PL!$B:$B,$B33,PL!$A:$A,$A33) -> 0 | U33: =SUMIFS(PL!Z:Z,PL!$B:$B,$B33,PL!$A:$A,$A33) -> 0 | V33: =SUMIFS(PL!AA:AA,PL!$B:$B,$B33,PL!$A:$A,$A33) -> 0 | W33: =SUMIFS(PL!AB:AB,PL!$B:$B,$B33,PL!$A:$A,$A33) -> 0 | X33: =SUMIFS(PL!AC:AC,PL!$B:$B,$B33,PL!$A:$A,$A33) -> 0 | Y33: =SUMIFS(PL!AD:AD,PL!$B:$B,$B33,PL!$A:$A,$A33) -> 0 | Z33: =SUMIFS(PL!AE:AE,PL!$B:$B,$B33,PL!$A:$A,$A33) -> 0 | AA33: =SUMIFS(PL!AF:AF,PL!$B:$B,$B33,PL!$A:$A,$A33) -> 0 | AB33: =SUMIFS(PL!AG:AG,PL!$B:$B,$B33,PL!$A:$A,$A33) -> 0 | AC33: =SUMIFS(PL!AH:AH,PL!$B:$B,$B33,PL!$A:$A,$A33) -> 0 | AD33: =SUMIFS(PL!AI:AI,PL!$B:$B,$B33,PL!$A:$A,$A33) -> 0 | AE33: =SUMIFS(PL!AJ:AJ,PL!$B:$B,$B33,PL!$A:$A,$A33) -> 0 | AF33: =SUMIFS(PL!AK:AK,PL!$B:$B,$B33,PL!$A:$A,$A33) -> 0 | AG33: =SUMIFS(PL!AL:AL,PL!$B:$B,$B33,PL!$A:$A,$A33) -> 0 | AH33: =SUMIFS(PL!AM:AM,PL!$B:$B,$B33,PL!$A:$A,$A33) -> 0 | AI33: =SUMIFS(PL!AN:AN,PL!$B:$B,$B33,PL!$A:$A,$A33) -> 0 | AJ33: =SUMIFS(PL!AS:AS,PL!$B:$B,$B33,PL!$A:$A,$A33) -> 0 | AK33: =SUMIFS(PL!AT:AT,PL!$B:$B,$B33,PL!$A:$A,$A33) -> 0 | AL33: =SUMIFS(PL!AU:AU,PL!$B:$B,$B33,PL!$A:$A,$A33) -> 0 | AM33: =SUMIFS(PL!AV:AV,PL!$B:$B,$B33,PL!$A:$A,$A33) -> 0
A34: Other | B34: Meals and Entertainment | C34: =SUMIFS($G34:$BC34,$G$5:$BC$5,"<="&EOMONTH(C$5,0),$G$6:$BC$6,"<="&C$5) -> 0 | D34: =SUMIFS($G34:$AT34,$G$5:$AT$5,">"&EOMONTH(D$5,-12),$G$5:$AT$5,"<="&D$5) -> 0 | E34: =SUMIFS($G34:$AT34,$G$5:$AT$5,">"&EOMONTH(E$5,-12),$G$5:$AT$5,"<="&E$5) -> 0 | G34: =SUMIFS(PL!L:L,PL!$B:$B,$B34,PL!$A:$A,$A34) -> 0 | H34: =SUMIFS(PL!M:M,PL!$B:$B,$B34,PL!$A:$A,$A34) -> 0 | I34: =SUMIFS(PL!N:N,PL!$B:$B,$B34,PL!$A:$A,$A34) -> 0 | J34: =SUMIFS(PL!O:O,PL!$B:$B,$B34,PL!$A:$A,$A34) -> 0 | K34: =SUMIFS(PL!P:P,PL!$B:$B,$B34,PL!$A:$A,$A34) -> 0 | L34: =SUMIFS(PL!Q:Q,PL!$B:$B,$B34,PL!$A:$A,$A34) -> 0 | M34: =SUMIFS(PL!R:R,PL!$B:$B,$B34,PL!$A:$A,$A34) -> 0 | N34: =SUMIFS(PL!S:S,PL!$B:$B,$B34,PL!$A:$A,$A34) -> 0 | O34: =SUMIFS(PL!T:T,PL!$B:$B,$B34,PL!$A:$A,$A34) -> 0 | P34: =SUMIFS(PL!U:U,PL!$B:$B,$B34,PL!$A:$A,$A34) -> 0 | Q34: =SUMIFS(PL!V:V,PL!$B:$B,$B34,PL!$A:$A,$A34) -> 0 | R34: =SUMIFS(PL!W:W,PL!$B:$B,$B34,PL!$A:$A,$A34) -> 0 | S34: =SUMIFS(PL!X:X,PL!$B:$B,$B34,PL!$A:$A,$A34) -> 0 | T34: =SUMIFS(PL!Y:Y,PL!$B:$B,$B34,PL!$A:$A,$A34) -> 0 | U34: =SUMIFS(PL!Z:Z,PL!$B:$B,$B34,PL!$A:$A,$A34) -> 0 | V34: =SUMIFS(PL!AA:AA,PL!$B:$B,$B34,PL!$A:$A,$A34) -> 0 | W34: =SUMIFS(PL!AB:AB,PL!$B:$B,$B34,PL!$A:$A,$A34) -> 0 | X34: =SUMIFS(PL!AC:AC,PL!$B:$B,$B34,PL!$A:$A,$A34) -> 0 | Y34: =SUMIFS(PL!AD:AD,PL!$B:$B,$B34,PL!$A:$A,$A34) -> 0 | Z34: =SUMIFS(PL!AE:AE,PL!$B:$B,$B34,PL!$A:$A,$A34) -> 0 | AA34: =SUMIFS(PL!AF:AF,PL!$B:$B,$B34,PL!$A:$A,$A34) -> 0 | AB34: =SUMIFS(PL!AG:AG,PL!$B:$B,$B34,PL!$A:$A,$A34) -> 0 | AC34: =SUMIFS(PL!AH:AH,PL!$B:$B,$B34,PL!$A:$A,$A34) -> 0 | AD34: =SUMIFS(PL!AI:AI,PL!$B:$B,$B34,PL!$A:$A,$A34) -> 0 | AE34: =SUMIFS(PL!AJ:AJ,PL!$B:$B,$B34,PL!$A:$A,$A34) -> 0 | AF34: =SUMIFS(PL!AK:AK,PL!$B:$B,$B34,PL!$A:$A,$A34) -> 0 | AG34: =SUMIFS(PL!AL:AL,PL!$B:$B,$B34,PL!$A:$A,$A34) -> 0 | AH34: =SUMIFS(PL!AM:AM,PL!$B:$B,$B34,PL!$A:$A,$A34) -> 0 | AI34: =SUMIFS(PL!AN:AN,PL!$B:$B,$B34,PL!$A:$A,$A34) -> 0 | AJ34: =SUMIFS(PL!AS:AS,PL!$B:$B,$B34,PL!$A:$A,$A34) -> 0 | AK34: =SUMIFS(PL!AT:AT,PL!$B:$B,$B34,PL!$A:$A,$A34) -> 0 | AL34: =SUMIFS(PL!AU:AU,PL!$B:$B,$B34,PL!$A:$A,$A34) -> 0 | AM34: =SUMIFS(PL!AV:AV,PL!$B:$B,$B34,PL!$A:$A,$A34) -> 0
A35: Other | B35: Merchant Fees | C35: =SUMIFS($G35:$BC35,$G$5:$BC$5,"<="&EOMONTH(C$5,0),$G$6:$BC$6,"<="&C$5) -> 0 | D35: =SUMIFS($G35:$AT35,$G$5:$AT$5,">"&EOMONTH(D$5,-12),$G$5:$AT$5,"<="&D$5) -> 0 | E35: =SUMIFS($G35:$AT35,$G$5:$AT$5,">"&EOMONTH(E$5,-12),$G$5:$AT$5,"<="&E$5) -> 0 | G35: =SUMIFS(PL!L:L,PL!$B:$B,$B35,PL!$A:$A,$A35) -> 0 | H35: =SUMIFS(PL!M:M,PL!$B:$B,$B35,PL!$A:$A,$A35) -> 0 | I35: =SUMIFS(PL!N:N,PL!$B:$B,$B35,PL!$A:$A,$A35) -> 0 | J35: =SUMIFS(PL!O:O,PL!$B:$B,$B35,PL!$A:$A,$A35) -> 0 | K35: =SUMIFS(PL!P:P,PL!$B:$B,$B35,PL!$A:$A,$A35) -> 0 | L35: =SUMIFS(PL!Q:Q,PL!$B:$B,$B35,PL!$A:$A,$A35) -> 0 | M35: =SUMIFS(PL!R:R,PL!$B:$B,$B35,PL!$A:$A,$A35) -> 0 | N35: =SUMIFS(PL!S:S,PL!$B:$B,$B35,PL!$A:$A,$A35) -> 0 | O35: =SUMIFS(PL!T:T,PL!$B:$B,$B35,PL!$A:$A,$A35) -> 0 | P35: =SUMIFS(PL!U:U,PL!$B:$B,$B35,PL!$A:$A,$A35) -> 0 | Q35: =SUMIFS(PL!V:V,PL!$B:$B,$B35,PL!$A:$A,$A35) -> 0 | R35: =SUMIFS(PL!W:W,PL!$B:$B,$B35,PL!$A:$A,$A35) -> 0 | S35: =SUMIFS(PL!X:X,PL!$B:$B,$B35,PL!$A:$A,$A35) -> 0 | T35: =SUMIFS(PL!Y:Y,PL!$B:$B,$B35,PL!$A:$A,$A35) -> 0 | U35: =SUMIFS(PL!Z:Z,PL!$B:$B,$B35,PL!$A:$A,$A35) -> 0 | V35: =SUMIFS(PL!AA:AA,PL!$B:$B,$B35,PL!$A:$A,$A35) -> 0 | W35: =SUMIFS(PL!AB:AB,PL!$B:$B,$B35,PL!$A:$A,$A35) -> 0 | X35: =SUMIFS(PL!AC:AC,PL!$B:$B,$B35,PL!$A:$A,$A35) -> 0 | Y35: =SUMIFS(PL!AD:AD,PL!$B:$B,$B35,PL!$A:$A,$A35) -> 0 | Z35: =SUMIFS(PL!AE:AE,PL!$B:$B,$B35,PL!$A:$A,$A35) -> 0 | AA35: =SUMIFS(PL!AF:AF,PL!$B:$B,$B35,PL!$A:$A,$A35) -> 0 | AB35: =SUMIFS(PL!AG:AG,PL!$B:$B,$B35,PL!$A:$A,$A35) -> 0 | AC35: =SUMIFS(PL!AH:AH,PL!$B:$B,$B35,PL!$A:$A,$A35) -> 0 | AD35: =SUMIFS(PL!AI:AI,PL!$B:$B,$B35,PL!$A:$A,$A35) -> 0 | AE35: =SUMIFS(PL!AJ:AJ,PL!$B:$B,$B35,PL!$A:$A,$A35) -> 0 | AF35: =SUMIFS(PL!AK:AK,PL!$B:$B,$B35,PL!$A:$A,$A35) -> 0 | AG35: =SUMIFS(PL!AL:AL,PL!$B:$B,$B35,PL!$A:$A,$A35) -> 0 | AH35: =SUMIFS(PL!AM:AM,PL!$B:$B,$B35,PL!$A:$A,$A35) -> 0 | AI35: =SUMIFS(PL!AN:AN,PL!$B:$B,$B35,PL!$A:$A,$A35) -> 0 | AJ35: =SUMIFS(PL!AS:AS,PL!$B:$B,$B35,PL!$A:$A,$A35) -> 0 | AK35: =SUMIFS(PL!AT:AT,PL!$B:$B,$B35,PL!$A:$A,$A35) -> 0 | AL35: =SUMIFS(PL!AU:AU,PL!$B:$B,$B35,PL!$A:$A,$A35) -> 0 | AM35: =SUMIFS(PL!AV:AV,PL!$B:$B,$B35,PL!$A:$A,$A35) -> 0
A36: Other | B36: Office Expense | C36: =SUMIFS($G36:$BC36,$G$5:$BC$5,"<="&EOMONTH(C$5,0),$G$6:$BC$6,"<="&C$5) -> 0 | D36: =SUMIFS($G36:$AT36,$G$5:$AT$5,">"&EOMONTH(D$5,-12),$G$5:$AT$5,"<="&D$5) -> 0 | E36: =SUMIFS($G36:$AT36,$G$5:$AT$5,">"&EOMONTH(E$5,-12),$G$5:$AT$5,"<="&E$5) -> 0 | G36: =SUMIFS(PL!L:L,PL!$B:$B,$B36,PL!$A:$A,$A36) -> 0 | H36: =SUMIFS(PL!M:M,PL!$B:$B,$B36,PL!$A:$A,$A36) -> 0 | I36: =SUMIFS(PL!N:N,PL!$B:$B,$B36,PL!$A:$A,$A36) -> 0 | J36: =SUMIFS(PL!O:O,PL!$B:$B,$B36,PL!$A:$A,$A36) -> 0 | K36: =SUMIFS(PL!P:P,PL!$B:$B,$B36,PL!$A:$A,$A36) -> 0 | L36: =SUMIFS(PL!Q:Q,PL!$B:$B,$B36,PL!$A:$A,$A36) -> 0 | M36: =SUMIFS(PL!R:R,PL!$B:$B,$B36,PL!$A:$A,$A36) -> 0 | N36: =SUMIFS(PL!S:S,PL!$B:$B,$B36,PL!$A:$A,$A36) -> 0 | O36: =SUMIFS(PL!T:T,PL!$B:$B,$B36,PL!$A:$A,$A36) -> 0 | P36: =SUMIFS(PL!U:U,PL!$B:$B,$B36,PL!$A:$A,$A36) -> 0 | Q36: =SUMIFS(PL!V:V,PL!$B:$B,$B36,PL!$A:$A,$A36) -> 0 | R36: =SUMIFS(PL!W:W,PL!$B:$B,$B36,PL!$A:$A,$A36) -> 0 | S36: =SUMIFS(PL!X:X,PL!$B:$B,$B36,PL!$A:$A,$A36) -> 0 | T36: =SUMIFS(PL!Y:Y,PL!$B:$B,$B36,PL!$A:$A,$A36) -> 0 | U36: =SUMIFS(PL!Z:Z,PL!$B:$B,$B36,PL!$A:$A,$A36) -> 0 | V36: =SUMIFS(PL!AA:AA,PL!$B:$B,$B36,PL!$A:$A,$A36) -> 0 | W36: =SUMIFS(PL!AB:AB,PL!$B:$B,$B36,PL!$A:$A,$A36) -> 0 | X36: =SUMIFS(PL!AC:AC,PL!$B:$B,$B36,PL!$A:$A,$A36) -> 0 | Y36: =SUMIFS(PL!AD:AD,PL!$B:$B,$B36,PL!$A:$A,$A36) -> 0 | Z36: =SUMIFS(PL!AE:AE,PL!$B:$B,$B36,PL!$A:$A,$A36) -> 0 | AA36: =SUMIFS(PL!AF:AF,PL!$B:$B,$B36,PL!$A:$A,$A36) -> 0 | AB36: =SUMIFS(PL!AG:AG,PL!$B:$B,$B36,PL!$A:$A,$A36) -> 0 | AC36: =SUMIFS(PL!AH:AH,PL!$B:$B,$B36,PL!$A:$A,$A36) -> 0 | AD36: =SUMIFS(PL!AI:AI,PL!$B:$B,$B36,PL!$A:$A,$A36) -> 0 | AE36: =SUMIFS(PL!AJ:AJ,PL!$B:$B,$B36,PL!$A:$A,$A36) -> 0 | AF36: =SUMIFS(PL!AK:AK,PL!$B:$B,$B36,PL!$A:$A,$A36) -> 0 | AG36: =SUMIFS(PL!AL:AL,PL!$B:$B,$B36,PL!$A:$A,$A36) -> 0 | AH36: =SUMIFS(PL!AM:AM,PL!$B:$B,$B36,PL!$A:$A,$A36) -> 0 | AI36: =SUMIFS(PL!AN:AN,PL!$B:$B,$B36,PL!$A:$A,$A36) -> 0 | AJ36: =SUMIFS(PL!AS:AS,PL!$B:$B,$B36,PL!$A:$A,$A36) -> 0 | AK36: =SUMIFS(PL!AT:AT,PL!$B:$B,$B36,PL!$A:$A,$A36) -> 0 | AL36: =SUMIFS(PL!AU:AU,PL!$B:$B,$B36,PL!$A:$A,$A36) -> 0 | AM36: =SUMIFS(PL!AV:AV,PL!$B:$B,$B36,PL!$A:$A,$A36) -> 0
A37: Other | B37: Outside Services | C37: =SUMIFS($G37:$BC37,$G$5:$BC$5,"<="&EOMONTH(C$5,0),$G$6:$BC$6,"<="&C$5) -> 0 | D37: =SUMIFS($G37:$AT37,$G$5:$AT$5,">"&EOMONTH(D$5,-12),$G$5:$AT$5,"<="&D$5) -> 0 | E37: =SUMIFS($G37:$AT37,$G$5:$AT$5,">"&EOMONTH(E$5,-12),$G$5:$AT$5,"<="&E$5) -> 0 | G37: =SUMIFS(PL!L:L,PL!$B:$B,$B37,PL!$A:$A,$A37) -> 0 | H37: =SUMIFS(PL!M:M,PL!$B:$B,$B37,PL!$A:$A,$A37) -> 0 | I37: =SUMIFS(PL!N:N,PL!$B:$B,$B37,PL!$A:$A,$A37) -> 0 | J37: =SUMIFS(PL!O:O,PL!$B:$B,$B37,PL!$A:$A,$A37) -> 0 | K37: =SUMIFS(PL!P:P,PL!$B:$B,$B37,PL!$A:$A,$A37) -> 0 | L37: =SUMIFS(PL!Q:Q,PL!$B:$B,$B37,PL!$A:$A,$A37) -> 0 | M37: =SUMIFS(PL!R:R,PL!$B:$B,$B37,PL!$A:$A,$A37) -> 0 | N37: =SUMIFS(PL!S:S,PL!$B:$B,$B37,PL!$A:$A,$A37) -> 0 | O37: =SUMIFS(PL!T:T,PL!$B:$B,$B37,PL!$A:$A,$A37) -> 0 | P37: =SUMIFS(PL!U:U,PL!$B:$B,$B37,PL!$A:$A,$A37) -> 0 | Q37: =SUMIFS(PL!V:V,PL!$B:$B,$B37,PL!$A:$A,$A37) -> 0 | R37: =SUMIFS(PL!W:W,PL!$B:$B,$B37,PL!$A:$A,$A37) -> 0 | S37: =SUMIFS(PL!X:X,PL!$B:$B,$B37,PL!$A:$A,$A37) -> 0 | T37: =SUMIFS(PL!Y:Y,PL!$B:$B,$B37,PL!$A:$A,$A37) -> 0 | U37: =SUMIFS(PL!Z:Z,PL!$B:$B,$B37,PL!$A:$A,$A37) -> 0 | V37: =SUMIFS(PL!AA:AA,PL!$B:$B,$B37,PL!$A:$A,$A37) -> 0 | W37: =SUMIFS(PL!AB:AB,PL!$B:$B,$B37,PL!$A:$A,$A37) -> 0 | X37: =SUMIFS(PL!AC:AC,PL!$B:$B,$B37,PL!$A:$A,$A37) -> 0 | Y37: =SUMIFS(PL!AD:AD,PL!$B:$B,$B37,PL!$A:$A,$A37) -> 0 | Z37: =SUMIFS(PL!AE:AE,PL!$B:$B,$B37,PL!$A:$A,$A37) -> 0 | AA37: =SUMIFS(PL!AF:AF,PL!$B:$B,$B37,PL!$A:$A,$A37) -> 0 | AB37: =SUMIFS(PL!AG:AG,PL!$B:$B,$B37,PL!$A:$A,$A37) -> 0 | AC37: =SUMIFS(PL!AH:AH,PL!$B:$B,$B37,PL!$A:$A,$A37) -> 0 | AD37: =SUMIFS(PL!AI:AI,PL!$B:$B,$B37,PL!$A:$A,$A37) -> 0 | AE37: =SUMIFS(PL!AJ:AJ,PL!$B:$B,$B37,PL!$A:$A,$A37) -> 0 | AF37: =SUMIFS(PL!AK:AK,PL!$B:$B,$B37,PL!$A:$A,$A37) -> 0 | AG37: =SUMIFS(PL!AL:AL,PL!$B:$B,$B37,PL!$A:$A,$A37) -> 0 | AH37: =SUMIFS(PL!AM:AM,PL!$B:$B,$B37,PL!$A:$A,$A37) -> 0 | AI37: =SUMIFS(PL!AN:AN,PL!$B:$B,$B37,PL!$A:$A,$A37) -> 0 | AJ37: =SUMIFS(PL!AS:AS,PL!$B:$B,$B37,PL!$A:$A,$A37) -> 0 | AK37: =SUMIFS(PL!AT:AT,PL!$B:$B,$B37,PL!$A:$A,$A37) -> 0 | AL37: =SUMIFS(PL!AU:AU,PL!$B:$B,$B37,PL!$A:$A,$A37) -> 0 | AM37: =SUMIFS(PL!AV:AV,PL!$B:$B,$B37,PL!$A:$A,$A37) -> 0
A38: Other | B38: Postage and Shipping | C38: =SUMIFS($G38:$BC38,$G$5:$BC$5,"<="&EOMONTH(C$5,0),$G$6:$BC$6,"<="&C$5) -> 0 | D38: =SUMIFS($G38:$AT38,$G$5:$AT$5,">"&EOMONTH(D$5,-12),$G$5:$AT$5,"<="&D$5) -> 0 | E38: =SUMIFS($G38:$AT38,$G$5:$AT$5,">"&EOMONTH(E$5,-12),$G$5:$AT$5,"<="&E$5) -> 0 | G38: =SUMIFS(PL!L:L,PL!$B:$B,$B38,PL!$A:$A,$A38) -> 0 | H38: =SUMIFS(PL!M:M,PL!$B:$B,$B38,PL!$A:$A,$A38) -> 0 | I38: =SUMIFS(PL!N:N,PL!$B:$B,$B38,PL!$A:$A,$A38) -> 0 | J38: =SUMIFS(PL!O:O,PL!$B:$B,$B38,PL!$A:$A,$A38) -> 0 | K38: =SUMIFS(PL!P:P,PL!$B:$B,$B38,PL!$A:$A,$A38) -> 0 | L38: =SUMIFS(PL!Q:Q,PL!$B:$B,$B38,PL!$A:$A,$A38) -> 0 | M38: =SUMIFS(PL!R:R,PL!$B:$B,$B38,PL!$A:$A,$A38) -> 0 | N38: =SUMIFS(PL!S:S,PL!$B:$B,$B38,PL!$A:$A,$A38) -> 0 | O38: =SUMIFS(PL!T:T,PL!$B:$B,$B38,PL!$A:$A,$A38) -> 0 | P38: =SUMIFS(PL!U:U,PL!$B:$B,$B38,PL!$A:$A,$A38) -> 0 | Q38: =SUMIFS(PL!V:V,PL!$B:$B,$B38,PL!$A:$A,$A38) -> 0 | R38: =SUMIFS(PL!W:W,PL!$B:$B,$B38,PL!$A:$A,$A38) -> 0 | S38: =SUMIFS(PL!X:X,PL!$B:$B,$B38,PL!$A:$A,$A38) -> 0 | T38: =SUMIFS(PL!Y:Y,PL!$B:$B,$B38,PL!$A:$A,$A38) -> 0 | U38: =SUMIFS(PL!Z:Z,PL!$B:$B,$B38,PL!$A:$A,$A38) -> 0 | V38: =SUMIFS(PL!AA:AA,PL!$B:$B,$B38,PL!$A:$A,$A38) -> 0 | W38: =SUMIFS(PL!AB:AB,PL!$B:$B,$B38,PL!$A:$A,$A38) -> 0 | X38: =SUMIFS(PL!AC:AC,PL!$B:$B,$B38,PL!$A:$A,$A38) -> 0 | Y38: =SUMIFS(PL!AD:AD,PL!$B:$B,$B38,PL!$A:$A,$A38) -> 0 | Z38: =SUMIFS(PL!AE:AE,PL!$B:$B,$B38,PL!$A:$A,$A38) -> 0 | AA38: =SUMIFS(PL!AF:AF,PL!$B:$B,$B38,PL!$A:$A,$A38) -> 0 | AB38: =SUMIFS(PL!AG:AG,PL!$B:$B,$B38,PL!$A:$A,$A38) -> 0 | AC38: =SUMIFS(PL!AH:AH,PL!$B:$B,$B38,PL!$A:$A,$A38) -> 0 | AD38: =SUMIFS(PL!AI:AI,PL!$B:$B,$B38,PL!$A:$A,$A38) -> 0 | AE38: =SUMIFS(PL!AJ:AJ,PL!$B:$B,$B38,PL!$A:$A,$A38) -> 0 | AF38: =SUMIFS(PL!AK:AK,PL!$B:$B,$B38,PL!$A:$A,$A38) -> 0 | AG38: =SUMIFS(PL!AL:AL,PL!$B:$B,$B38,PL!$A:$A,$A38) -> 0 | AH38: =SUMIFS(PL!AM:AM,PL!$B:$B,$B38,PL!$A:$A,$A38) -> 0 | AI38: =SUMIFS(PL!AN:AN,PL!$B:$B,$B38,PL!$A:$A,$A38) -> 0 | AJ38: =SUMIFS(PL!AS:AS,PL!$B:$B,$B38,PL!$A:$A,$A38) -> 0 | AK38: =SUMIFS(PL!AT:AT,PL!$B:$B,$B38,PL!$A:$A,$A38) -> 0 | AL38: =SUMIFS(PL!AU:AU,PL!$B:$B,$B38,PL!$A:$A,$A38) -> 0 | AM38: =SUMIFS(PL!AV:AV,PL!$B:$B,$B38,PL!$A:$A,$A38) -> 0
A39: Other | B39: Professional Fees | C39: =SUMIFS($G39:$BC39,$G$5:$BC$5,"<="&EOMONTH(C$5,0),$G$6:$BC$6,"<="&C$5) -> 0 | D39: =SUMIFS($G39:$AT39,$G$5:$AT$5,">"&EOMONTH(D$5,-12),$G$5:$AT$5,"<="&D$5) -> 0 | E39: =SUMIFS($G39:$AT39,$G$5:$AT$5,">"&EOMONTH(E$5,-12),$G$5:$AT$5,"<="&E$5) -> 0 | G39: =SUMIFS(PL!L:L,PL!$B:$B,$B39,PL!$A:$A,$A39) -> 0 | H39: =SUMIFS(PL!M:M,PL!$B:$B,$B39,PL!$A:$A,$A39) -> 0 | I39: =SUMIFS(PL!N:N,PL!$B:$B,$B39,PL!$A:$A,$A39) -> 0 | J39: =SUMIFS(PL!O:O,PL!$B:$B,$B39,PL!$A:$A,$A39) -> 0 | K39: =SUMIFS(PL!P:P,PL!$B:$B,$B39,PL!$A:$A,$A39) -> 0 | L39: =SUMIFS(PL!Q:Q,PL!$B:$B,$B39,PL!$A:$A,$A39) -> 0 | M39: =SUMIFS(PL!R:R,PL!$B:$B,$B39,PL!$A:$A,$A39) -> 0 | N39: =SUMIFS(PL!S:S,PL!$B:$B,$B39,PL!$A:$A,$A39) -> 0 | O39: =SUMIFS(PL!T:T,PL!$B:$B,$B39,PL!$A:$A,$A39) -> 0 | P39: =SUMIFS(PL!U:U,PL!$B:$B,$B39,PL!$A:$A,$A39) -> 0 | Q39: =SUMIFS(PL!V:V,PL!$B:$B,$B39,PL!$A:$A,$A39) -> 0 | R39: =SUMIFS(PL!W:W,PL!$B:$B,$B39,PL!$A:$A,$A39) -> 0 | S39: =SUMIFS(PL!X:X,PL!$B:$B,$B39,PL!$A:$A,$A39) -> 0 | T39: =SUMIFS(PL!Y:Y,PL!$B:$B,$B39,PL!$A:$A,$A39) -> 0 | U39: =SUMIFS(PL!Z:Z,PL!$B:$B,$B39,PL!$A:$A,$A39) -> 0 | V39: =SUMIFS(PL!AA:AA,PL!$B:$B,$B39,PL!$A:$A,$A39) -> 0 | W39: =SUMIFS(PL!AB:AB,PL!$B:$B,$B39,PL!$A:$A,$A39) -> 0 | X39: =SUMIFS(PL!AC:AC,PL!$B:$B,$B39,PL!$A:$A,$A39) -> 0 | Y39: =SUMIFS(PL!AD:AD,PL!$B:$B,$B39,PL!$A:$A,$A39) -> 0 | Z39: =SUMIFS(PL!AE:AE,PL!$B:$B,$B39,PL!$A:$A,$A39) -> 0 | AA39: =SUMIFS(PL!AF:AF,PL!$B:$B,$B39,PL!$A:$A,$A39) -> 0 | AB39: =SUMIFS(PL!AG:AG,PL!$B:$B,$B39,PL!$A:$A,$A39) -> 0 | AC39: =SUMIFS(PL!AH:AH,PL!$B:$B,$B39,PL!$A:$A,$A39) -> 0 | AD39: =SUMIFS(PL!AI:AI,PL!$B:$B,$B39,PL!$A:$A,$A39) -> 0 | AE39: =SUMIFS(PL!AJ:AJ,PL!$B:$B,$B39,PL!$A:$A,$A39) -> 0 | AF39: =SUMIFS(PL!AK:AK,PL!$B:$B,$B39,PL!$A:$A,$A39) -> 0 | AG39: =SUMIFS(PL!AL:AL,PL!$B:$B,$B39,PL!$A:$A,$A39) -> 0 | AH39: =SUMIFS(PL!AM:AM,PL!$B:$B,$B39,PL!$A:$A,$A39) -> 0 | AI39: =SUMIFS(PL!AN:AN,PL!$B:$B,$B39,PL!$A:$A,$A39) -> 0 | AJ39: =SUMIFS(PL!AS:AS,PL!$B:$B,$B39,PL!$A:$A,$A39) -> 0 | AK39: =SUMIFS(PL!AT:AT,PL!$B:$B,$B39,PL!$A:$A,$A39) -> 0 | AL39: =SUMIFS(PL!AU:AU,PL!$B:$B,$B39,PL!$A:$A,$A39) -> 0 | AM39: =SUMIFS(PL!AV:AV,PL!$B:$B,$B39,PL!$A:$A,$A39) -> 0
... A42: Other | B42: Uniforms Expense | C42: =SUMIFS($G42:$BC42,$G$5:$BC$5,"<="&EOMONTH(C$5,0),$G$6:$BC$6,"<="&C$5) -> 0 | D42: =SUMIFS($G42:$AT42,$G$5:$AT$5,">"&EOMONTH(D$5,-12),$G$5:$AT$5,"<="&D$5) -> 0 | E42: =SUMIFS($G42:$AT42,$G$5:$AT$5,">"&EOMONTH(E$5,-12),$G$5:$AT$5,"<="&E$5) -> 0 | G42: =SUMIFS(PL!L:L,PL!$B:$B,$B42,PL!$A:$A,$A42) -> 0 | H42: =SUMIFS(PL!M:M,PL!$B:$B,$B42,PL!$A:$A,$A42) -> 0 | I42: =SUMIFS(PL!N:N,PL!$B:$B,$B42,PL!$A:$A,$A42) -> 0 | J42: =SUMIFS(PL!O:O,PL!$B:$B,$B42,PL!$A:$A,$A42) -> 0 | K42: =SUMIFS(PL!P:P,PL!$B:$B,$B42,PL!$A:$A,$A42) -> 0 | L42: =SUMIFS(PL!Q:Q,PL!$B:$B,$B42,PL!$A:$A,$A42) -> 0 | M42: =SUMIFS(PL!R:R,PL!$B:$B,$B42,PL!$A:$A,$A42) -> 0 | N42: =SUMIFS(PL!S:S,PL!$B:$B,$B42,PL!$A:$A,$A42) -> 0 | O42: =SUMIFS(PL!T:T,PL!$B:$B,$B42,PL!$A:$A,$A42) -> 0 | P42: =SUMIFS(PL!U:U,PL!$B:$B,$B42,PL!$A:$A,$A42) -> 0 | Q42: =SUMIFS(PL!V:V,PL!$B:$B,$B42,PL!$A:$A,$A42) -> 0 | R42: =SUMIFS(PL!W:W,PL!$B:$B,$B42,PL!$A:$A,$A42) -> 0 | S42: =SUMIFS(PL!X:X,PL!$B:$B,$B42,PL!$A:$A,$A42) -> 0 | T42: =SUMIFS(PL!Y:Y,PL!$B:$B,$B42,PL!$A:$A,$A42) -> 0 | U42: =SUMIFS(PL!Z:Z,PL!$B:$B,$B42,PL!$A:$A,$A42) -> 0 | V42: =SUMIFS(PL!AA:AA,PL!$B:$B,$B42,PL!$A:$A,$A42) -> 0 | W42: =SUMIFS(PL!AB:AB,PL!$B:$B,$B42,PL!$A:$A,$A42) -> 0 | X42: =SUMIFS(PL!AC:AC,PL!$B:$B,$B42,PL!$A:$A,$A42) -> 0 | Y42: =SUMIFS(PL!AD:AD,PL!$B:$B,$B42,PL!$A:$A,$A42) -> 0 | Z42: =SUMIFS(PL!AE:AE,PL!$B:$B,$B42,PL!$A:$A,$A42) -> 0 | AA42: =SUMIFS(PL!AF:AF,PL!$B:$B,$B42,PL!$A:$A,$A42) -> 0 | AB42: =SUMIFS(PL!AG:AG,PL!$B:$B,$B42,PL!$A:$A,$A42) -> 0 | AC42: =SUMIFS(PL!AH:AH,PL!$B:$B,$B42,PL!$A:$A,$A42) -> 0 | AD42: =SUMIFS(PL!AI:AI,PL!$B:$B,$B42,PL!$A:$A,$A42) -> 0 | AE42: =SUMIFS(PL!AJ:AJ,PL!$B:$B,$B42,PL!$A:$A,$A42) -> 0 | AF42: =SUMIFS(PL!AK:AK,PL!$B:$B,$B42,PL!$A:$A,$A42) -> 0 | AG42: =SUMIFS(PL!AL:AL,PL!$B:$B,$B42,PL!$A:$A,$A42) -> 0 | AH42: =SUMIFS(PL!AM:AM,PL!$B:$B,$B42,PL!$A:$A,$A42) -> 0 | AI42: =SUMIFS(PL!AN:AN,PL!$B:$B,$B42,PL!$A:$A,$A42) -> 0 | AJ42: =SUMIFS(PL!AS:AS,PL!$B:$B,$B42,PL!$A:$A,$A42) -> 0 | AK42: =SUMIFS(PL!AT:AT,PL!$B:$B,$B42,PL!$A:$A,$A42) -> 0 | AL42: =SUMIFS(PL!AU:AU,PL!$B:$B,$B42,PL!$A:$A,$A42) -> 0 | AM42: =SUMIFS(PL!AV:AV,PL!$B:$B,$B42,PL!$A:$A,$A42) -> 0
B43: Practice-level EBITDA | C43: =C11-SUBTOTAL(9,C20,C25:C27) -> 0 | D43: =D11-SUBTOTAL(9,D20,D25:D27) -> 0 | E43: =E11-SUBTOTAL(9,E20,E25:E27) -> 0 | G43: =G11-SUBTOTAL(9,G20,G25:G27) -> 0 | H43: =H11-SUBTOTAL(9,H20,H25:H27) -> 0 | I43: =I11-SUBTOTAL(9,I20,I25:I27) -> 0 | J43: =J11-SUBTOTAL(9,J20,J25:J27) -> 0 | K43: =K11-SUBTOTAL(9,K20,K25:K27) -> 0 | L43: =L11-SUBTOTAL(9,L20,L25:L27) -> 0 | M43: =M11-SUBTOTAL(9,M20,M25:M27) -> 0 | N43: =N11-SUBTOTAL(9,N20,N25:N27) -> 0 | ... AM43: =AM11-SUBTOTAL(9,AM20,AM25:AM27) -> 0
B44: Source: Internal financials provided by Management & STOC analysis
B46: Check | C46: =SUMIFS($G46:$BC46,$G$5:$BC$5,"<="&EOMONTH(C$5,0),$G$6:$BC$6,"<="&C$5) -> 0 | D46: =SUMIFS($G46:$AT46,$G$5:$AT$5,">"&EOMONTH(D$5,-12),$G$5:$AT$5,"<="&D$5) -> 0 | E46: =SUMIFS($G46:$AT46,$G$5:$AT$5,">"&EOMONTH(E$5,-12),$G$5:$AT$5,"<="&E$5) -> 0 | G46: ='Lead QE'!J12-G43 -> 0 | H46: ='Lead QE'!K12-H43 -> 0 | I46: ='Lead QE'!L12-I43 -> 0 | J46: ='Lead QE'!M12-J43 -> 0 | K46: ='Lead QE'!N12-K43 -> 0 | L46: ='Lead QE'!O12-L43 -> 0 | M46: ='Lead QE'!P12-M43 -> 0 | N46: ='Lead QE'!Q12-N43 -> 0 | ... AM46: ='Lead QE'!AP12-AM43 -> 0
B48: Summary P&L Format: Reported (As a % of Revenue)
B49: In $000's | C49: =C5 -> 44926 | D49: =D5 -> 45291 | E49: =E5 -> 45565 | G49: 44562 | H49: =EOMONTH(G49,1) -> 44620 | I49: =EOMONTH(H49,1) -> 44651 | J49: =EOMONTH(I49,1) -> 44681 | K49: =EOMONTH(J49,1) -> 44712 | L49: =EOMONTH(K49,1) -> 44742 | M49: =EOMONTH(L49,1) -> 44773 | N49: =EOMONTH(M49,1) -> 44804 | O49: =EOMONTH(N49,1) -> 44834 | ... AM49: =EOMONTH(AL49,1) -> 45565
A50: Revenue, net | B50: Revenue, net | C50: =C6 -> 0 | D50: =D6 -> 0 | E50: =E6 -> 0 | G50: =G6 -> 0 | H50: =H6 -> 0 | I50: =I6 -> 0 | J50: =J6 -> 0 | K50: =K6 -> 0 | L50: =L6 -> 0 | M50: =M6 -> 0 | N50: =N6 -> 0 | ... AM50: =AM6 -> 0
B51: Dental supplies | C51: =+IFERROR((C7/C$6)*100,0) -> 0 | D51: =+IFERROR((D7/D$6)*100,0) -> 0 | E51: =+IFERROR((E7/E$6)*100,0) -> 0 | G51: =+IFERROR((G7/G$6)*100,0) -> 0 | H51: =+IFERROR((H7/H$6)*100,0) -> 0 | I51: =+IFERROR((I7/I$6)*100,0) -> 0 | J51: =+IFERROR((J7/J$6)*100,0) -> 0 | K51: =+IFERROR((K7/K$6)*100,0) -> 0 | L51: =+IFERROR((L7/L$6)*100,0) -> 0 | M51: =+IFERROR((M7/M$6)*100,0) -> 0 | N51: =+IFERROR((N7/N$6)*100,0) -> 0 | ... AM51: =+IFERROR((AM7/AM$6)*100,0) -> 0
B52: Ortho supplies | C52: =+IFERROR((C8/C$6)*100,0) -> 0 | D52: =+IFERROR((D8/D$6)*100,0) -> 0 | E52: =+IFERROR((E8/E$6)*100,0) -> 0 | G52: =+IFERROR((G8/G$6)*100,0) -> 0 | H52: =+IFERROR((H8/H$6)*100,0) -> 0 | I52: =+IFERROR((I8/I$6)*100,0) -> 0 | J52: =+IFERROR((J8/J$6)*100,0) -> 0 | K52: =+IFERROR((K8/K$6)*100,0) -> 0 | L52: =+IFERROR((L8/L$6)*100,0) -> 0 | M52: =+IFERROR((M8/M$6)*100,0) -> 0 | N52: =+IFERROR((N8/N$6)*100,0) -> 0 | ... AM52: =+IFERROR((AM8/AM$6)*100,0) -> 0
B53: Lab fees | C53: =+IFERROR((C9/C$6)*100,0) -> 0 | D53: =+IFERROR((D9/D$6)*100,0) -> 0 | E53: =+IFERROR((E9/E$6)*100,0) -> 0 | G53: =+IFERROR((G9/G$6)*100,0) -> 0 | H53: =+IFERROR((H9/H$6)*100,0) -> 0 | I53: =+IFERROR((I9/I$6)*100,0) -> 0 | J53: =+IFERROR((J9/J$6)*100,0) -> 0 | K53: =+IFERROR((K9/K$6)*100,0) -> 0 | L53: =+IFERROR((L9/L$6)*100,0) -> 0 | M53: =+IFERROR((M9/M$6)*100,0) -> 0 | N53: =+IFERROR((N9/N$6)*100,0) -> 0 | ... AM53: =+IFERROR((AM9/AM$6)*100,0) -> 0
B54: Cost of goods sold | C54: =+IFERROR((C10/C$6)*100,0) -> 0 | D54: =+IFERROR((D10/D$6)*100,0) -> 0 | E54: =+IFERROR((E10/E$6)*100,0) -> 0 | G54: =+IFERROR((G10/G$6)*100,0) -> 0 | H54: =+IFERROR((H10/H$6)*100,0) -> 0 | I54: =+IFERROR((I10/I$6)*100,0) -> 0 | J54: =+IFERROR((J10/J$6)*100,0) -> 0 | K54: =+IFERROR((K10/K$6)*100,0) -> 0 | L54: =+IFERROR((L10/L$6)*100,0) -> 0 | M54: =+IFERROR((M10/M$6)*100,0) -> 0 | N54: =+IFERROR((N10/N$6)*100,0) -> 0 | ... AM54: =+IFERROR((AM10/AM$6)*100,0) -> 0
B55: Gross profit | C55: =+IFERROR((C11/C$6)*100,0) -> 0 | D55: =+IFERROR((D11/D$6)*100,0) -> 0 | E55: =+IFERROR((E11/E$6)*100,0) -> 0 | G55: =+IFERROR((G11/G$6)*100,0) -> 0 | H55: =+IFERROR((H11/H$6)*100,0) -> 0 | I55: =+IFERROR((I11/I$6)*100,0) -> 0 | J55: =+IFERROR((J11/J$6)*100,0) -> 0 | K55: =+IFERROR((K11/K$6)*100,0) -> 0 | L55: =+IFERROR((L11/L$6)*100,0) -> 0 | M55: =+IFERROR((M11/M$6)*100,0) -> 0 | N55: =+IFERROR((N11/N$6)*100,0) -> 0 | ... AM55: =+IFERROR((AM11/AM$6)*100,0) -> 0
B57: Doctor wages | C57: =+IFERROR((C13/C$6)*100,0) -> 0 | D57: =+IFERROR((D13/D$6)*100,0) -> 0 | E57: =+IFERROR((E13/E$6)*100,0) -> 0 | G57: =+IFERROR((G13/G$6)*100,0) -> 0 | H57: =+IFERROR((H13/H$6)*100,0) -> 0 | I57: =+IFERROR((I13/I$6)*100,0) -> 0 | J57: =+IFERROR((J13/J$6)*100,0) -> 0 | K57: =+IFERROR((K13/K$6)*100,0) -> 0 | L57: =+IFERROR((L13/L$6)*100,0) -> 0 | M57: =+IFERROR((M13/M$6)*100,0) -> 0 | N57: =+IFERROR((N13/N$6)*100,0) -> 0 | ... AM57: =+IFERROR((AM13/AM$6)*100,0) -> 0
B58: Clinic wages | C58: =+IFERROR((C14/C$6)*100,0) -> 0 | D58: =+IFERROR((D14/D$6)*100,0) -> 0 | E58: =+IFERROR((E14/E$6)*100,0) -> 0 | G58: =+IFERROR((G14/G$6)*100,0) -> 0 | H58: =+IFERROR((H14/H$6)*100,0) -> 0 | I58: =+IFERROR((I14/I$6)*100,0) -> 0 | J58: =+IFERROR((J14/J$6)*100,0) -> 0 | K58: =+IFERROR((K14/K$6)*100,0) -> 0 | L58: =+IFERROR((L14/L$6)*100,0) -> 0 | M58: =+IFERROR((M14/M$6)*100,0) -> 0 | N58: =+IFERROR((N14/N$6)*100,0) -> 0 | ... AM58: =+IFERROR((AM14/AM$6)*100,0) -> 0
B59: Admin wages | C59: =+IFERROR((C15/C$6)*100,0) -> 0 | D59: =+IFERROR((D15/D$6)*100,0) -> 0 | E59: =+IFERROR((E15/E$6)*100,0) -> 0 | G59: =+IFERROR((G15/G$6)*100,0) -> 0 | H59: =+IFERROR((H15/H$6)*100,0) -> 0 | I59: =+IFERROR((I15/I$6)*100,0) -> 0 | J59: =+IFERROR((J15/J$6)*100,0) -> 0 | K59: =+IFERROR((K15/K$6)*100,0) -> 0 | L59: =+IFERROR((L15/L$6)*100,0) -> 0 | M59: =+IFERROR((M15/M$6)*100,0) -> 0 | N59: =+IFERROR((N15/N$6)*100,0) -> 0 | ... AM59: =+IFERROR((AM15/AM$6)*100,0) -> 0
B60: Gross wages, total | C60: =+IFERROR((C16/C$6)*100,0) -> 0 | D60: =+IFERROR((D16/D$6)*100,0) -> 0 | E60: =+IFERROR((E16/E$6)*100,0) -> 0 | G60: =+IFERROR((G16/G$6)*100,0) -> 0 | H60: =+IFERROR((H16/H$6)*100,0) -> 0 | I60: =+IFERROR((I16/I$6)*100,0) -> 0 | J60: =+IFERROR((J16/J$6)*100,0) -> 0 | K60: =+IFERROR((K16/K$6)*100,0) -> 0 | L60: =+IFERROR((L16/L$6)*100,0) -> 0 | M60: =+IFERROR((M16/M$6)*100,0) -> 0 | N60: =+IFERROR((N16/N$6)*100,0) -> 0 | ... AM60: =+IFERROR((AM16/AM$6)*100,0) -> 0
B61: Payroll taxes | C61: =+IFERROR((C17/C$6)*100,0) -> 0 | D61: =+IFERROR((D17/D$6)*100,0) -> 0 | E61: =+IFERROR((E17/E$6)*100,0) -> 0 | G61: =+IFERROR((G17/G$6)*100,0) -> 0 | H61: =+IFERROR((H17/H$6)*100,0) -> 0 | I61: =+IFERROR((I17/I$6)*100,0) -> 0 | J61: =+IFERROR((J17/J$6)*100,0) -> 0 | K61: =+IFERROR((K17/K$6)*100,0) -> 0 | L61: =+IFERROR((L17/L$6)*100,0) -> 0 | M61: =+IFERROR((M17/M$6)*100,0) -> 0 | N61: =+IFERROR((N17/N$6)*100,0) -> 0 | ... AM61: =+IFERROR((AM17/AM$6)*100,0) -> 0
B62: Insurance | C62: =+IFERROR((C18/C$6)*100,0) -> 0 | D62: =+IFERROR((D18/D$6)*100,0) -> 0 | E62: =+IFERROR((E18/E$6)*100,0) -> 0 | G62: =+IFERROR((G18/G$6)*100,0) -> 0 | H62: =+IFERROR((H18/H$6)*100,0) -> 0 | I62: =+IFERROR((I18/I$6)*100,0) -> 0 | J62: =+IFERROR((J18/J$6)*100,0) -> 0 | K62: =+IFERROR((K18/K$6)*100,0) -> 0 | L62: =+IFERROR((L18/L$6)*100,0) -> 0 | M62: =+IFERROR((M18/M$6)*100,0) -> 0 | N62: =+IFERROR((N18/N$6)*100,0) -> 0 | ... AM62: =+IFERROR((AM18/AM$6)*100,0) -> 0
B63: Employee 401(k) | C63: =+IFERROR((C19/C$6)*100,0) -> 0 | D63: =+IFERROR((D19/D$6)*100,0) -> 0 | E63: =+IFERROR((E19/E$6)*100,0) -> 0 | G63: =+IFERROR((G19/G$6)*100,0) -> 0 | H63: =+IFERROR((H19/H$6)*100,0) -> 0 | I63: =+IFERROR((I19/I$6)*100,0) -> 0 | J63: =+IFERROR((J19/J$6)*100,0) -> 0 | K63: =+IFERROR((K19/K$6)*100,0) -> 0 | L63: =+IFERROR((L19/L$6)*100,0) -> 0 | M63: =+IFERROR((M19/M$6)*100,0) -> 0 | N63: =+IFERROR((N19/N$6)*100,0) -> 0 | ... AM63: =+IFERROR((AM19/AM$6)*100,0) -> 0
... B87: Reported EBITDA | C87: =+IFERROR((C43/C$6)*100,0) -> 0 | D87: =+IFERROR((D43/D$6)*100,0) -> 0 | E87: =+IFERROR((E43/E$6)*100,0) -> 0 | G87: =+IFERROR((G43/G$6)*100,0) -> 0 | H87: =+IFERROR((H43/H$6)*100,0) -> 0 | I87: =+IFERROR((I43/I$6)*100,0) -> 0 | J87: =+IFERROR((J43/J$6)*100,0) -> 0 | K87: =+IFERROR((K43/K$6)*100,0) -> 0 | L87: =+IFERROR((L43/L$6)*100,0) -> 0 | M87: =+IFERROR((M43/M$6)*100,0) -> 0 | N87: =+IFERROR((N43/N$6)*100,0) -> 0 | ... AM87: =+IFERROR((AM43/AM$6)*100,0) -> 0
B88: Source: Internal financials provided by Management & STOC analysis

Sheet Recast Mgmt. Adjusted
B1: =Project&" - "&City&", "&State -> OPEN - OPEN, OPEN
B2: =MID(CELL("filename",B1),FIND("]",CELL("filename",B1))+1,255) -> Recast Mgmt. Adjusted
A4: Recast PL | B4: Summarized Mgmt. Adjusted P&L
B5: In $000's | C5: =First_Reporting_Year -> 44926 | D5: =Second_Reporting_Year -> 45291 | E5: =Stub_Period -> 45565 | G5: =EOMONTH(C5,-11) -> 44592 | H5: =EOMONTH(G5,1) -> 44620 | I5: =EOMONTH(H5,1) -> 44651 | J5: =EOMONTH(I5,1) -> 44681 | K5: =EOMONTH(J5,1) -> 44712 | L5: =EOMONTH(K5,1) -> 44742 | M5: =EOMONTH(L5,1) -> 44773 | N5: =EOMONTH(M5,1) -> 44804 | O5: =EOMONTH(N5,1) -> 44834 | ... AM5: =EOMONTH(AL5,1) -> 45565
B6: Revenue, net | C6: =SUMIFS($G6:$BC6,$G$5:$BC$5,"<="&EOMONTH(C$5,0),$G$6:$BC$6,"<="&C$5) -> 0 | D6: =SUMIFS($G6:$AT6,$G$5:$AT$5,">"&EOMONTH(D$5,-12),$G$5:$AT$5,"<="&D$5) -> 0 | E6: =SUMIFS($G6:$AT6,$G$5:$AT$5,">"&EOMONTH(E$5,-12),$G$5:$AT$5,"<="&E$5) -> 0 | G6: ='Recast Reported'!G6+SUMIFS('QE Detail - MGMT.'!H:H,'QE Detail - MGMT.'!$B:$B,'Recast Mgmt. Adjusted'!$B6) -> 0 | H6: ='Recast Reported'!H6+SUMIFS('QE Detail - MGMT.'!I:I,'QE Detail - MGMT.'!$B:$B,'Recast Mgmt. Adjusted'!$B6) -> 0 | I6: ='Recast Reported'!I6+SUMIFS('QE Detail - MGMT.'!J:J,'QE Detail - MGMT.'!$B:$B,'Recast Mgmt. Adjusted'!$B6) -> 0 | J6: ='Recast Reported'!J6+SUMIFS('QE Detail - MGMT.'!K:K,'QE Detail - MGMT.'!$B:$B,'Recast Mgmt. Adjusted'!$B6) -> 0 | K6: ='Recast Reported'!K6+SUMIFS('QE Detail - MGMT.'!L:L,'QE Detail - MGMT.'!$B:$B,'Recast Mgmt. Adjusted'!$B6) -> 0 | L6: ='Recast Reported'!L6+SUMIFS('QE Detail - MGMT.'!M:M,'QE Detail - MGMT.'!$B:$B,'Recast Mgmt. Adjusted'!$B6) -> 0 | M6: ='Recast Reported'!M6+SUMIFS('QE Detail - MGMT.'!N:N,'QE Detail - MGMT.'!$B:$B,'Recast Mgmt. Adjusted'!$B6) -> 0 | N6: ='Recast Reported'!N6+SUMIFS('QE Detail - MGMT.'!O:O,'QE Detail - MGMT.'!$B:$B,'Recast Mgmt. Adjusted'!$B6) -> 0 | O6: ='Recast Reported'!O6+SUMIFS('QE Detail - MGMT.'!P:P,'QE Detail - MGMT.'!$B:$B,'Recast Mgmt. Adjusted'!$B6) -> 0 | P6: ='Recast Reported'!P6+SUMIFS('QE Detail - MGMT.'!Q:Q,'QE Detail - MGMT.'!$B:$B,'Recast Mgmt. Adjusted'!$B6) -> 0 | Q6: ='Recast Reported'!Q6+SUMIFS('QE Detail - MGMT.'!R:R,'QE Detail - MGMT.'!$B:$B,'Recast Mgmt. Adjusted'!$B6) -> 0 | R6: ='Recast Reported'!R6+SUMIFS('QE Detail - MGMT.'!S:S,'QE Detail - MGMT.'!$B:$B,'Recast Mgmt. Adjusted'!$B6) -> 0 | S6: ='Recast Reported'!S6+SUMIFS('QE Detail - MGMT.'!T:T,'QE Detail - MGMT.'!$B:$B,'Recast Mgmt. Adjusted'!$B6) -> 0 | T6: ='Recast Reported'!T6+SUMIFS('QE Detail - MGMT.'!U:U,'QE Detail - MGMT.'!$B:$B,'Recast Mgmt. Adjusted'!$B6) -> 0 | U6: ='Recast Reported'!U6+SUMIFS('QE Detail - MGMT.'!V:V,'QE Detail - MGMT.'!$B:$B,'Recast Mgmt. Adjusted'!$B6) -> 0 | V6: ='Recast Reported'!V6+SUMIFS('QE Detail - MGMT.'!W:W,'QE Detail - MGMT.'!$B:$B,'Recast Mgmt. Adjusted'!$B6) -> 0 | W6: ='Recast Reported'!W6+SUMIFS('QE Detail - MGMT.'!X:X,'QE Detail - MGMT.'!$B:$B,'Recast Mgmt. Adjusted'!$B6) -> 0 | X6: ='Recast Reported'!X6+SUMIFS('QE Detail - MGMT.'!Y:Y,'QE Detail - MGMT.'!$B:$B,'Recast Mgmt. Adjusted'!$B6) -> 0 | Y6: ='Recast Reported'!Y6+SUMIFS('QE Detail - MGMT.'!Z:Z,'QE Detail - MGMT.'!$B:$B,'Recast Mgmt. Adjusted'!$B6) -> 0 | Z6: ='Recast Reported'!Z6+SUMIFS('QE Detail - MGMT.'!AA:AA,'QE Detail - MGMT.'!$B:$B,'Recast Mgmt. Adjusted'!$B6) -> 0 | AA6: ='Recast Reported'!AA6+SUMIFS('QE Detail - MGMT.'!AB:AB,'QE Detail - MGMT.'!$B:$B,'Recast Mgmt. Adjusted'!$B6) -> 0 | AB6: ='Recast Reported'!AB6+SUMIFS('QE Detail - MGMT.'!AC:AC,'QE Detail - MGMT.'!$B:$B,'Recast Mgmt. Adjusted'!$B6) -> 0 | AC6: ='Recast Reported'!AC6+SUMIFS('QE Detail - MGMT.'!AD:AD,'QE Detail - MGMT.'!$B:$B,'Recast Mgmt. Adjusted'!$B6) -> 0 | AD6: ='Recast Reported'!AD6+SUMIFS('QE Detail - MGMT.'!AE:AE,'QE Detail - MGMT.'!$B:$B,'Recast Mgmt. Adjusted'!$B6) -> 0 | AE6: ='Recast Reported'!AE6+SUMIFS('QE Detail - MGMT.'!AF:AF,'QE Detail - MGMT.'!$B:$B,'Recast Mgmt. Adjusted'!$B6) -> 0 | AF6: ='Recast Reported'!AF6+SUMIFS('QE Detail - MGMT.'!AG:AG,'QE Detail - MGMT.'!$B:$B,'Recast Mgmt. Adjusted'!$B6) -> 0 | AG6: ='Recast Reported'!AG6+SUMIFS('QE Detail - MGMT.'!AH:AH,'QE Detail - MGMT.'!$B:$B,'Recast Mgmt. Adjusted'!$B6) -> 0 | AH6: ='Recast Reported'!AH6+SUMIFS('QE Detail - MGMT.'!AI:AI,'QE Detail - MGMT.'!$B:$B,'Recast Mgmt. Adjusted'!$B6) -> 0 | AI6: ='Recast Reported'!AI6+SUMIFS('QE Detail - MGMT.'!AJ:AJ,'QE Detail - MGMT.'!$B:$B,'Recast Mgmt. Adjusted'!$B6) -> 0 | AJ6: ='Recast Reported'!AJ6+SUMIFS('QE Detail - MGMT.'!AK:AK,'QE Detail - MGMT.'!$B:$B,'Recast Mgmt. Adjusted'!$B6) -> 0 | AK6: ='Recast Reported'!AK6+SUMIFS('QE Detail - MGMT.'!AL:AL,'QE Detail - MGMT.'!$B:$B,'Recast Mgmt. Adjusted'!$B6) -> 0 | AL6: ='Recast Reported'!AL6+SUMIFS('QE Detail - MGMT.'!AM:AM,'QE Detail - MGMT.'!$B:$B,'Recast Mgmt. Adjusted'!$B6) -> 0 | AM6: ='Recast Reported'!AM6+SUMIFS('QE Detail - MGMT.'!AN:AN,'QE Detail - MGMT.'!$B:$B,'Recast Mgmt. Adjusted'!$B6) -> 0
A7: Dental supplies | B7: Dental supplies | C7: =SUMIFS($G7:$BC7,$G$5:$BC$5,"<="&EOMONTH(C$5,0),$G$6:$BC$6,"<="&C$5) -> 0 | D7: =SUMIFS($G7:$AT7,$G$5:$AT$5,">"&EOMONTH(D$5,-12),$G$5:$AT$5,"<="&D$5) -> 0 | E7: =SUMIFS($G7:$AT7,$G$5:$AT$5,">"&EOMONTH(E$5,-12),$G$5:$AT$5,"<="&E$5) -> 0 | G7: ='Recast Reported'!G7-SUMIFS('QE Detail - MGMT.'!H:H,'QE Detail - MGMT.'!$B:$B,'Recast Mgmt. Adjusted'!$B7) -> 0 | H7: ='Recast Reported'!H7-SUMIFS('QE Detail - MGMT.'!I:I,'QE Detail - MGMT.'!$B:$B,'Recast Mgmt. Adjusted'!$B7) -> 0 | I7: ='Recast Reported'!I7-SUMIFS('QE Detail - MGMT.'!J:J,'QE Detail - MGMT.'!$B:$B,'Recast Mgmt. Adjusted'!$B7) -> 0 | J7: ='Recast Reported'!J7-SUMIFS('QE Detail - MGMT.'!K:K,'QE Detail - MGMT.'!$B:$B,'Recast Mgmt. Adjusted'!$B7) -> 0 | K7: ='Recast Reported'!K7-SUMIFS('QE Detail - MGMT.'!L:L,'QE Detail - MGMT.'!$B:$B,'Recast Mgmt. Adjusted'!$B7) -> 0 | L7: ='Recast Reported'!L7-SUMIFS('QE Detail - MGMT.'!M:M,'QE Detail - MGMT.'!$B:$B,'Recast Mgmt. Adjusted'!$B7) -> 0 | M7: ='Recast Reported'!M7-SUMIFS('QE Detail - MGMT.'!N:N,'QE Detail - MGMT.'!$B:$B,'Recast Mgmt. Adjusted'!$B7) -> 0 | N7: ='Recast Reported'!N7-SUMIFS('QE Detail - MGMT.'!O:O,'QE Detail - MGMT.'!$B:$B,'Recast Mgmt. Adjusted'!$B7) -> 0 | O7: ='Recast Reported'!O7-SUMIFS('QE Detail - MGMT.'!P:P,'QE Detail - MGMT.'!$B:$B,'Recast Mgmt. Adjusted'!$B7) -> 0 | P7: ='Recast Reported'!P7-SUMIFS('QE Detail - MGMT.'!Q:Q,'QE Detail - MGMT.'!$B:$B,'Recast Mgmt. Adjusted'!$B7) -> 0 | Q7: ='Recast Reported'!Q7-SUMIFS('QE Detail - MGMT.'!R:R,'QE Detail - MGMT.'!$B:$B,'Recast Mgmt. Adjusted'!$B7) -> 0 | R7: ='Recast Reported'!R7-SUMIFS('QE Detail - MGMT.'!S:S,'QE Detail - MGMT.'!$B:$B,'Recast Mgmt. Adjusted'!$B7) -> 0 | S7: ='Recast Reported'!S7-SUMIFS('QE Detail - MGMT.'!T:T,'QE Detail - MGMT.'!$B:$B,'Recast Mgmt. Adjusted'!$B7) -> 0 | T7: ='Recast Reported'!T7-SUMIFS('QE Detail - MGMT.'!U:U,'QE Detail - MGMT.'!$B:$B,'Recast Mgmt. Adjusted'!$B7) -> 0 | U7: ='Recast Reported'!U7-SUMIFS('QE Detail - MGMT.'!V:V,'QE Detail - MGMT.'!$B:$B,'Recast Mgmt. Adjusted'!$B7) -> 0 | V7: ='Recast Reported'!V7-SUMIFS('QE Detail - MGMT.'!W:W,'QE Detail - MGMT.'!$B:$B,'Recast Mgmt. Adjusted'!$B7) -> 0 | W7: ='Recast Reported'!W7-SUMIFS('QE Detail - MGMT.'!X:X,'QE Detail - MGMT.'!$B:$B,'Recast Mgmt. Adjusted'!$B7) -> 0 | X7: ='Recast Reported'!X7-SUMIFS('QE Detail - MGMT.'!Y:Y,'QE Detail - MGMT.'!$B:$B,'Recast Mgmt. Adjusted'!$B7) -> 0 | Y7: ='Recast Reported'!Y7-SUMIFS('QE Detail - MGMT.'!Z:Z,'QE Detail - MGMT.'!$B:$B,'Recast Mgmt. Adjusted'!$B7) -> 0 | Z7: ='Recast Reported'!Z7-SUMIFS('QE Detail - MGMT.'!AA:AA,'QE Detail - MGMT.'!$B:$B,'Recast Mgmt. Adjusted'!$B7) -> 0 | AA7: ='Recast Reported'!AA7-SUMIFS('QE Detail - MGMT.'!AB:AB,'QE Detail - MGMT.'!$B:$B,'Recast Mgmt. Adjusted'!$B7) -> 0 | AB7: ='Recast Reported'!AB7-SUMIFS('QE Detail - MGMT.'!AC:AC,'QE Detail - MGMT.'!$B:$B,'Recast Mgmt. Adjusted'!$B7) -> 0 | AC7: ='Recast Reported'!AC7-SUMIFS('QE Detail - MGMT.'!AD:AD,'QE Detail - MGMT.'!$B:$B,'Recast Mgmt. Adjusted'!$B7) -> 0 | AD7: ='Recast Reported'!AD7-SUMIFS('QE Detail - MGMT.'!AE:AE,'QE Detail - MGMT.'!$B:$B,'Recast Mgmt. Adjusted'!$B7) -> 0 | AE7: ='Recast Reported'!AE7-SUMIFS('QE Detail - MGMT.'!AF:AF,'QE Detail - MGMT.'!$B:$B,'Recast Mgmt. Adjusted'!$B7) -> 0 | AF7: ='Recast Reported'!AF7-SUMIFS('QE Detail - MGMT.'!AG:AG,'QE Detail - MGMT.'!$B:$B,'Recast Mgmt. Adjusted'!$B7) -> 0 | AG7: ='Recast Reported'!AG7-SUMIFS('QE Detail - MGMT.'!AH:AH,'QE Detail - MGMT.'!$B:$B,'Recast Mgmt. Adjusted'!$B7) -> 0 | AH7: ='Recast Reported'!AH7-SUMIFS('QE Detail - MGMT.'!AI:AI,'QE Detail - MGMT.'!$B:$B,'Recast Mgmt. Adjusted'!$B7) -> 0 | AI7: ='Recast Reported'!AI7-SUMIFS('QE Detail - MGMT.'!AJ:AJ,'QE Detail - MGMT.'!$B:$B,'Recast Mgmt. Adjusted'!$B7) -> 0 | AJ7: ='Recast Reported'!AJ7-SUMIFS('QE Detail - MGMT.'!AK:AK,'QE Detail - MGMT.'!$B:$B,'Recast Mgmt. Adjusted'!$B7) -> 0 | AK7: ='Recast Reported'!AK7-SUMIFS('QE Detail - MGMT.'!AL:AL,'QE Detail - MGMT.'!$B:$B,'Recast Mgmt. Adjusted'!$B7) -> 0 | AL7: ='Recast Reported'!AL7-SUMIFS('QE Detail - MGMT.'!AM:AM,'QE Detail - MGMT.'!$B:$B,'Recast Mgmt. Adjusted'!$B7) -> 0 | AM7: ='Recast Reported'!AM7-SUMIFS('QE Detail - MGMT.'!AN:AN,'QE Detail - MGMT.'!$B:$B,'Recast Mgmt. Adjusted'!$B7) -> 0
A8: Ortho supplies | B8: Ortho supplies | C8: =SUMIFS($G8:$BC8,$G$5:$BC$5,"<="&EOMONTH(C$5,0),$G$6:$BC$6,"<="&C$5) -> 0 | D8: =SUMIFS($G8:$AT8,$G$5:$AT$5,">"&EOMONTH(D$5,-12),$G$5:$AT$5,"<="&D$5) -> 0 | E8: =SUMIFS($G8:$AT8,$G$5:$AT$5,">"&EOMONTH(E$5,-12),$G$5:$AT$5,"<="&E$5) -> 0 | G8: ='Recast Reported'!G8-SUMIFS('QE Detail - MGMT.'!H:H,'QE Detail - MGMT.'!$B:$B,'Recast Mgmt. Adjusted'!$B8) -> 0 | H8: ='Recast Reported'!H8-SUMIFS('QE Detail - MGMT.'!I:I,'QE Detail - MGMT.'!$B:$B,'Recast Mgmt. Adjusted'!$B8) -> 0 | I8: ='Recast Reported'!I8-SUMIFS('QE Detail - MGMT.'!J:J,'QE Detail - MGMT.'!$B:$B,'Recast Mgmt. Adjusted'!$B8) -> 0 | J8: ='Recast Reported'!J8-SUMIFS('QE Detail - MGMT.'!K:K,'QE Detail - MGMT.'!$B:$B,'Recast Mgmt. Adjusted'!$B8) -> 0 | K8: ='Recast Reported'!K8-SUMIFS('QE Detail - MGMT.'!L:L,'QE Detail - MGMT.'!$B:$B,'Recast Mgmt. Adjusted'!$B8) -> 0 | L8: ='Recast Reported'!L8-SUMIFS('QE Detail - MGMT.'!M:M,'QE Detail - MGMT.'!$B:$B,'Recast Mgmt. Adjusted'!$B8) -> 0 | M8: ='Recast Reported'!M8-SUMIFS('QE Detail - MGMT.'!N:N,'QE Detail - MGMT.'!$B:$B,'Recast Mgmt. Adjusted'!$B8) -> 0 | N8: ='Recast Reported'!N8-SUMIFS('QE Detail - MGMT.'!O:O,'QE Detail - MGMT.'!$B:$B,'Recast Mgmt. Adjusted'!$B8) -> 0 | O8: ='Recast Reported'!O8-SUMIFS('QE Detail - MGMT.'!P:P,'QE Detail - MGMT.'!$B:$B,'Recast Mgmt. Adjusted'!$B8) -> 0 | P8: ='Recast Reported'!P8-SUMIFS('QE Detail - MGMT.'!Q:Q,'QE Detail - MGMT.'!$B:$B,'Recast Mgmt. Adjusted'!$B8) -> 0 | Q8: ='Recast Reported'!Q8-SUMIFS('QE Detail - MGMT.'!R:R,'QE Detail - MGMT.'!$B:$B,'Recast Mgmt. Adjusted'!$B8) -> 0 | R8: ='Recast Reported'!R8-SUMIFS('QE Detail - MGMT.'!S:S,'QE Detail - MGMT.'!$B:$B,'Recast Mgmt. Adjusted'!$B8) -> 0 | S8: ='Recast Reported'!S8-SUMIFS('QE Detail - MGMT.'!T:T,'QE Detail - MGMT.'!$B:$B,'Recast Mgmt. Adjusted'!$B8) -> 0 | T8: ='Recast Reported'!T8-SUMIFS('QE Detail - MGMT.'!U:U,'QE Detail - MGMT.'!$B:$B,'Recast Mgmt. Adjusted'!$B8) -> 0 | U8: ='Recast Reported'!U8-SUMIFS('QE Detail - MGMT.'!V:V,'QE Detail - MGMT.'!$B:$B,'Recast Mgmt. Adjusted'!$B8) -> 0 | V8: ='Recast Reported'!V8-SUMIFS('QE Detail - MGMT.'!W:W,'QE Detail - MGMT.'!$B:$B,'Recast Mgmt. Adjusted'!$B8) -> 0 | W8: ='Recast Reported'!W8-SUMIFS('QE Detail - MGMT.'!X:X,'QE Detail - MGMT.'!$B:$B,'Recast Mgmt. Adjusted'!$B8) -> 0 | X8: ='Recast Reported'!X8-SUMIFS('QE Detail - MGMT.'!Y:Y,'QE Detail - MGMT.'!$B:$B,'Recast Mgmt. Adjusted'!$B8) -> 0 | Y8: ='Recast Reported'!Y8-SUMIFS('QE Detail - MGMT.'!Z:Z,'QE Detail - MGMT.'!$B:$B,'Recast Mgmt. Adjusted'!$B8) -> 0 | Z8: ='Recast Reported'!Z8-SUMIFS('QE Detail - MGMT.'!AA:AA,'QE Detail - MGMT.'!$B:$B,'Recast Mgmt. Adjusted'!$B8) -> 0 | AA8: ='Recast Reported'!AA8-SUMIFS('QE Detail - MGMT.'!AB:AB,'QE Detail - MGMT.'!$B:$B,'Recast Mgmt. Adjusted'!$B8) -> 0 | AB8: ='Recast Reported'!AB8-SUMIFS('QE Detail - MGMT.'!AC:AC,'QE Detail - MGMT.'!$B:$B,'Recast Mgmt. Adjusted'!$B8) -> 0 | AC8: ='Recast Reported'!AC8-SUMIFS('QE Detail - MGMT.'!AD:AD,'QE Detail - MGMT.'!$B:$B,'Recast Mgmt. Adjusted'!$B8) -> 0 | AD8: ='Recast Reported'!AD8-SUMIFS('QE Detail - MGMT.'!AE:AE,'QE Detail - MGMT.'!$B:$B,'Recast Mgmt. Adjusted'!$B8) -> 0 | AE8: ='Recast Reported'!AE8-SUMIFS('QE Detail - MGMT.'!AF:AF,'QE Detail - MGMT.'!$B:$B,'Recast Mgmt. Adjusted'!$B8) -> 0 | AF8: ='Recast Reported'!AF8-SUMIFS('QE Detail - MGMT.'!AG:AG,'QE Detail - MGMT.'!$B:$B,'Recast Mgmt. Adjusted'!$B8) -> 0 | AG8: ='Recast Reported'!AG8-SUMIFS('QE Detail - MGMT.'!AH:AH,'QE Detail - MGMT.'!$B:$B,'Recast Mgmt. Adjusted'!$B8) -> 0 | AH8: ='Recast Reported'!AH8-SUMIFS('QE Detail - MGMT.'!AI:AI,'QE Detail - MGMT.'!$B:$B,'Recast Mgmt. Adjusted'!$B8) -> 0 | AI8: ='Recast Reported'!AI8-SUMIFS('QE Detail - MGMT.'!AJ:AJ,'QE Detail - MGMT.'!$B:$B,'Recast Mgmt. Adjusted'!$B8) -> 0 | AJ8: ='Recast Reported'!AJ8-SUMIFS('QE Detail - MGMT.'!AK:AK,'QE Detail - MGMT.'!$B:$B,'Recast Mgmt. Adjusted'!$B8) -> 0 | AK8: ='Recast Reported'!AK8-SUMIFS('QE Detail - MGMT.'!AL:AL,'QE Detail - MGMT.'!$B:$B,'Recast Mgmt. Adjusted'!$B8) -> 0 | AL8: ='Recast Reported'!AL8-SUMIFS('QE Detail - MGMT.'!AM:AM,'QE Detail - MGMT.'!$B:$B,'Recast Mgmt. Adjusted'!$B8) -> 0 | AM8: ='Recast Reported'!AM8-SUMIFS('QE Detail - MGMT.'!AN:AN,'QE Detail - MGMT.'!$B:$B,'Recast Mgmt. Adjusted'!$B8) -> 0
A9: Lab fees | B9: Lab fees | C9: =SUMIFS($G9:$BC9,$G$5:$BC$5,"<="&EOMONTH(C$5,0),$G$6:$BC$6,"<="&C$5) -> 0 | D9: =SUMIFS($G9:$AT9,$G$5:$AT$5,">"&EOMONTH(D$5,-12),$G$5:$AT$5,"<="&D$5) -> 0 | E9: =SUMIFS($G9:$AT9,$G$5:$AT$5,">"&EOMONTH(E$5,-12),$G$5:$AT$5,"<="&E$5) -> 0 | G9: ='Recast Reported'!G9-SUMIFS('QE Detail - MGMT.'!H:H,'QE Detail - MGMT.'!$B:$B,'Recast Mgmt. Adjusted'!$B9) -> 0 | H9: ='Recast Reported'!H9-SUMIFS('QE Detail - MGMT.'!I:I,'QE Detail - MGMT.'!$B:$B,'Recast Mgmt. Adjusted'!$B9) -> 0 | I9: ='Recast Reported'!I9-SUMIFS('QE Detail - MGMT.'!J:J,'QE Detail - MGMT.'!$B:$B,'Recast Mgmt. Adjusted'!$B9) -> 0 | J9: ='Recast Reported'!J9-SUMIFS('QE Detail - MGMT.'!K:K,'QE Detail - MGMT.'!$B:$B,'Recast Mgmt. Adjusted'!$B9) -> 0 | K9: ='Recast Reported'!K9-SUMIFS('QE Detail - MGMT.'!L:L,'QE Detail - MGMT.'!$B:$B,'Recast Mgmt. Adjusted'!$B9) -> 0 | L9: ='Recast Reported'!L9-SUMIFS('QE Detail - MGMT.'!M:M,'QE Detail - MGMT.'!$B:$B,'Recast Mgmt. Adjusted'!$B9) -> 0 | M9: ='Recast Reported'!M9-SUMIFS('QE Detail - MGMT.'!N:N,'QE Detail - MGMT.'!$B:$B,'Recast Mgmt. Adjusted'!$B9) -> 0 | N9: ='Recast Reported'!N9-SUMIFS('QE Detail - MGMT.'!O:O,'QE Detail - MGMT.'!$B:$B,'Recast Mgmt. Adjusted'!$B9) -> 0 | O9: ='Recast Reported'!O9-SUMIFS('QE Detail - MGMT.'!P:P,'QE Detail - MGMT.'!$B:$B,'Recast Mgmt. Adjusted'!$B9) -> 0 | P9: ='Recast Reported'!P9-SUMIFS('QE Detail - MGMT.'!Q:Q,'QE Detail - MGMT.'!$B:$B,'Recast Mgmt. Adjusted'!$B9) -> 0 | Q9: ='Recast Reported'!Q9-SUMIFS('QE Detail - MGMT.'!R:R,'QE Detail - MGMT.'!$B:$B,'Recast Mgmt. Adjusted'!$B9) -> 0 | R9: ='Recast Reported'!R9-SUMIFS('QE Detail - MGMT.'!S:S,'QE Detail - MGMT.'!$B:$B,'Recast Mgmt. Adjusted'!$B9) -> 0 | S9: ='Recast Reported'!S9-SUMIFS('QE Detail - MGMT.'!T:T,'QE Detail - MGMT.'!$B:$B,'Recast Mgmt. Adjusted'!$B9) -> 0 | T9: ='Recast Reported'!T9-SUMIFS('QE Detail - MGMT.'!U:U,'QE Detail - MGMT.'!$B:$B,'Recast Mgmt. Adjusted'!$B9) -> 0 | U9: ='Recast Reported'!U9-SUMIFS('QE Detail - MGMT.'!V:V,'QE Detail - MGMT.'!$B:$B,'Recast Mgmt. Adjusted'!$B9) -> 0 | V9: ='Recast Reported'!V9-SUMIFS('QE Detail - MGMT.'!W:W,'QE Detail - MGMT.'!$B:$B,'Recast Mgmt. Adjusted'!$B9) -> 0 | W9: ='Recast Reported'!W9-SUMIFS('QE Detail - MGMT.'!X:X,'QE Detail - MGMT.'!$B:$B,'Recast Mgmt. Adjusted'!$B9) -> 0 | X9: ='Recast Reported'!X9-SUMIFS('QE Detail - MGMT.'!Y:Y,'QE Detail - MGMT.'!$B:$B,'Recast Mgmt. Adjusted'!$B9) -> 0 | Y9: ='Recast Reported'!Y9-SUMIFS('QE Detail - MGMT.'!Z:Z,'QE Detail - MGMT.'!$B:$B,'Recast Mgmt. Adjusted'!$B9) -> 0 | Z9: ='Recast Reported'!Z9-SUMIFS('QE Detail - MGMT.'!AA:AA,'QE Detail - MGMT.'!$B:$B,'Recast Mgmt. Adjusted'!$B9) -> 0 | AA9: ='Recast Reported'!AA9-SUMIFS('QE Detail - MGMT.'!AB:AB,'QE Detail - MGMT.'!$B:$B,'Recast Mgmt. Adjusted'!$B9) -> 0 | AB9: ='Recast Reported'!AB9-SUMIFS('QE Detail - MGMT.'!AC:AC,'QE Detail - MGMT.'!$B:$B,'Recast Mgmt. Adjusted'!$B9) -> 0 | AC9: ='Recast Reported'!AC9-SUMIFS('QE Detail - MGMT.'!AD:AD,'QE Detail - MGMT.'!$B:$B,'Recast Mgmt. Adjusted'!$B9) -> 0 | AD9: ='Recast Reported'!AD9-SUMIFS('QE Detail - MGMT.'!AE:AE,'QE Detail - MGMT.'!$B:$B,'Recast Mgmt. Adjusted'!$B9) -> 0 | AE9: ='Recast Reported'!AE9-SUMIFS('QE Detail - MGMT.'!AF:AF,'QE Detail - MGMT.'!$B:$B,'Recast Mgmt. Adjusted'!$B9) -> 0 | AF9: ='Recast Reported'!AF9-SUMIFS('QE Detail - MGMT.'!AG:AG,'QE Detail - MGMT.'!$B:$B,'Recast Mgmt. Adjusted'!$B9) -> 0 | AG9: ='Recast Reported'!AG9-SUMIFS('QE Detail - MGMT.'!AH:AH,'QE Detail - MGMT.'!$B:$B,'Recast Mgmt. Adjusted'!$B9) -> 0 | AH9: ='Recast Reported'!AH9-SUMIFS('QE Detail - MGMT.'!AI:AI,'QE Detail - MGMT.'!$B:$B,'Recast Mgmt. Adjusted'!$B9) -> 0 | AI9: ='Recast Reported'!AI9-SUMIFS('QE Detail - MGMT.'!AJ:AJ,'QE Detail - MGMT.'!$B:$B,'Recast Mgmt. Adjusted'!$B9) -> 0 | AJ9: ='Recast Reported'!AJ9-SUMIFS('QE Detail - MGMT.'!AK:AK,'QE Detail - MGMT.'!$B:$B,'Recast Mgmt. Adjusted'!$B9) -> 0 | AK9: ='Recast Reported'!AK9-SUMIFS('QE Detail - MGMT.'!AL:AL,'QE Detail - MGMT.'!$B:$B,'Recast Mgmt. Adjusted'!$B9) -> 0 | AL9: ='Recast Reported'!AL9-SUMIFS('QE Detail - MGMT.'!AM:AM,'QE Detail - MGMT.'!$B:$B,'Recast Mgmt. Adjusted'!$B9) -> 0 | AM9: ='Recast Reported'!AM9-SUMIFS('QE Detail - MGMT.'!AN:AN,'QE Detail - MGMT.'!$B:$B,'Recast Mgmt. Adjusted'!$B9) -> 0
B10: Cost of goods sold | C10: =SUM(C7:C9) -> 0 | D10: =SUM(D7:D9) -> 0 | E10: =SUM(E7:E9) -> 0 | G10: =SUM(G7:G9) -> 0 | H10: =SUM(H7:H9) -> 0 | I10: =SUM(I7:I9) -> 0 | J10: =SUM(J7:J9) -> 0 | K10: =SUM(K7:K9) -> 0 | L10: =SUM(L7:L9) -> 0 | M10: =SUM(M7:M9) -> 0 | N10: =SUM(N7:N9) -> 0 | ... AM10: =SUM(AM7:AM9) -> 0
B11: Gross profit | C11: =C6-SUM(C7:C9) -> 0 | D11: =D6-SUM(D7:D9) -> 0 | E11: =E6-SUM(E7:E9) -> 0 | G11: =G6-SUM(G7:G9) -> 0 | H11: =H6-SUM(H7:H9) -> 0 | I11: =I6-SUM(I7:I9) -> 0 | J11: =J6-SUM(J7:J9) -> 0 | K11: =K6-SUM(K7:K9) -> 0 | L11: =L6-SUM(L7:L9) -> 0 | M11: =M6-SUM(M7:M9) -> 0 | N11: =N6-SUM(N7:N9) -> 0 | ... AM11: =AM6-SUM(AM7:AM9) -> 0
A13: Doctor wages | B13: Doctor wages | C13: =SUMIFS($G13:$BC13,$G$5:$BC$5,"<="&EOMONTH(C$5,0),$G$6:$BC$6,"<="&C$5) -> 0 | D13: =SUMIFS($G13:$AT13,$G$5:$AT$5,">"&EOMONTH(D$5,-12),$G$5:$AT$5,"<="&D$5) -> 0 | E13: =SUMIFS($G13:$AT13,$G$5:$AT$5,">"&EOMONTH(E$5,-12),$G$5:$AT$5,"<="&E$5) -> 0 | G13: ='Recast Reported'!G13-SUMIFS('QE Detail - MGMT.'!H:H,'QE Detail - MGMT.'!$B:$B,'Recast Mgmt. Adjusted'!$B13) -> 0 | H13: ='Recast Reported'!H13-SUMIFS('QE Detail - MGMT.'!I:I,'QE Detail - MGMT.'!$B:$B,'Recast Mgmt. Adjusted'!$B13) -> 0 | I13: ='Recast Reported'!I13-SUMIFS('QE Detail - MGMT.'!J:J,'QE Detail - MGMT.'!$B:$B,'Recast Mgmt. Adjusted'!$B13) -> 0 | J13: ='Recast Reported'!J13-SUMIFS('QE Detail - MGMT.'!K:K,'QE Detail - MGMT.'!$B:$B,'Recast Mgmt. Adjusted'!$B13) -> 0 | K13: ='Recast Reported'!K13-SUMIFS('QE Detail - MGMT.'!L:L,'QE Detail - MGMT.'!$B:$B,'Recast Mgmt. Adjusted'!$B13) -> 0 | L13: ='Recast Reported'!L13-SUMIFS('QE Detail - MGMT.'!M:M,'QE Detail - MGMT.'!$B:$B,'Recast Mgmt. Adjusted'!$B13) -> 0 | M13: ='Recast Reported'!M13-SUMIFS('QE Detail - MGMT.'!N:N,'QE Detail - MGMT.'!$B:$B,'Recast Mgmt. Adjusted'!$B13) -> 0 | N13: ='Recast Reported'!N13-SUMIFS('QE Detail - MGMT.'!O:O,'QE Detail - MGMT.'!$B:$B,'Recast Mgmt. Adjusted'!$B13) -> 0 | O13: ='Recast Reported'!O13-SUMIFS('QE Detail - MGMT.'!P:P,'QE Detail - MGMT.'!$B:$B,'Recast Mgmt. Adjusted'!$B13) -> 0 | P13: ='Recast Reported'!P13-SUMIFS('QE Detail - MGMT.'!Q:Q,'QE Detail - MGMT.'!$B:$B,'Recast Mgmt. Adjusted'!$B13) -> 0 | Q13: ='Recast Reported'!Q13-SUMIFS('QE Detail - MGMT.'!R:R,'QE Detail - MGMT.'!$B:$B,'Recast Mgmt. Adjusted'!$B13) -> 0 | R13: ='Recast Reported'!R13-SUMIFS('QE Detail - MGMT.'!S:S,'QE Detail - MGMT.'!$B:$B,'Recast Mgmt. Adjusted'!$B13) -> 0 | S13: ='Recast Reported'!S13-SUMIFS('QE Detail - MGMT.'!T:T,'QE Detail - MGMT.'!$B:$B,'Recast Mgmt. Adjusted'!$B13) -> 0 | T13: ='Recast Reported'!T13-SUMIFS('QE Detail - MGMT.'!U:U,'QE Detail - MGMT.'!$B:$B,'Recast Mgmt. Adjusted'!$B13) -> 0 | U13: ='Recast Reported'!U13-SUMIFS('QE Detail - MGMT.'!V:V,'QE Detail - MGMT.'!$B:$B,'Recast Mgmt. Adjusted'!$B13) -> 0 | V13: ='Recast Reported'!V13-SUMIFS('QE Detail - MGMT.'!W:W,'QE Detail - MGMT.'!$B:$B,'Recast Mgmt. Adjusted'!$B13) -> 0 | W13: ='Recast Reported'!W13-SUMIFS('QE Detail - MGMT.'!X:X,'QE Detail - MGMT.'!$B:$B,'Recast Mgmt. Adjusted'!$B13) -> 0 | X13: ='Recast Reported'!X13-SUMIFS('QE Detail - MGMT.'!Y:Y,'QE Detail - MGMT.'!$B:$B,'Recast Mgmt. Adjusted'!$B13) -> 0 | Y13: ='Recast Reported'!Y13-SUMIFS('QE Detail - MGMT.'!Z:Z,'QE Detail - MGMT.'!$B:$B,'Recast Mgmt. Adjusted'!$B13) -> 0 | Z13: ='Recast Reported'!Z13-SUMIFS('QE Detail - MGMT.'!AA:AA,'QE Detail - MGMT.'!$B:$B,'Recast Mgmt. Adjusted'!$B13) -> 0 | AA13: ='Recast Reported'!AA13-SUMIFS('QE Detail - MGMT.'!AB:AB,'QE Detail - MGMT.'!$B:$B,'Recast Mgmt. Adjusted'!$B13) -> 0 | AB13: ='Recast Reported'!AB13-SUMIFS('QE Detail - MGMT.'!AC:AC,'QE Detail - MGMT.'!$B:$B,'Recast Mgmt. Adjusted'!$B13) -> 0 | AC13: ='Recast Reported'!AC13-SUMIFS('QE Detail - MGMT.'!AD:AD,'QE Detail - MGMT.'!$B:$B,'Recast Mgmt. Adjusted'!$B13) -> 0 | AD13: ='Recast Reported'!AD13-SUMIFS('QE Detail - MGMT.'!AE:AE,'QE Detail - MGMT.'!$B:$B,'Recast Mgmt. Adjusted'!$B13) -> 0 | AE13: ='Recast Reported'!AE13-SUMIFS('QE Detail - MGMT.'!AF:AF,'QE Detail - MGMT.'!$B:$B,'Recast Mgmt. Adjusted'!$B13) -> 0 | AF13: ='Recast Reported'!AF13-SUMIFS('QE Detail - MGMT.'!AG:AG,'QE Detail - MGMT.'!$B:$B,'Recast Mgmt. Adjusted'!$B13) -> 0 | AG13: ='Recast Reported'!AG13-SUMIFS('QE Detail - MGMT.'!AH:AH,'QE Detail - MGMT.'!$B:$B,'Recast Mgmt. Adjusted'!$B13) -> 0 | AH13: ='Recast Reported'!AH13-SUMIFS('QE Detail - MGMT.'!AI:AI,'QE Detail - MGMT.'!$B:$B,'Recast Mgmt. Adjusted'!$B13) -> 0 | AI13: ='Recast Reported'!AI13-SUMIFS('QE Detail - MGMT.'!AJ:AJ,'QE Detail - MGMT.'!$B:$B,'Recast Mgmt. Adjusted'!$B13) -> 0 | AJ13: ='Recast Reported'!AJ13-SUMIFS('QE Detail - MGMT.'!AK:AK,'QE Detail - MGMT.'!$B:$B,'Recast Mgmt. Adjusted'!$B13) -> 0 | AK13: ='Recast Reported'!AK13-SUMIFS('QE Detail - MGMT.'!AL:AL,'QE Detail - MGMT.'!$B:$B,'Recast Mgmt. Adjusted'!$B13) -> 0 | AL13: ='Recast Reported'!AL13-SUMIFS('QE Detail - MGMT.'!AM:AM,'QE Detail - MGMT.'!$B:$B,'Recast Mgmt. Adjusted'!$B13) -> 0 | AM13: ='Recast Reported'!AM13-SUMIFS('QE Detail - MGMT.'!AN:AN,'QE Detail - MGMT.'!$B:$B,'Recast Mgmt. Adjusted'!$B13) -> 0
A14: Clinic wages | B14: Clinic wages | C14: =SUMIFS($G14:$BC14,$G$5:$BC$5,"<="&EOMONTH(C$5,0),$G$6:$BC$6,"<="&C$5) -> 0 | D14: =SUMIFS($G14:$AT14,$G$5:$AT$5,">"&EOMONTH(D$5,-12),$G$5:$AT$5,"<="&D$5) -> 0 | E14: =SUMIFS($G14:$AT14,$G$5:$AT$5,">"&EOMONTH(E$5,-12),$G$5:$AT$5,"<="&E$5) -> 0 | G14: ='Recast Reported'!G14-SUMIFS('QE Detail - MGMT.'!H:H,'QE Detail - MGMT.'!$B:$B,'Recast Mgmt. Adjusted'!$B14) -> 0 | H14: ='Recast Reported'!H14-SUMIFS('QE Detail - MGMT.'!I:I,'QE Detail - MGMT.'!$B:$B,'Recast Mgmt. Adjusted'!$B14) -> 0 | I14: ='Recast Reported'!I14-SUMIFS('QE Detail - MGMT.'!J:J,'QE Detail - MGMT.'!$B:$B,'Recast Mgmt. Adjusted'!$B14) -> 0 | J14: ='Recast Reported'!J14-SUMIFS('QE Detail - MGMT.'!K:K,'QE Detail - MGMT.'!$B:$B,'Recast Mgmt. Adjusted'!$B14) -> 0 | K14: ='Recast Reported'!K14-SUMIFS('QE Detail - MGMT.'!L:L,'QE Detail - MGMT.'!$B:$B,'Recast Mgmt. Adjusted'!$B14) -> 0 | L14: ='Recast Reported'!L14-SUMIFS('QE Detail - MGMT.'!M:M,'QE Detail - MGMT.'!$B:$B,'Recast Mgmt. Adjusted'!$B14) -> 0 | M14: ='Recast Reported'!M14-SUMIFS('QE Detail - MGMT.'!N:N,'QE Detail - MGMT.'!$B:$B,'Recast Mgmt. Adjusted'!$B14) -> 0 | N14: ='Recast Reported'!N14-SUMIFS('QE Detail - MGMT.'!O:O,'QE Detail - MGMT.'!$B:$B,'Recast Mgmt. Adjusted'!$B14) -> 0 | O14: ='Recast Reported'!O14-SUMIFS('QE Detail - MGMT.'!P:P,'QE Detail - MGMT.'!$B:$B,'Recast Mgmt. Adjusted'!$B14) -> 0 | P14: ='Recast Reported'!P14-SUMIFS('QE Detail - MGMT.'!Q:Q,'QE Detail - MGMT.'!$B:$B,'Recast Mgmt. Adjusted'!$B14) -> 0 | Q14: ='Recast Reported'!Q14-SUMIFS('QE Detail - MGMT.'!R:R,'QE Detail - MGMT.'!$B:$B,'Recast Mgmt. Adjusted'!$B14) -> 0 | R14: ='Recast Reported'!R14-SUMIFS('QE Detail - MGMT.'!S:S,'QE Detail - MGMT.'!$B:$B,'Recast Mgmt. Adjusted'!$B14) -> 0 | S14: ='Recast Reported'!S14-SUMIFS('QE Detail - MGMT.'!T:T,'QE Detail - MGMT.'!$B:$B,'Recast Mgmt. Adjusted'!$B14) -> 0 | T14: ='Recast Reported'!T14-SUMIFS('QE Detail - MGMT.'!U:U,'QE Detail - MGMT.'!$B:$B,'Recast Mgmt. Adjusted'!$B14) -> 0 | U14: ='Recast Reported'!U14-SUMIFS('QE Detail - MGMT.'!V:V,'QE Detail - MGMT.'!$B:$B,'Recast Mgmt. Adjusted'!$B14) -> 0 | V14: ='Recast Reported'!V14-SUMIFS('QE Detail - MGMT.'!W:W,'QE Detail - MGMT.'!$B:$B,'Recast Mgmt. Adjusted'!$B14) -> 0 | W14: ='Recast Reported'!W14-SUMIFS('QE Detail - MGMT.'!X:X,'QE Detail - MGMT.'!$B:$B,'Recast Mgmt. Adjusted'!$B14) -> 0 | X14: ='Recast Reported'!X14-SUMIFS('QE Detail - MGMT.'!Y:Y,'QE Detail - MGMT.'!$B:$B,'Recast Mgmt. Adjusted'!$B14) -> 0 | Y14: ='Recast Reported'!Y14-SUMIFS('QE Detail - MGMT.'!Z:Z,'QE Detail - MGMT.'!$B:$B,'Recast Mgmt. Adjusted'!$B14) -> 0 | Z14: ='Recast Reported'!Z14-SUMIFS('QE Detail - MGMT.'!AA:AA,'QE Detail - MGMT.'!$B:$B,'Recast Mgmt. Adjusted'!$B14) -> 0 | AA14: ='Recast Reported'!AA14-SUMIFS('QE Detail - MGMT.'!AB:AB,'QE Detail - MGMT.'!$B:$B,'Recast Mgmt. Adjusted'!$B14) -> 0 | AB14: ='Recast Reported'!AB14-SUMIFS('QE Detail - MGMT.'!AC:AC,'QE Detail - MGMT.'!$B:$B,'Recast Mgmt. Adjusted'!$B14) -> 0 | AC14: ='Recast Reported'!AC14-SUMIFS('QE Detail - MGMT.'!AD:AD,'QE Detail - MGMT.'!$B:$B,'Recast Mgmt. Adjusted'!$B14) -> 0 | AD14: ='Recast Reported'!AD14-SUMIFS('QE Detail - MGMT.'!AE:AE,'QE Detail - MGMT.'!$B:$B,'Recast Mgmt. Adjusted'!$B14) -> 0 | AE14: ='Recast Reported'!AE14-SUMIFS('QE Detail - MGMT.'!AF:AF,'QE Detail - MGMT.'!$B:$B,'Recast Mgmt. Adjusted'!$B14) -> 0 | AF14: ='Recast Reported'!AF14-SUMIFS('QE Detail - MGMT.'!AG:AG,'QE Detail - MGMT.'!$B:$B,'Recast Mgmt. Adjusted'!$B14) -> 0 | AG14: ='Recast Reported'!AG14-SUMIFS('QE Detail - MGMT.'!AH:AH,'QE Detail - MGMT.'!$B:$B,'Recast Mgmt. Adjusted'!$B14) -> 0 | AH14: ='Recast Reported'!AH14-SUMIFS('QE Detail - MGMT.'!AI:AI,'QE Detail - MGMT.'!$B:$B,'Recast Mgmt. Adjusted'!$B14) -> 0 | AI14: ='Recast Reported'!AI14-SUMIFS('QE Detail - MGMT.'!AJ:AJ,'QE Detail - MGMT.'!$B:$B,'Recast Mgmt. Adjusted'!$B14) -> 0 | AJ14: ='Recast Reported'!AJ14-SUMIFS('QE Detail - MGMT.'!AK:AK,'QE Detail - MGMT.'!$B:$B,'Recast Mgmt. Adjusted'!$B14) -> 0 | AK14: ='Recast Reported'!AK14-SUMIFS('QE Detail - MGMT.'!AL:AL,'QE Detail - MGMT.'!$B:$B,'Recast Mgmt. Adjusted'!$B14) -> 0 | AL14: ='Recast Reported'!AL14-SUMIFS('QE Detail - MGMT.'!AM:AM,'QE Detail - MGMT.'!$B:$B,'Recast Mgmt. Adjusted'!$B14) -> 0 | AM14: ='Recast Reported'!AM14-SUMIFS('QE Detail - MGMT.'!AN:AN,'QE Detail - MGMT.'!$B:$B,'Recast Mgmt. Adjusted'!$B14) -> 0
A15: Admin wages | B15: Admin wages | C15: =SUMIFS($G15:$BC15,$G$5:$BC$5,"<="&EOMONTH(C$5,0),$G$6:$BC$6,"<="&C$5) -> 0 | D15: =SUMIFS($G15:$AT15,$G$5:$AT$5,">"&EOMONTH(D$5,-12),$G$5:$AT$5,"<="&D$5) -> 0 | E15: =SUMIFS($G15:$AT15,$G$5:$AT$5,">"&EOMONTH(E$5,-12),$G$5:$AT$5,"<="&E$5) -> 0 | G15: ='Recast Reported'!G15-SUMIFS('QE Detail - MGMT.'!H:H,'QE Detail - MGMT.'!$B:$B,'Recast Mgmt. Adjusted'!$B15) -> 0 | H15: ='Recast Reported'!H15-SUMIFS('QE Detail - MGMT.'!I:I,'QE Detail - MGMT.'!$B:$B,'Recast Mgmt. Adjusted'!$B15) -> 0 | I15: ='Recast Reported'!I15-SUMIFS('QE Detail - MGMT.'!J:J,'QE Detail - MGMT.'!$B:$B,'Recast Mgmt. Adjusted'!$B15) -> 0 | J15: ='Recast Reported'!J15-SUMIFS('QE Detail - MGMT.'!K:K,'QE Detail - MGMT.'!$B:$B,'Recast Mgmt. Adjusted'!$B15) -> 0 | K15: ='Recast Reported'!K15-SUMIFS('QE Detail - MGMT.'!L:L,'QE Detail - MGMT.'!$B:$B,'Recast Mgmt. Adjusted'!$B15) -> 0 | L15: ='Recast Reported'!L15-SUMIFS('QE Detail - MGMT.'!M:M,'QE Detail - MGMT.'!$B:$B,'Recast Mgmt. Adjusted'!$B15) -> 0 | M15: ='Recast Reported'!M15-SUMIFS('QE Detail - MGMT.'!N:N,'QE Detail - MGMT.'!$B:$B,'Recast Mgmt. Adjusted'!$B15) -> 0 | N15: ='Recast Reported'!N15-SUMIFS('QE Detail - MGMT.'!O:O,'QE Detail - MGMT.'!$B:$B,'Recast Mgmt. Adjusted'!$B15) -> 0 | O15: ='Recast Reported'!O15-SUMIFS('QE Detail - MGMT.'!P:P,'QE Detail - MGMT.'!$B:$B,'Recast Mgmt. Adjusted'!$B15) -> 0 | P15: ='Recast Reported'!P15-SUMIFS('QE Detail - MGMT.'!Q:Q,'QE Detail - MGMT.'!$B:$B,'Recast Mgmt. Adjusted'!$B15) -> 0 | Q15: ='Recast Reported'!Q15-SUMIFS('QE Detail - MGMT.'!R:R,'QE Detail - MGMT.'!$B:$B,'Recast Mgmt. Adjusted'!$B15) -> 0 | R15: ='Recast Reported'!R15-SUMIFS('QE Detail - MGMT.'!S:S,'QE Detail - MGMT.'!$B:$B,'Recast Mgmt. Adjusted'!$B15) -> 0 | S15: ='Recast Reported'!S15-SUMIFS('QE Detail - MGMT.'!T:T,'QE Detail - MGMT.'!$B:$B,'Recast Mgmt. Adjusted'!$B15) -> 0 | T15: ='Recast Reported'!T15-SUMIFS('QE Detail - MGMT.'!U:U,'QE Detail - MGMT.'!$B:$B,'Recast Mgmt. Adjusted'!$B15) -> 0 | U15: ='Recast Reported'!U15-SUMIFS('QE Detail - MGMT.'!V:V,'QE Detail - MGMT.'!$B:$B,'Recast Mgmt. Adjusted'!$B15) -> 0 | V15: ='Recast Reported'!V15-SUMIFS('QE Detail - MGMT.'!W:W,'QE Detail - MGMT.'!$B:$B,'Recast Mgmt. Adjusted'!$B15) -> 0 | W15: ='Recast Reported'!W15-SUMIFS('QE Detail - MGMT.'!X:X,'QE Detail - MGMT.'!$B:$B,'Recast Mgmt. Adjusted'!$B15) -> 0 | X15: ='Recast Reported'!X15-SUMIFS('QE Detail - MGMT.'!Y:Y,'QE Detail - MGMT.'!$B:$B,'Recast Mgmt. Adjusted'!$B15) -> 0 | Y15: ='Recast Reported'!Y15-SUMIFS('QE Detail - MGMT.'!Z:Z,'QE Detail - MGMT.'!$B:$B,'Recast Mgmt. Adjusted'!$B15) -> 0 | Z15: ='Recast Reported'!Z15-SUMIFS('QE Detail - MGMT.'!AA:AA,'QE Detail - MGMT.'!$B:$B,'Recast Mgmt. Adjusted'!$B15) -> 0 | AA15: ='Recast Reported'!AA15-SUMIFS('QE Detail - MGMT.'!AB:AB,'QE Detail - MGMT.'!$B:$B,'Recast Mgmt. Adjusted'!$B15) -> 0 | AB15: ='Recast Reported'!AB15-SUMIFS('QE Detail - MGMT.'!AC:AC,'QE Detail - MGMT.'!$B:$B,'Recast Mgmt. Adjusted'!$B15) -> 0 | AC15: ='Recast Reported'!AC15-SUMIFS('QE Detail - MGMT.'!AD:AD,'QE Detail - MGMT.'!$B:$B,'Recast Mgmt. Adjusted'!$B15) -> 0 | AD15: ='Recast Reported'!AD15-SUMIFS('QE Detail - MGMT.'!AE:AE,'QE Detail - MGMT.'!$B:$B,'Recast Mgmt. Adjusted'!$B15) -> 0 | AE15: ='Recast Reported'!AE15-SUMIFS('QE Detail - MGMT.'!AF:AF,'QE Detail - MGMT.'!$B:$B,'Recast Mgmt. Adjusted'!$B15) -> 0 | AF15: ='Recast Reported'!AF15-SUMIFS('QE Detail - MGMT.'!AG:AG,'QE Detail - MGMT.'!$B:$B,'Recast Mgmt. Adjusted'!$B15) -> 0 | AG15: ='Recast Reported'!AG15-SUMIFS('QE Detail - MGMT.'!AH:AH,'QE Detail - MGMT.'!$B:$B,'Recast Mgmt. Adjusted'!$B15) -> 0 | AH15: ='Recast Reported'!AH15-SUMIFS('QE Detail - MGMT.'!AI:AI,'QE Detail - MGMT.'!$B:$B,'Recast Mgmt. Adjusted'!$B15) -> 0 | AI15: ='Recast Reported'!AI15-SUMIFS('QE Detail - MGMT.'!AJ:AJ,'QE Detail - MGMT.'!$B:$B,'Recast Mgmt. Adjusted'!$B15) -> 0 | AJ15: ='Recast Reported'!AJ15-SUMIFS('QE Detail - MGMT.'!AK:AK,'QE Detail - MGMT.'!$B:$B,'Recast Mgmt. Adjusted'!$B15) -> 0 | AK15: ='Recast Reported'!AK15-SUMIFS('QE Detail - MGMT.'!AL:AL,'QE Detail - MGMT.'!$B:$B,'Recast Mgmt. Adjusted'!$B15) -> 0 | AL15: ='Recast Reported'!AL15-SUMIFS('QE Detail - MGMT.'!AM:AM,'QE Detail - MGMT.'!$B:$B,'Recast Mgmt. Adjusted'!$B15) -> 0 | AM15: ='Recast Reported'!AM15-SUMIFS('QE Detail - MGMT.'!AN:AN,'QE Detail - MGMT.'!$B:$B,'Recast Mgmt. Adjusted'!$B15) -> 0
B16: Gross wages, total | C16: =SUBTOTAL(9,C13:C15) -> 0 | D16: =SUBTOTAL(9,D13:D15) -> 0 | E16: =SUBTOTAL(9,E13:E15) -> 0 | G16: =SUBTOTAL(9,G13:G15) -> 0 | H16: =SUBTOTAL(9,H13:H15) -> 0 | I16: =SUBTOTAL(9,I13:I15) -> 0 | J16: =SUBTOTAL(9,J13:J15) -> 0 | K16: =SUBTOTAL(9,K13:K15) -> 0 | L16: =SUBTOTAL(9,L13:L15) -> 0 | M16: =SUBTOTAL(9,M13:M15) -> 0 | N16: =SUBTOTAL(9,N13:N15) -> 0 | ... AM16: =SUBTOTAL(9,AM13:AM15) -> 0
A17: Payroll taxes | B17: Payroll taxes | C17: =SUMIFS($G17:$BC17,$G$5:$BC$5,"<="&EOMONTH(C$5,0),$G$6:$BC$6,"<="&C$5) -> 0 | D17: =SUMIFS($G17:$AT17,$G$5:$AT$5,">"&EOMONTH(D$5,-12),$G$5:$AT$5,"<="&D$5) -> 0 | E17: =SUMIFS($G17:$AT17,$G$5:$AT$5,">"&EOMONTH(E$5,-12),$G$5:$AT$5,"<="&E$5) -> 0 | G17: ='Recast Reported'!G17-SUMIFS('QE Detail - MGMT.'!H:H,'QE Detail - MGMT.'!$B:$B,'Recast Mgmt. Adjusted'!$B17) -> 0 | H17: ='Recast Reported'!H17-SUMIFS('QE Detail - MGMT.'!I:I,'QE Detail - MGMT.'!$B:$B,'Recast Mgmt. Adjusted'!$B17) -> 0 | I17: ='Recast Reported'!I17-SUMIFS('QE Detail - MGMT.'!J:J,'QE Detail - MGMT.'!$B:$B,'Recast Mgmt. Adjusted'!$B17) -> 0 | J17: ='Recast Reported'!J17-SUMIFS('QE Detail - MGMT.'!K:K,'QE Detail - MGMT.'!$B:$B,'Recast Mgmt. Adjusted'!$B17) -> 0 | K17: ='Recast Reported'!K17-SUMIFS('QE Detail - MGMT.'!L:L,'QE Detail - MGMT.'!$B:$B,'Recast Mgmt. Adjusted'!$B17) -> 0 | L17: ='Recast Reported'!L17-SUMIFS('QE Detail - MGMT.'!M:M,'QE Detail - MGMT.'!$B:$B,'Recast Mgmt. Adjusted'!$B17) -> 0 | M17: ='Recast Reported'!M17-SUMIFS('QE Detail - MGMT.'!N:N,'QE Detail - MGMT.'!$B:$B,'Recast Mgmt. Adjusted'!$B17) -> 0 | N17: ='Recast Reported'!N17-SUMIFS('QE Detail - MGMT.'!O:O,'QE Detail - MGMT.'!$B:$B,'Recast Mgmt. Adjusted'!$B17) -> 0 | O17: ='Recast Reported'!O17-SUMIFS('QE Detail - MGMT.'!P:P,'QE Detail - MGMT.'!$B:$B,'Recast Mgmt. Adjusted'!$B17) -> 0 | P17: ='Recast Reported'!P17-SUMIFS('QE Detail - MGMT.'!Q:Q,'QE Detail - MGMT.'!$B:$B,'Recast Mgmt. Adjusted'!$B17) -> 0 | Q17: ='Recast Reported'!Q17-SUMIFS('QE Detail - MGMT.'!R:R,'QE Detail - MGMT.'!$B:$B,'Recast Mgmt. Adjusted'!$B17) -> 0 | R17: ='Recast Reported'!R17-SUMIFS('QE Detail - MGMT.'!S:S,'QE Detail - MGMT.'!$B:$B,'Recast Mgmt. Adjusted'!$B17) -> 0 | S17: ='Recast Reported'!S17-SUMIFS('QE Detail - MGMT.'!T:T,'QE Detail - MGMT.'!$B:$B,'Recast Mgmt. Adjusted'!$B17) -> 0 | T17: ='Recast Reported'!T17-SUMIFS('QE Detail - MGMT.'!U:U,'QE Detail - MGMT.'!$B:$B,'Recast Mgmt. Adjusted'!$B17) -> 0 | U17: ='Recast Reported'!U17-SUMIFS('QE Detail - MGMT.'!V:V,'QE Detail - MGMT.'!$B:$B,'Recast Mgmt. Adjusted'!$B17) -> 0 | V17: ='Recast Reported'!V17-SUMIFS('QE Detail - MGMT.'!W:W,'QE Detail - MGMT.'!$B:$B,'Recast Mgmt. Adjusted'!$B17) -> 0 | W17: ='Recast Reported'!W17-SUMIFS('QE Detail - MGMT.'!X:X,'QE Detail - MGMT.'!$B:$B,'Recast Mgmt. Adjusted'!$B17) -> 0 | X17: ='Recast Reported'!X17-SUMIFS('QE Detail - MGMT.'!Y:Y,'QE Detail - MGMT.'!$B:$B,'Recast Mgmt. Adjusted'!$B17) -> 0 | Y17: ='Recast Reported'!Y17-SUMIFS('QE Detail - MGMT.'!Z:Z,'QE Detail - MGMT.'!$B:$B,'Recast Mgmt. Adjusted'!$B17) -> 0 | Z17: ='Recast Reported'!Z17-SUMIFS('QE Detail - MGMT.'!AA:AA,'QE Detail - MGMT.'!$B:$B,'Recast Mgmt. Adjusted'!$B17) -> 0 | AA17: ='Recast Reported'!AA17-SUMIFS('QE Detail - MGMT.'!AB:AB,'QE Detail - MGMT.'!$B:$B,'Recast Mgmt. Adjusted'!$B17) -> 0 | AB17: ='Recast Reported'!AB17-SUMIFS('QE Detail - MGMT.'!AC:AC,'QE Detail - MGMT.'!$B:$B,'Recast Mgmt. Adjusted'!$B17) -> 0 | AC17: ='Recast Reported'!AC17-SUMIFS('QE Detail - MGMT.'!AD:AD,'QE Detail - MGMT.'!$B:$B,'Recast Mgmt. Adjusted'!$B17) -> 0 | AD17: ='Recast Reported'!AD17-SUMIFS('QE Detail - MGMT.'!AE:AE,'QE Detail - MGMT.'!$B:$B,'Recast Mgmt. Adjusted'!$B17) -> 0 | AE17: ='Recast Reported'!AE17-SUMIFS('QE Detail - MGMT.'!AF:AF,'QE Detail - MGMT.'!$B:$B,'Recast Mgmt. Adjusted'!$B17) -> 0 | AF17: ='Recast Reported'!AF17-SUMIFS('QE Detail - MGMT.'!AG:AG,'QE Detail - MGMT.'!$B:$B,'Recast Mgmt. Adjusted'!$B17) -> 0 | AG17: ='Recast Reported'!AG17-SUMIFS('QE Detail - MGMT.'!AH:AH,'QE Detail - MGMT.'!$B:$B,'Recast Mgmt. Adjusted'!$B17) -> 0 | AH17: ='Recast Reported'!AH17-SUMIFS('QE Detail - MGMT.'!AI:AI,'QE Detail - MGMT.'!$B:$B,'Recast Mgmt. Adjusted'!$B17) -> 0 | AI17: ='Recast Reported'!AI17-SUMIFS('QE Detail - MGMT.'!AJ:AJ,'QE Detail - MGMT.'!$B:$B,'Recast Mgmt. Adjusted'!$B17) -> 0 | AJ17: ='Recast Reported'!AJ17-SUMIFS('QE Detail - MGMT.'!AK:AK,'QE Detail - MGMT.'!$B:$B,'Recast Mgmt. Adjusted'!$B17) -> 0 | AK17: ='Recast Reported'!AK17-SUMIFS('QE Detail - MGMT.'!AL:AL,'QE Detail - MGMT.'!$B:$B,'Recast Mgmt. Adjusted'!$B17) -> 0 | AL17: ='Recast Reported'!AL17-SUMIFS('QE Detail - MGMT.'!AM:AM,'QE Detail - MGMT.'!$B:$B,'Recast Mgmt. Adjusted'!$B17) -> 0 | AM17: ='Recast Reported'!AM17-SUMIFS('QE Detail - MGMT.'!AN:AN,'QE Detail - MGMT.'!$B:$B,'Recast Mgmt. Adjusted'!$B17) -> 0
A18: Insurance | B18: Insurance | C18: =SUMIFS($G18:$BC18,$G$5:$BC$5,"<="&EOMONTH(C$5,0),$G$6:$BC$6,"<="&C$5) -> 0 | D18: =SUMIFS($G18:$AT18,$G$5:$AT$5,">"&EOMONTH(D$5,-12),$G$5:$AT$5,"<="&D$5) -> 0 | E18: =SUMIFS($G18:$AT18,$G$5:$AT$5,">"&EOMONTH(E$5,-12),$G$5:$AT$5,"<="&E$5) -> 0 | G18: ='Recast Reported'!G18-SUMIFS('QE Detail - MGMT.'!H:H,'QE Detail - MGMT.'!$B:$B,'Recast Mgmt. Adjusted'!$B18) -> 0 | H18: ='Recast Reported'!H18-SUMIFS('QE Detail - MGMT.'!I:I,'QE Detail - MGMT.'!$B:$B,'Recast Mgmt. Adjusted'!$B18) -> 0 | I18: ='Recast Reported'!I18-SUMIFS('QE Detail - MGMT.'!J:J,'QE Detail - MGMT.'!$B:$B,'Recast Mgmt. Adjusted'!$B18) -> 0 | J18: ='Recast Reported'!J18-SUMIFS('QE Detail - MGMT.'!K:K,'QE Detail - MGMT.'!$B:$B,'Recast Mgmt. Adjusted'!$B18) -> 0 | K18: ='Recast Reported'!K18-SUMIFS('QE Detail - MGMT.'!L:L,'QE Detail - MGMT.'!$B:$B,'Recast Mgmt. Adjusted'!$B18) -> 0 | L18: ='Recast Reported'!L18-SUMIFS('QE Detail - MGMT.'!M:M,'QE Detail - MGMT.'!$B:$B,'Recast Mgmt. Adjusted'!$B18) -> 0 | M18: ='Recast Reported'!M18-SUMIFS('QE Detail - MGMT.'!N:N,'QE Detail - MGMT.'!$B:$B,'Recast Mgmt. Adjusted'!$B18) -> 0 | N18: ='Recast Reported'!N18-SUMIFS('QE Detail - MGMT.'!O:O,'QE Detail - MGMT.'!$B:$B,'Recast Mgmt. Adjusted'!$B18) -> 0 | O18: ='Recast Reported'!O18-SUMIFS('QE Detail - MGMT.'!P:P,'QE Detail - MGMT.'!$B:$B,'Recast Mgmt. Adjusted'!$B18) -> 0 | P18: ='Recast Reported'!P18-SUMIFS('QE Detail - MGMT.'!Q:Q,'QE Detail - MGMT.'!$B:$B,'Recast Mgmt. Adjusted'!$B18) -> 0 | Q18: ='Recast Reported'!Q18-SUMIFS('QE Detail - MGMT.'!R:R,'QE Detail - MGMT.'!$B:$B,'Recast Mgmt. Adjusted'!$B18) -> 0 | R18: ='Recast Reported'!R18-SUMIFS('QE Detail - MGMT.'!S:S,'QE Detail - MGMT.'!$B:$B,'Recast Mgmt. Adjusted'!$B18) -> 0 | S18: ='Recast Reported'!S18-SUMIFS('QE Detail - MGMT.'!T:T,'QE Detail - MGMT.'!$B:$B,'Recast Mgmt. Adjusted'!$B18) -> 0 | T18: ='Recast Reported'!T18-SUMIFS('QE Detail - MGMT.'!U:U,'QE Detail - MGMT.'!$B:$B,'Recast Mgmt. Adjusted'!$B18) -> 0 | U18: ='Recast Reported'!U18-SUMIFS('QE Detail - MGMT.'!V:V,'QE Detail - MGMT.'!$B:$B,'Recast Mgmt. Adjusted'!$B18) -> 0 | V18: ='Recast Reported'!V18-SUMIFS('QE Detail - MGMT.'!W:W,'QE Detail - MGMT.'!$B:$B,'Recast Mgmt. Adjusted'!$B18) -> 0 | W18: ='Recast Reported'!W18-SUMIFS('QE Detail - MGMT.'!X:X,'QE Detail - MGMT.'!$B:$B,'Recast Mgmt. Adjusted'!$B18) -> 0 | X18: ='Recast Reported'!X18-SUMIFS('QE Detail - MGMT.'!Y:Y,'QE Detail - MGMT.'!$B:$B,'Recast Mgmt. Adjusted'!$B18) -> 0 | Y18: ='Recast Reported'!Y18-SUMIFS('QE Detail - MGMT.'!Z:Z,'QE Detail - MGMT.'!$B:$B,'Recast Mgmt. Adjusted'!$B18) -> 0 | Z18: ='Recast Reported'!Z18-SUMIFS('QE Detail - MGMT.'!AA:AA,'QE Detail - MGMT.'!$B:$B,'Recast Mgmt. Adjusted'!$B18) -> 0 | AA18: ='Recast Reported'!AA18-SUMIFS('QE Detail - MGMT.'!AB:AB,'QE Detail - MGMT.'!$B:$B,'Recast Mgmt. Adjusted'!$B18) -> 0 | AB18: ='Recast Reported'!AB18-SUMIFS('QE Detail - MGMT.'!AC:AC,'QE Detail - MGMT.'!$B:$B,'Recast Mgmt. Adjusted'!$B18) -> 0 | AC18: ='Recast Reported'!AC18-SUMIFS('QE Detail - MGMT.'!AD:AD,'QE Detail - MGMT.'!$B:$B,'Recast Mgmt. Adjusted'!$B18) -> 0 | AD18: ='Recast Reported'!AD18-SUMIFS('QE Detail - MGMT.'!AE:AE,'QE Detail - MGMT.'!$B:$B,'Recast Mgmt. Adjusted'!$B18) -> 0 | AE18: ='Recast Reported'!AE18-SUMIFS('QE Detail - MGMT.'!AF:AF,'QE Detail - MGMT.'!$B:$B,'Recast Mgmt. Adjusted'!$B18) -> 0 | AF18: ='Recast Reported'!AF18-SUMIFS('QE Detail - MGMT.'!AG:AG,'QE Detail - MGMT.'!$B:$B,'Recast Mgmt. Adjusted'!$B18) -> 0 | AG18: ='Recast Reported'!AG18-SUMIFS('QE Detail - MGMT.'!AH:AH,'QE Detail - MGMT.'!$B:$B,'Recast Mgmt. Adjusted'!$B18) -> 0 | AH18: ='Recast Reported'!AH18-SUMIFS('QE Detail - MGMT.'!AI:AI,'QE Detail - MGMT.'!$B:$B,'Recast Mgmt. Adjusted'!$B18) -> 0 | AI18: ='Recast Reported'!AI18-SUMIFS('QE Detail - MGMT.'!AJ:AJ,'QE Detail - MGMT.'!$B:$B,'Recast Mgmt. Adjusted'!$B18) -> 0 | AJ18: ='Recast Reported'!AJ18-SUMIFS('QE Detail - MGMT.'!AK:AK,'QE Detail - MGMT.'!$B:$B,'Recast Mgmt. Adjusted'!$B18) -> 0 | AK18: ='Recast Reported'!AK18-SUMIFS('QE Detail - MGMT.'!AL:AL,'QE Detail - MGMT.'!$B:$B,'Recast Mgmt. Adjusted'!$B18) -> 0 | AL18: ='Recast Reported'!AL18-SUMIFS('QE Detail - MGMT.'!AM:AM,'QE Detail - MGMT.'!$B:$B,'Recast Mgmt. Adjusted'!$B18) -> 0 | AM18: ='Recast Reported'!AM18-SUMIFS('QE Detail - MGMT.'!AN:AN,'QE Detail - MGMT.'!$B:$B,'Recast Mgmt. Adjusted'!$B18) -> 0
A19: Employee 401(k) | B19: Employee 401(k) | C19: =SUMIFS($G19:$BC19,$G$5:$BC$5,"<="&EOMONTH(C$5,0),$G$6:$BC$6,"<="&C$5) -> 0 | D19: =SUMIFS($G19:$AT19,$G$5:$AT$5,">"&EOMONTH(D$5,-12),$G$5:$AT$5,"<="&D$5) -> 0 | E19: =SUMIFS($G19:$AT19,$G$5:$AT$5,">"&EOMONTH(E$5,-12),$G$5:$AT$5,"<="&E$5) -> 0 | G19: ='Recast Reported'!G19-SUMIFS('QE Detail - MGMT.'!H:H,'QE Detail - MGMT.'!$B:$B,'Recast Mgmt. Adjusted'!$B19) -> 0 | H19: ='Recast Reported'!H19-SUMIFS('QE Detail - MGMT.'!I:I,'QE Detail - MGMT.'!$B:$B,'Recast Mgmt. Adjusted'!$B19) -> 0 | I19: ='Recast Reported'!I19-SUMIFS('QE Detail - MGMT.'!J:J,'QE Detail - MGMT.'!$B:$B,'Recast Mgmt. Adjusted'!$B19) -> 0 | J19: ='Recast Reported'!J19-SUMIFS('QE Detail - MGMT.'!K:K,'QE Detail - MGMT.'!$B:$B,'Recast Mgmt. Adjusted'!$B19) -> 0 | K19: ='Recast Reported'!K19-SUMIFS('QE Detail - MGMT.'!L:L,'QE Detail - MGMT.'!$B:$B,'Recast Mgmt. Adjusted'!$B19) -> 0 | L19: ='Recast Reported'!L19-SUMIFS('QE Detail - MGMT.'!M:M,'QE Detail - MGMT.'!$B:$B,'Recast Mgmt. Adjusted'!$B19) -> 0 | M19: ='Recast Reported'!M19-SUMIFS('QE Detail - MGMT.'!N:N,'QE Detail - MGMT.'!$B:$B,'Recast Mgmt. Adjusted'!$B19) -> 0 | N19: ='Recast Reported'!N19-SUMIFS('QE Detail - MGMT.'!O:O,'QE Detail - MGMT.'!$B:$B,'Recast Mgmt. Adjusted'!$B19) -> 0 | O19: ='Recast Reported'!O19-SUMIFS('QE Detail - MGMT.'!P:P,'QE Detail - MGMT.'!$B:$B,'Recast Mgmt. Adjusted'!$B19) -> 0 | P19: ='Recast Reported'!P19-SUMIFS('QE Detail - MGMT.'!Q:Q,'QE Detail - MGMT.'!$B:$B,'Recast Mgmt. Adjusted'!$B19) -> 0 | Q19: ='Recast Reported'!Q19-SUMIFS('QE Detail - MGMT.'!R:R,'QE Detail - MGMT.'!$B:$B,'Recast Mgmt. Adjusted'!$B19) -> 0 | R19: ='Recast Reported'!R19-SUMIFS('QE Detail - MGMT.'!S:S,'QE Detail - MGMT.'!$B:$B,'Recast Mgmt. Adjusted'!$B19) -> 0 | S19: ='Recast Reported'!S19-SUMIFS('QE Detail - MGMT.'!T:T,'QE Detail - MGMT.'!$B:$B,'Recast Mgmt. Adjusted'!$B19) -> 0 | T19: ='Recast Reported'!T19-SUMIFS('QE Detail - MGMT.'!U:U,'QE Detail - MGMT.'!$B:$B,'Recast Mgmt. Adjusted'!$B19) -> 0 | U19: ='Recast Reported'!U19-SUMIFS('QE Detail - MGMT.'!V:V,'QE Detail - MGMT.'!$B:$B,'Recast Mgmt. Adjusted'!$B19) -> 0 | V19: ='Recast Reported'!V19-SUMIFS('QE Detail - MGMT.'!W:W,'QE Detail - MGMT.'!$B:$B,'Recast Mgmt. Adjusted'!$B19) -> 0 | W19: ='Recast Reported'!W19-SUMIFS('QE Detail - MGMT.'!X:X,'QE Detail - MGMT.'!$B:$B,'Recast Mgmt. Adjusted'!$B19) -> 0 | X19: ='Recast Reported'!X19-SUMIFS('QE Detail - MGMT.'!Y:Y,'QE Detail - MGMT.'!$B:$B,'Recast Mgmt. Adjusted'!$B19) -> 0 | Y19: ='Recast Reported'!Y19-SUMIFS('QE Detail - MGMT.'!Z:Z,'QE Detail - MGMT.'!$B:$B,'Recast Mgmt. Adjusted'!$B19) -> 0 | Z19: ='Recast Reported'!Z19-SUMIFS('QE Detail - MGMT.'!AA:AA,'QE Detail - MGMT.'!$B:$B,'Recast Mgmt. Adjusted'!$B19) -> 0 | AA19: ='Recast Reported'!AA19-SUMIFS('QE Detail - MGMT.'!AB:AB,'QE Detail - MGMT.'!$B:$B,'Recast Mgmt. Adjusted'!$B19) -> 0 | AB19: ='Recast Reported'!AB19-SUMIFS('QE Detail - MGMT.'!AC:AC,'QE Detail - MGMT.'!$B:$B,'Recast Mgmt. Adjusted'!$B19) -> 0 | AC19: ='Recast Reported'!AC19-SUMIFS('QE Detail - MGMT.'!AD:AD,'QE Detail - MGMT.'!$B:$B,'Recast Mgmt. Adjusted'!$B19) -> 0 | AD19: ='Recast Reported'!AD19-SUMIFS('QE Detail - MGMT.'!AE:AE,'QE Detail - MGMT.'!$B:$B,'Recast Mgmt. Adjusted'!$B19) -> 0 | AE19: ='Recast Reported'!AE19-SUMIFS('QE Detail - MGMT.'!AF:AF,'QE Detail - MGMT.'!$B:$B,'Recast Mgmt. Adjusted'!$B19) -> 0 | AF19: ='Recast Reported'!AF19-SUMIFS('QE Detail - MGMT.'!AG:AG,'QE Detail - MGMT.'!$B:$B,'Recast Mgmt. Adjusted'!$B19) -> 0 | AG19: ='Recast Reported'!AG19-SUMIFS('QE Detail - MGMT.'!AH:AH,'QE Detail - MGMT.'!$B:$B,'Recast Mgmt. Adjusted'!$B19) -> 0 | AH19: ='Recast Reported'!AH19-SUMIFS('QE Detail - MGMT.'!AI:AI,'QE Detail - MGMT.'!$B:$B,'Recast Mgmt. Adjusted'!$B19) -> 0 | AI19: ='Recast Reported'!AI19-SUMIFS('QE Detail - MGMT.'!AJ:AJ,'QE Detail - MGMT.'!$B:$B,'Recast Mgmt. Adjusted'!$B19) -> 0 | AJ19: ='Recast Reported'!AJ19-SUMIFS('QE Detail - MGMT.'!AK:AK,'QE Detail - MGMT.'!$B:$B,'Recast Mgmt. Adjusted'!$B19) -> 0 | AK19: ='Recast Reported'!AK19-SUMIFS('QE Detail - MGMT.'!AL:AL,'QE Detail - MGMT.'!$B:$B,'Recast Mgmt. Adjusted'!$B19) -> 0 | AL19: ='Recast Reported'!AL19-SUMIFS('QE Detail - MGMT.'!AM:AM,'QE Detail - MGMT.'!$B:$B,'Recast Mgmt. Adjusted'!$B19) -> 0 | AM19: ='Recast Reported'!AM19-SUMIFS('QE Detail - MGMT.'!AN:AN,'QE Detail - MGMT.'!$B:$B,'Recast Mgmt. Adjusted'!$B19) -> 0
B20: Salary, payroll taxes, and benefits, total | C20: =SUM(C16:C19) -> 0 | D20: =SUM(D16:D19) -> 0 | E20: =SUM(E16:E19) -> 0 | G20: =SUM(G16:G19) -> 0 | H20: =SUM(H16:H19) -> 0 | I20: =SUM(I16:I19) -> 0 | J20: =SUM(J16:J19) -> 0 | K20: =SUM(K16:K19) -> 0 | L20: =SUM(L16:L19) -> 0 | M20: =SUM(M16:M19) -> 0 | N20: =SUM(N16:N19) -> 0 | ... AM20: =SUM(AM16:AM19) -> 0
A21: Rent - real property | B21: Rent - real property | C21: =SUMIFS($G21:$BC21,$G$5:$BC$5,"<="&EOMONTH(C$5,0),$G$6:$BC$6,"<="&C$5) -> 0 | D21: =SUMIFS($G21:$AT21,$G$5:$AT$5,">"&EOMONTH(D$5,-12),$G$5:$AT$5,"<="&D$5) -> 0 | E21: =SUMIFS($G21:$AT21,$G$5:$AT$5,">"&EOMONTH(E$5,-12),$G$5:$AT$5,"<="&E$5) -> 0 | G21: ='Recast Reported'!G21-SUMIFS('QE Detail - MGMT.'!H:H,'QE Detail - MGMT.'!$B:$B,'Recast Mgmt. Adjusted'!$B21) -> 0 | H21: ='Recast Reported'!H21-SUMIFS('QE Detail - MGMT.'!I:I,'QE Detail - MGMT.'!$B:$B,'Recast Mgmt. Adjusted'!$B21) -> 0 | I21: ='Recast Reported'!I21-SUMIFS('QE Detail - MGMT.'!J:J,'QE Detail - MGMT.'!$B:$B,'Recast Mgmt. Adjusted'!$B21) -> 0 | J21: ='Recast Reported'!J21-SUMIFS('QE Detail - MGMT.'!K:K,'QE Detail - MGMT.'!$B:$B,'Recast Mgmt. Adjusted'!$B21) -> 0 | K21: ='Recast Reported'!K21-SUMIFS('QE Detail - MGMT.'!L:L,'QE Detail - MGMT.'!$B:$B,'Recast Mgmt. Adjusted'!$B21) -> 0 | L21: ='Recast Reported'!L21-SUMIFS('QE Detail - MGMT.'!M:M,'QE Detail - MGMT.'!$B:$B,'Recast Mgmt. Adjusted'!$B21) -> 0 | M21: ='Recast Reported'!M21-SUMIFS('QE Detail - MGMT.'!N:N,'QE Detail - MGMT.'!$B:$B,'Recast Mgmt. Adjusted'!$B21) -> 0 | N21: ='Recast Reported'!N21-SUMIFS('QE Detail - MGMT.'!O:O,'QE Detail - MGMT.'!$B:$B,'Recast Mgmt. Adjusted'!$B21) -> 0 | O21: ='Recast Reported'!O21-SUMIFS('QE Detail - MGMT.'!P:P,'QE Detail - MGMT.'!$B:$B,'Recast Mgmt. Adjusted'!$B21) -> 0 | P21: ='Recast Reported'!P21-SUMIFS('QE Detail - MGMT.'!Q:Q,'QE Detail - MGMT.'!$B:$B,'Recast Mgmt. Adjusted'!$B21) -> 0 | Q21: ='Recast Reported'!Q21-SUMIFS('QE Detail - MGMT.'!R:R,'QE Detail - MGMT.'!$B:$B,'Recast Mgmt. Adjusted'!$B21) -> 0 | R21: ='Recast Reported'!R21-SUMIFS('QE Detail - MGMT.'!S:S,'QE Detail - MGMT.'!$B:$B,'Recast Mgmt. Adjusted'!$B21) -> 0 | S21: ='Recast Reported'!S21-SUMIFS('QE Detail - MGMT.'!T:T,'QE Detail - MGMT.'!$B:$B,'Recast Mgmt. Adjusted'!$B21) -> 0 | T21: ='Recast Reported'!T21-SUMIFS('QE Detail - MGMT.'!U:U,'QE Detail - MGMT.'!$B:$B,'Recast Mgmt. Adjusted'!$B21) -> 0 | U21: ='Recast Reported'!U21-SUMIFS('QE Detail - MGMT.'!V:V,'QE Detail - MGMT.'!$B:$B,'Recast Mgmt. Adjusted'!$B21) -> 0 | V21: ='Recast Reported'!V21-SUMIFS('QE Detail - MGMT.'!W:W,'QE Detail - MGMT.'!$B:$B,'Recast Mgmt. Adjusted'!$B21) -> 0 | W21: ='Recast Reported'!W21-SUMIFS('QE Detail - MGMT.'!X:X,'QE Detail - MGMT.'!$B:$B,'Recast Mgmt. Adjusted'!$B21) -> 0 | X21: ='Recast Reported'!X21-SUMIFS('QE Detail - MGMT.'!Y:Y,'QE Detail - MGMT.'!$B:$B,'Recast Mgmt. Adjusted'!$B21) -> 0 | Y21: ='Recast Reported'!Y21-SUMIFS('QE Detail - MGMT.'!Z:Z,'QE Detail - MGMT.'!$B:$B,'Recast Mgmt. Adjusted'!$B21) -> 0 | Z21: ='Recast Reported'!Z21-SUMIFS('QE Detail - MGMT.'!AA:AA,'QE Detail - MGMT.'!$B:$B,'Recast Mgmt. Adjusted'!$B21) -> 0 | AA21: ='Recast Reported'!AA21-SUMIFS('QE Detail - MGMT.'!AB:AB,'QE Detail - MGMT.'!$B:$B,'Recast Mgmt. Adjusted'!$B21) -> 0 | AB21: ='Recast Reported'!AB21-SUMIFS('QE Detail - MGMT.'!AC:AC,'QE Detail - MGMT.'!$B:$B,'Recast Mgmt. Adjusted'!$B21) -> 0 | AC21: ='Recast Reported'!AC21-SUMIFS('QE Detail - MGMT.'!AD:AD,'QE Detail - MGMT.'!$B:$B,'Recast Mgmt. Adjusted'!$B21) -> 0 | AD21: ='Recast Reported'!AD21-SUMIFS('QE Detail - MGMT.'!AE:AE,'QE Detail - MGMT.'!$B:$B,'Recast Mgmt. Adjusted'!$B21) -> 0 | AE21: ='Recast Reported'!AE21-SUMIFS('QE Detail - MGMT.'!AF:AF,'QE Detail - MGMT.'!$B:$B,'Recast Mgmt. Adjusted'!$B21) -> 0 | AF21: ='Recast Reported'!AF21-SUMIFS('QE Detail - MGMT.'!AG:AG,'QE Detail - MGMT.'!$B:$B,'Recast Mgmt. Adjusted'!$B21) -> 0 | AG21: ='Recast Reported'!AG21-SUMIFS('QE Detail - MGMT.'!AH:AH,'QE Detail - MGMT.'!$B:$B,'Recast Mgmt. Adjusted'!$B21) -> 0 | AH21: ='Recast Reported'!AH21-SUMIFS('QE Detail - MGMT.'!AI:AI,'QE Detail - MGMT.'!$B:$B,'Recast Mgmt. Adjusted'!$B21) -> 0 | AI21: ='Recast Reported'!AI21-SUMIFS('QE Detail - MGMT.'!AJ:AJ,'QE Detail - MGMT.'!$B:$B,'Recast Mgmt. Adjusted'!$B21) -> 0 | AJ21: ='Recast Reported'!AJ21-SUMIFS('QE Detail - MGMT.'!AK:AK,'QE Detail - MGMT.'!$B:$B,'Recast Mgmt. Adjusted'!$B21) -> 0 | AK21: ='Recast Reported'!AK21-SUMIFS('QE Detail - MGMT.'!AL:AL,'QE Detail - MGMT.'!$B:$B,'Recast Mgmt. Adjusted'!$B21) -> 0 | AL21: ='Recast Reported'!AL21-SUMIFS('QE Detail - MGMT.'!AM:AM,'QE Detail - MGMT.'!$B:$B,'Recast Mgmt. Adjusted'!$B21) -> 0 | AM21: ='Recast Reported'!AM21-SUMIFS('QE Detail - MGMT.'!AN:AN,'QE Detail - MGMT.'!$B:$B,'Recast Mgmt. Adjusted'!$B21) -> 0
A22: Property tax expense | B22: Property tax expense | C22: =SUMIFS($G22:$BC22,$G$5:$BC$5,"<="&EOMONTH(C$5,0),$G$6:$BC$6,"<="&C$5) -> 0 | D22: =SUMIFS($G22:$AT22,$G$5:$AT$5,">"&EOMONTH(D$5,-12),$G$5:$AT$5,"<="&D$5) -> 0 | E22: =SUMIFS($G22:$AT22,$G$5:$AT$5,">"&EOMONTH(E$5,-12),$G$5:$AT$5,"<="&E$5) -> 0 | G22: ='Recast Reported'!G22-SUMIFS('QE Detail - MGMT.'!H:H,'QE Detail - MGMT.'!$B:$B,'Recast Mgmt. Adjusted'!$B22) -> 0 | H22: ='Recast Reported'!H22-SUMIFS('QE Detail - MGMT.'!I:I,'QE Detail - MGMT.'!$B:$B,'Recast Mgmt. Adjusted'!$B22) -> 0 | I22: ='Recast Reported'!I22-SUMIFS('QE Detail - MGMT.'!J:J,'QE Detail - MGMT.'!$B:$B,'Recast Mgmt. Adjusted'!$B22) -> 0 | J22: ='Recast Reported'!J22-SUMIFS('QE Detail - MGMT.'!K:K,'QE Detail - MGMT.'!$B:$B,'Recast Mgmt. Adjusted'!$B22) -> 0 | K22: ='Recast Reported'!K22-SUMIFS('QE Detail - MGMT.'!L:L,'QE Detail - MGMT.'!$B:$B,'Recast Mgmt. Adjusted'!$B22) -> 0 | L22: ='Recast Reported'!L22-SUMIFS('QE Detail - MGMT.'!M:M,'QE Detail - MGMT.'!$B:$B,'Recast Mgmt. Adjusted'!$B22) -> 0 | M22: ='Recast Reported'!M22-SUMIFS('QE Detail - MGMT.'!N:N,'QE Detail - MGMT.'!$B:$B,'Recast Mgmt. Adjusted'!$B22) -> 0 | N22: ='Recast Reported'!N22-SUMIFS('QE Detail - MGMT.'!O:O,'QE Detail - MGMT.'!$B:$B,'Recast Mgmt. Adjusted'!$B22) -> 0 | O22: ='Recast Reported'!O22-SUMIFS('QE Detail - MGMT.'!P:P,'QE Detail - MGMT.'!$B:$B,'Recast Mgmt. Adjusted'!$B22) -> 0 | P22: ='Recast Reported'!P22-SUMIFS('QE Detail - MGMT.'!Q:Q,'QE Detail - MGMT.'!$B:$B,'Recast Mgmt. Adjusted'!$B22) -> 0 | Q22: ='Recast Reported'!Q22-SUMIFS('QE Detail - MGMT.'!R:R,'QE Detail - MGMT.'!$B:$B,'Recast Mgmt. Adjusted'!$B22) -> 0 | R22: ='Recast Reported'!R22-SUMIFS('QE Detail - MGMT.'!S:S,'QE Detail - MGMT.'!$B:$B,'Recast Mgmt. Adjusted'!$B22) -> 0 | S22: ='Recast Reported'!S22-SUMIFS('QE Detail - MGMT.'!T:T,'QE Detail - MGMT.'!$B:$B,'Recast Mgmt. Adjusted'!$B22) -> 0 | T22: ='Recast Reported'!T22-SUMIFS('QE Detail - MGMT.'!U:U,'QE Detail - MGMT.'!$B:$B,'Recast Mgmt. Adjusted'!$B22) -> 0 | U22: ='Recast Reported'!U22-SUMIFS('QE Detail - MGMT.'!V:V,'QE Detail - MGMT.'!$B:$B,'Recast Mgmt. Adjusted'!$B22) -> 0 | V22: ='Recast Reported'!V22-SUMIFS('QE Detail - MGMT.'!W:W,'QE Detail - MGMT.'!$B:$B,'Recast Mgmt. Adjusted'!$B22) -> 0 | W22: ='Recast Reported'!W22-SUMIFS('QE Detail - MGMT.'!X:X,'QE Detail - MGMT.'!$B:$B,'Recast Mgmt. Adjusted'!$B22) -> 0 | X22: ='Recast Reported'!X22-SUMIFS('QE Detail - MGMT.'!Y:Y,'QE Detail - MGMT.'!$B:$B,'Recast Mgmt. Adjusted'!$B22) -> 0 | Y22: ='Recast Reported'!Y22-SUMIFS('QE Detail - MGMT.'!Z:Z,'QE Detail - MGMT.'!$B:$B,'Recast Mgmt. Adjusted'!$B22) -> 0 | Z22: ='Recast Reported'!Z22-SUMIFS('QE Detail - MGMT.'!AA:AA,'QE Detail - MGMT.'!$B:$B,'Recast Mgmt. Adjusted'!$B22) -> 0 | AA22: ='Recast Reported'!AA22-SUMIFS('QE Detail - MGMT.'!AB:AB,'QE Detail - MGMT.'!$B:$B,'Recast Mgmt. Adjusted'!$B22) -> 0 | AB22: ='Recast Reported'!AB22-SUMIFS('QE Detail - MGMT.'!AC:AC,'QE Detail - MGMT.'!$B:$B,'Recast Mgmt. Adjusted'!$B22) -> 0 | AC22: ='Recast Reported'!AC22-SUMIFS('QE Detail - MGMT.'!AD:AD,'QE Detail - MGMT.'!$B:$B,'Recast Mgmt. Adjusted'!$B22) -> 0 | AD22: ='Recast Reported'!AD22-SUMIFS('QE Detail - MGMT.'!AE:AE,'QE Detail - MGMT.'!$B:$B,'Recast Mgmt. Adjusted'!$B22) -> 0 | AE22: ='Recast Reported'!AE22-SUMIFS('QE Detail - MGMT.'!AF:AF,'QE Detail - MGMT.'!$B:$B,'Recast Mgmt. Adjusted'!$B22) -> 0 | AF22: ='Recast Reported'!AF22-SUMIFS('QE Detail - MGMT.'!AG:AG,'QE Detail - MGMT.'!$B:$B,'Recast Mgmt. Adjusted'!$B22) -> 0 | AG22: ='Recast Reported'!AG22-SUMIFS('QE Detail - MGMT.'!AH:AH,'QE Detail - MGMT.'!$B:$B,'Recast Mgmt. Adjusted'!$B22) -> 0 | AH22: ='Recast Reported'!AH22-SUMIFS('QE Detail - MGMT.'!AI:AI,'QE Detail - MGMT.'!$B:$B,'Recast Mgmt. Adjusted'!$B22) -> 0 | AI22: ='Recast Reported'!AI22-SUMIFS('QE Detail - MGMT.'!AJ:AJ,'QE Detail - MGMT.'!$B:$B,'Recast Mgmt. Adjusted'!$B22) -> 0 | AJ22: ='Recast Reported'!AJ22-SUMIFS('QE Detail - MGMT.'!AK:AK,'QE Detail - MGMT.'!$B:$B,'Recast Mgmt. Adjusted'!$B22) -> 0 | AK22: ='Recast Reported'!AK22-SUMIFS('QE Detail - MGMT.'!AL:AL,'QE Detail - MGMT.'!$B:$B,'Recast Mgmt. Adjusted'!$B22) -> 0 | AL22: ='Recast Reported'!AL22-SUMIFS('QE Detail - MGMT.'!AM:AM,'QE Detail - MGMT.'!$B:$B,'Recast Mgmt. Adjusted'!$B22) -> 0 | AM22: ='Recast Reported'!AM22-SUMIFS('QE Detail - MGMT.'!AN:AN,'QE Detail - MGMT.'!$B:$B,'Recast Mgmt. Adjusted'!$B22) -> 0
A23: Repairs and maintenance | B23: Repairs and maintenance | C23: =SUMIFS($G23:$BC23,$G$5:$BC$5,"<="&EOMONTH(C$5,0),$G$6:$BC$6,"<="&C$5) -> 0 | D23: =SUMIFS($G23:$AT23,$G$5:$AT$5,">"&EOMONTH(D$5,-12),$G$5:$AT$5,"<="&D$5) -> 0 | E23: =SUMIFS($G23:$AT23,$G$5:$AT$5,">"&EOMONTH(E$5,-12),$G$5:$AT$5,"<="&E$5) -> 0 | G23: ='Recast Reported'!G23-SUMIFS('QE Detail - MGMT.'!H:H,'QE Detail - MGMT.'!$B:$B,'Recast Mgmt. Adjusted'!$B23) -> 0 | H23: ='Recast Reported'!H23-SUMIFS('QE Detail - MGMT.'!I:I,'QE Detail - MGMT.'!$B:$B,'Recast Mgmt. Adjusted'!$B23) -> 0 | I23: ='Recast Reported'!I23-SUMIFS('QE Detail - MGMT.'!J:J,'QE Detail - MGMT.'!$B:$B,'Recast Mgmt. Adjusted'!$B23) -> 0 | J23: ='Recast Reported'!J23-SUMIFS('QE Detail - MGMT.'!K:K,'QE Detail - MGMT.'!$B:$B,'Recast Mgmt. Adjusted'!$B23) -> 0 | K23: ='Recast Reported'!K23-SUMIFS('QE Detail - MGMT.'!L:L,'QE Detail - MGMT.'!$B:$B,'Recast Mgmt. Adjusted'!$B23) -> 0 | L23: ='Recast Reported'!L23-SUMIFS('QE Detail - MGMT.'!M:M,'QE Detail - MGMT.'!$B:$B,'Recast Mgmt. Adjusted'!$B23) -> 0 | M23: ='Recast Reported'!M23-SUMIFS('QE Detail - MGMT.'!N:N,'QE Detail - MGMT.'!$B:$B,'Recast Mgmt. Adjusted'!$B23) -> 0 | N23: ='Recast Reported'!N23-SUMIFS('QE Detail - MGMT.'!O:O,'QE Detail - MGMT.'!$B:$B,'Recast Mgmt. Adjusted'!$B23) -> 0 | O23: ='Recast Reported'!O23-SUMIFS('QE Detail - MGMT.'!P:P,'QE Detail - MGMT.'!$B:$B,'Recast Mgmt. Adjusted'!$B23) -> 0 | P23: ='Recast Reported'!P23-SUMIFS('QE Detail - MGMT.'!Q:Q,'QE Detail - MGMT.'!$B:$B,'Recast Mgmt. Adjusted'!$B23) -> 0 | Q23: ='Recast Reported'!Q23-SUMIFS('QE Detail - MGMT.'!R:R,'QE Detail - MGMT.'!$B:$B,'Recast Mgmt. Adjusted'!$B23) -> 0 | R23: ='Recast Reported'!R23-SUMIFS('QE Detail - MGMT.'!S:S,'QE Detail - MGMT.'!$B:$B,'Recast Mgmt. Adjusted'!$B23) -> 0 | S23: ='Recast Reported'!S23-SUMIFS('QE Detail - MGMT.'!T:T,'QE Detail - MGMT.'!$B:$B,'Recast Mgmt. Adjusted'!$B23) -> 0 | T23: ='Recast Reported'!T23-SUMIFS('QE Detail - MGMT.'!U:U,'QE Detail - MGMT.'!$B:$B,'Recast Mgmt. Adjusted'!$B23) -> 0 | U23: ='Recast Reported'!U23-SUMIFS('QE Detail - MGMT.'!V:V,'QE Detail - MGMT.'!$B:$B,'Recast Mgmt. Adjusted'!$B23) -> 0 | V23: ='Recast Reported'!V23-SUMIFS('QE Detail - MGMT.'!W:W,'QE Detail - MGMT.'!$B:$B,'Recast Mgmt. Adjusted'!$B23) -> 0 | W23: ='Recast Reported'!W23-SUMIFS('QE Detail - MGMT.'!X:X,'QE Detail - MGMT.'!$B:$B,'Recast Mgmt. Adjusted'!$B23) -> 0 | X23: ='Recast Reported'!X23-SUMIFS('QE Detail - MGMT.'!Y:Y,'QE Detail - MGMT.'!$B:$B,'Recast Mgmt. Adjusted'!$B23) -> 0 | Y23: ='Recast Reported'!Y23-SUMIFS('QE Detail - MGMT.'!Z:Z,'QE Detail - MGMT.'!$B:$B,'Recast Mgmt. Adjusted'!$B23) -> 0 | Z23: ='Recast Reported'!Z23-SUMIFS('QE Detail - MGMT.'!AA:AA,'QE Detail - MGMT.'!$B:$B,'Recast Mgmt. Adjusted'!$B23) -> 0 | AA23: ='Recast Reported'!AA23-SUMIFS('QE Detail - MGMT.'!AB:AB,'QE Detail - MGMT.'!$B:$B,'Recast Mgmt. Adjusted'!$B23) -> 0 | AB23: ='Recast Reported'!AB23-SUMIFS('QE Detail - MGMT.'!AC:AC,'QE Detail - MGMT.'!$B:$B,'Recast Mgmt. Adjusted'!$B23) -> 0 | AC23: ='Recast Reported'!AC23-SUMIFS('QE Detail - MGMT.'!AD:AD,'QE Detail - MGMT.'!$B:$B,'Recast Mgmt. Adjusted'!$B23) -> 0 | AD23: ='Recast Reported'!AD23-SUMIFS('QE Detail - MGMT.'!AE:AE,'QE Detail - MGMT.'!$B:$B,'Recast Mgmt. Adjusted'!$B23) -> 0 | AE23: ='Recast Reported'!AE23-SUMIFS('QE Detail - MGMT.'!AF:AF,'QE Detail - MGMT.'!$B:$B,'Recast Mgmt. Adjusted'!$B23) -> 0 | AF23: ='Recast Reported'!AF23-SUMIFS('QE Detail - MGMT.'!AG:AG,'QE Detail - MGMT.'!$B:$B,'Recast Mgmt. Adjusted'!$B23) -> 0 | AG23: ='Recast Reported'!AG23-SUMIFS('QE Detail - MGMT.'!AH:AH,'QE Detail - MGMT.'!$B:$B,'Recast Mgmt. Adjusted'!$B23) -> 0 | AH23: ='Recast Reported'!AH23-SUMIFS('QE Detail - MGMT.'!AI:AI,'QE Detail - MGMT.'!$B:$B,'Recast Mgmt. Adjusted'!$B23) -> 0 | AI23: ='Recast Reported'!AI23-SUMIFS('QE Detail - MGMT.'!AJ:AJ,'QE Detail - MGMT.'!$B:$B,'Recast Mgmt. Adjusted'!$B23) -> 0 | AJ23: ='Recast Reported'!AJ23-SUMIFS('QE Detail - MGMT.'!AK:AK,'QE Detail - MGMT.'!$B:$B,'Recast Mgmt. Adjusted'!$B23) -> 0 | AK23: ='Recast Reported'!AK23-SUMIFS('QE Detail - MGMT.'!AL:AL,'QE Detail - MGMT.'!$B:$B,'Recast Mgmt. Adjusted'!$B23) -> 0 | AL23: ='Recast Reported'!AL23-SUMIFS('QE Detail - MGMT.'!AM:AM,'QE Detail - MGMT.'!$B:$B,'Recast Mgmt. Adjusted'!$B23) -> 0 | AM23: ='Recast Reported'!AM23-SUMIFS('QE Detail - MGMT.'!AN:AN,'QE Detail - MGMT.'!$B:$B,'Recast Mgmt. Adjusted'!$B23) -> 0
A24: Utilities expense | B24: Utilities expense | C24: =SUMIFS($G24:$BC24,$G$5:$BC$5,"<="&EOMONTH(C$5,0),$G$6:$BC$6,"<="&C$5) -> 0 | D24: =SUMIFS($G24:$AT24,$G$5:$AT$5,">"&EOMONTH(D$5,-12),$G$5:$AT$5,"<="&D$5) -> 0 | E24: =SUMIFS($G24:$AT24,$G$5:$AT$5,">"&EOMONTH(E$5,-12),$G$5:$AT$5,"<="&E$5) -> 0 | G24: ='Recast Reported'!G24-SUMIFS('QE Detail - MGMT.'!H:H,'QE Detail - MGMT.'!$B:$B,'Recast Mgmt. Adjusted'!$B24) -> 0 | H24: ='Recast Reported'!H24-SUMIFS('QE Detail - MGMT.'!I:I,'QE Detail - MGMT.'!$B:$B,'Recast Mgmt. Adjusted'!$B24) -> 0 | I24: ='Recast Reported'!I24-SUMIFS('QE Detail - MGMT.'!J:J,'QE Detail - MGMT.'!$B:$B,'Recast Mgmt. Adjusted'!$B24) -> 0 | J24: ='Recast Reported'!J24-SUMIFS('QE Detail - MGMT.'!K:K,'QE Detail - MGMT.'!$B:$B,'Recast Mgmt. Adjusted'!$B24) -> 0 | K24: ='Recast Reported'!K24-SUMIFS('QE Detail - MGMT.'!L:L,'QE Detail - MGMT.'!$B:$B,'Recast Mgmt. Adjusted'!$B24) -> 0 | L24: ='Recast Reported'!L24-SUMIFS('QE Detail - MGMT.'!M:M,'QE Detail - MGMT.'!$B:$B,'Recast Mgmt. Adjusted'!$B24) -> 0 | M24: ='Recast Reported'!M24-SUMIFS('QE Detail - MGMT.'!N:N,'QE Detail - MGMT.'!$B:$B,'Recast Mgmt. Adjusted'!$B24) -> 0 | N24: ='Recast Reported'!N24-SUMIFS('QE Detail - MGMT.'!O:O,'QE Detail - MGMT.'!$B:$B,'Recast Mgmt. Adjusted'!$B24) -> 0 | O24: ='Recast Reported'!O24-SUMIFS('QE Detail - MGMT.'!P:P,'QE Detail - MGMT.'!$B:$B,'Recast Mgmt. Adjusted'!$B24) -> 0 | P24: ='Recast Reported'!P24-SUMIFS('QE Detail - MGMT.'!Q:Q,'QE Detail - MGMT.'!$B:$B,'Recast Mgmt. Adjusted'!$B24) -> 0 | Q24: ='Recast Reported'!Q24-SUMIFS('QE Detail - MGMT.'!R:R,'QE Detail - MGMT.'!$B:$B,'Recast Mgmt. Adjusted'!$B24) -> 0 | R24: ='Recast Reported'!R24-SUMIFS('QE Detail - MGMT.'!S:S,'QE Detail - MGMT.'!$B:$B,'Recast Mgmt. Adjusted'!$B24) -> 0 | S24: ='Recast Reported'!S24-SUMIFS('QE Detail - MGMT.'!T:T,'QE Detail - MGMT.'!$B:$B,'Recast Mgmt. Adjusted'!$B24) -> 0 | T24: ='Recast Reported'!T24-SUMIFS('QE Detail - MGMT.'!U:U,'QE Detail - MGMT.'!$B:$B,'Recast Mgmt. Adjusted'!$B24) -> 0 | U24: ='Recast Reported'!U24-SUMIFS('QE Detail - MGMT.'!V:V,'QE Detail - MGMT.'!$B:$B,'Recast Mgmt. Adjusted'!$B24) -> 0 | V24: ='Recast Reported'!V24-SUMIFS('QE Detail - MGMT.'!W:W,'QE Detail - MGMT.'!$B:$B,'Recast Mgmt. Adjusted'!$B24) -> 0 | W24: ='Recast Reported'!W24-SUMIFS('QE Detail - MGMT.'!X:X,'QE Detail - MGMT.'!$B:$B,'Recast Mgmt. Adjusted'!$B24) -> 0 | X24: ='Recast Reported'!X24-SUMIFS('QE Detail - MGMT.'!Y:Y,'QE Detail - MGMT.'!$B:$B,'Recast Mgmt. Adjusted'!$B24) -> 0 | Y24: ='Recast Reported'!Y24-SUMIFS('QE Detail - MGMT.'!Z:Z,'QE Detail - MGMT.'!$B:$B,'Recast Mgmt. Adjusted'!$B24) -> 0 | Z24: ='Recast Reported'!Z24-SUMIFS('QE Detail - MGMT.'!AA:AA,'QE Detail - MGMT.'!$B:$B,'Recast Mgmt. Adjusted'!$B24) -> 0 | AA24: ='Recast Reported'!AA24-SUMIFS('QE Detail - MGMT.'!AB:AB,'QE Detail - MGMT.'!$B:$B,'Recast Mgmt. Adjusted'!$B24) -> 0 | AB24: ='Recast Reported'!AB24-SUMIFS('QE Detail - MGMT.'!AC:AC,'QE Detail - MGMT.'!$B:$B,'Recast Mgmt. Adjusted'!$B24) -> 0 | AC24: ='Recast Reported'!AC24-SUMIFS('QE Detail - MGMT.'!AD:AD,'QE Detail - MGMT.'!$B:$B,'Recast Mgmt. Adjusted'!$B24) -> 0 | AD24: ='Recast Reported'!AD24-SUMIFS('QE Detail - MGMT.'!AE:AE,'QE Detail - MGMT.'!$B:$B,'Recast Mgmt. Adjusted'!$B24) -> 0 | AE24: ='Recast Reported'!AE24-SUMIFS('QE Detail - MGMT.'!AF:AF,'QE Detail - MGMT.'!$B:$B,'Recast Mgmt. Adjusted'!$B24) -> 0 | AF24: ='Recast Reported'!AF24-SUMIFS('QE Detail - MGMT.'!AG:AG,'QE Detail - MGMT.'!$B:$B,'Recast Mgmt. Adjusted'!$B24) -> 0 | AG24: ='Recast Reported'!AG24-SUMIFS('QE Detail - MGMT.'!AH:AH,'QE Detail - MGMT.'!$B:$B,'Recast Mgmt. Adjusted'!$B24) -> 0 | AH24: ='Recast Reported'!AH24-SUMIFS('QE Detail - MGMT.'!AI:AI,'QE Detail - MGMT.'!$B:$B,'Recast Mgmt. Adjusted'!$B24) -> 0 | AI24: ='Recast Reported'!AI24-SUMIFS('QE Detail - MGMT.'!AJ:AJ,'QE Detail - MGMT.'!$B:$B,'Recast Mgmt. Adjusted'!$B24) -> 0 | AJ24: ='Recast Reported'!AJ24-SUMIFS('QE Detail - MGMT.'!AK:AK,'QE Detail - MGMT.'!$B:$B,'Recast Mgmt. Adjusted'!$B24) -> 0 | AK24: ='Recast Reported'!AK24-SUMIFS('QE Detail - MGMT.'!AL:AL,'QE Detail - MGMT.'!$B:$B,'Recast Mgmt. Adjusted'!$B24) -> 0 | AL24: ='Recast Reported'!AL24-SUMIFS('QE Detail - MGMT.'!AM:AM,'QE Detail - MGMT.'!$B:$B,'Recast Mgmt. Adjusted'!$B24) -> 0 | AM24: ='Recast Reported'!AM24-SUMIFS('QE Detail - MGMT.'!AN:AN,'QE Detail - MGMT.'!$B:$B,'Recast Mgmt. Adjusted'!$B24) -> 0
B25: Rent and building expenses, total | C25: =SUM(C21:C24) -> 0 | D25: =SUM(D21:D24) -> 0 | E25: =SUM(E21:E24) -> 0 | G25: =SUM(G21:G24) -> 0 | H25: =SUM(H21:H24) -> 0 | I25: =SUM(I21:I24) -> 0 | J25: =SUM(J21:J24) -> 0 | K25: =SUM(K21:K24) -> 0 | L25: =SUM(L21:L24) -> 0 | M25: =SUM(M21:M24) -> 0 | N25: =SUM(N21:N24) -> 0 | ... AM25: =SUM(AM21:AM24) -> 0
B26: Advertising | C26: =SUMIFS($G26:$BC26,$G$5:$BC$5,"<="&EOMONTH(C$5,0),$G$6:$BC$6,"<="&C$5) -> 0 | D26: =SUMIFS($G26:$AT26,$G$5:$AT$5,">"&EOMONTH(D$5,-12),$G$5:$AT$5,"<="&D$5) -> 0 | E26: =SUMIFS($G26:$AT26,$G$5:$AT$5,">"&EOMONTH(E$5,-12),$G$5:$AT$5,"<="&E$5) -> 0 | G26: ='Recast Reported'!G26-SUMIFS('QE Detail - MGMT.'!H:H,'QE Detail - MGMT.'!$B:$B,'Recast Mgmt. Adjusted'!$B26) -> 0 | H26: ='Recast Reported'!H26-SUMIFS('QE Detail - MGMT.'!I:I,'QE Detail - MGMT.'!$B:$B,'Recast Mgmt. Adjusted'!$B26) -> 0 | I26: ='Recast Reported'!I26-SUMIFS('QE Detail - MGMT.'!J:J,'QE Detail - MGMT.'!$B:$B,'Recast Mgmt. Adjusted'!$B26) -> 0 | J26: ='Recast Reported'!J26-SUMIFS('QE Detail - MGMT.'!K:K,'QE Detail - MGMT.'!$B:$B,'Recast Mgmt. Adjusted'!$B26) -> 0 | K26: ='Recast Reported'!K26-SUMIFS('QE Detail - MGMT.'!L:L,'QE Detail - MGMT.'!$B:$B,'Recast Mgmt. Adjusted'!$B26) -> 0 | L26: ='Recast Reported'!L26-SUMIFS('QE Detail - MGMT.'!M:M,'QE Detail - MGMT.'!$B:$B,'Recast Mgmt. Adjusted'!$B26) -> 0 | M26: ='Recast Reported'!M26-SUMIFS('QE Detail - MGMT.'!N:N,'QE Detail - MGMT.'!$B:$B,'Recast Mgmt. Adjusted'!$B26) -> 0 | N26: ='Recast Reported'!N26-SUMIFS('QE Detail - MGMT.'!O:O,'QE Detail - MGMT.'!$B:$B,'Recast Mgmt. Adjusted'!$B26) -> 0 | O26: ='Recast Reported'!O26-SUMIFS('QE Detail - MGMT.'!P:P,'QE Detail - MGMT.'!$B:$B,'Recast Mgmt. Adjusted'!$B26) -> 0 | P26: ='Recast Reported'!P26-SUMIFS('QE Detail - MGMT.'!Q:Q,'QE Detail - MGMT.'!$B:$B,'Recast Mgmt. Adjusted'!$B26) -> 0 | Q26: ='Recast Reported'!Q26-SUMIFS('QE Detail - MGMT.'!R:R,'QE Detail - MGMT.'!$B:$B,'Recast Mgmt. Adjusted'!$B26) -> 0 | R26: ='Recast Reported'!R26-SUMIFS('QE Detail - MGMT.'!S:S,'QE Detail - MGMT.'!$B:$B,'Recast Mgmt. Adjusted'!$B26) -> 0 | S26: ='Recast Reported'!S26-SUMIFS('QE Detail - MGMT.'!T:T,'QE Detail - MGMT.'!$B:$B,'Recast Mgmt. Adjusted'!$B26) -> 0 | T26: ='Recast Reported'!T26-SUMIFS('QE Detail - MGMT.'!U:U,'QE Detail - MGMT.'!$B:$B,'Recast Mgmt. Adjusted'!$B26) -> 0 | U26: ='Recast Reported'!U26-SUMIFS('QE Detail - MGMT.'!V:V,'QE Detail - MGMT.'!$B:$B,'Recast Mgmt. Adjusted'!$B26) -> 0 | V26: ='Recast Reported'!V26-SUMIFS('QE Detail - MGMT.'!W:W,'QE Detail - MGMT.'!$B:$B,'Recast Mgmt. Adjusted'!$B26) -> 0 | W26: ='Recast Reported'!W26-SUMIFS('QE Detail - MGMT.'!X:X,'QE Detail - MGMT.'!$B:$B,'Recast Mgmt. Adjusted'!$B26) -> 0 | X26: ='Recast Reported'!X26-SUMIFS('QE Detail - MGMT.'!Y:Y,'QE Detail - MGMT.'!$B:$B,'Recast Mgmt. Adjusted'!$B26) -> 0 | Y26: ='Recast Reported'!Y26-SUMIFS('QE Detail - MGMT.'!Z:Z,'QE Detail - MGMT.'!$B:$B,'Recast Mgmt. Adjusted'!$B26) -> 0 | Z26: ='Recast Reported'!Z26-SUMIFS('QE Detail - MGMT.'!AA:AA,'QE Detail - MGMT.'!$B:$B,'Recast Mgmt. Adjusted'!$B26) -> 0 | AA26: ='Recast Reported'!AA26-SUMIFS('QE Detail - MGMT.'!AB:AB,'QE Detail - MGMT.'!$B:$B,'Recast Mgmt. Adjusted'!$B26) -> 0 | AB26: ='Recast Reported'!AB26-SUMIFS('QE Detail - MGMT.'!AC:AC,'QE Detail - MGMT.'!$B:$B,'Recast Mgmt. Adjusted'!$B26) -> 0 | AC26: ='Recast Reported'!AC26-SUMIFS('QE Detail - MGMT.'!AD:AD,'QE Detail - MGMT.'!$B:$B,'Recast Mgmt. Adjusted'!$B26) -> 0 | AD26: ='Recast Reported'!AD26-SUMIFS('QE Detail - MGMT.'!AE:AE,'QE Detail - MGMT.'!$B:$B,'Recast Mgmt. Adjusted'!$B26) -> 0 | AE26: ='Recast Reported'!AE26-SUMIFS('QE Detail - MGMT.'!AF:AF,'QE Detail - MGMT.'!$B:$B,'Recast Mgmt. Adjusted'!$B26) -> 0 | AF26: ='Recast Reported'!AF26-SUMIFS('QE Detail - MGMT.'!AG:AG,'QE Detail - MGMT.'!$B:$B,'Recast Mgmt. Adjusted'!$B26) -> 0 | AG26: ='Recast Reported'!AG26-SUMIFS('QE Detail - MGMT.'!AH:AH,'QE Detail - MGMT.'!$B:$B,'Recast Mgmt. Adjusted'!$B26) -> 0 | AH26: ='Recast Reported'!AH26-SUMIFS('QE Detail - MGMT.'!AI:AI,'QE Detail - MGMT.'!$B:$B,'Recast Mgmt. Adjusted'!$B26) -> 0 | AI26: ='Recast Reported'!AI26-SUMIFS('QE Detail - MGMT.'!AJ:AJ,'QE Detail - MGMT.'!$B:$B,'Recast Mgmt. Adjusted'!$B26) -> 0 | AJ26: ='Recast Reported'!AJ26-SUMIFS('QE Detail - MGMT.'!AK:AK,'QE Detail - MGMT.'!$B:$B,'Recast Mgmt. Adjusted'!$B26) -> 0 | AK26: ='Recast Reported'!AK26-SUMIFS('QE Detail - MGMT.'!AL:AL,'QE Detail - MGMT.'!$B:$B,'Recast Mgmt. Adjusted'!$B26) -> 0 | AL26: ='Recast Reported'!AL26-SUMIFS('QE Detail - MGMT.'!AM:AM,'QE Detail - MGMT.'!$B:$B,'Recast Mgmt. Adjusted'!$B26) -> 0 | AM26: ='Recast Reported'!AM26-SUMIFS('QE Detail - MGMT.'!AN:AN,'QE Detail - MGMT.'!$B:$B,'Recast Mgmt. Adjusted'!$B26) -> 0
B27: Other | C27: =SUBTOTAL(9,C28:C42) -> 0 | D27: =SUBTOTAL(9,D28:D42) -> 0 | E27: =SUBTOTAL(9,E28:E42) -> 0 | G27: =SUBTOTAL(9,G28:G42) -> 0 | H27: =SUBTOTAL(9,H28:H42) -> 0 | I27: =SUBTOTAL(9,I28:I42) -> 0 | J27: =SUBTOTAL(9,J28:J42) -> 0 | K27: =SUBTOTAL(9,K28:K42) -> 0 | L27: =SUBTOTAL(9,L28:L42) -> 0 | M27: =SUBTOTAL(9,M28:M42) -> 0 | N27: =SUBTOTAL(9,N28:N42) -> 0 | ... AM27: =SUBTOTAL(9,AM28:AM42) -> 0
A28: Other | B28: Bank Service Fees | C28: =SUMIFS($G28:$BC28,$G$5:$BC$5,"<="&EOMONTH(C$5,0),$G$6:$BC$6,"<="&C$5) -> 0 | D28: =SUMIFS($G28:$AT28,$G$5:$AT$5,">"&EOMONTH(D$5,-12),$G$5:$AT$5,"<="&D$5) -> 0 | E28: =SUMIFS($G28:$AT28,$G$5:$AT$5,">"&EOMONTH(E$5,-12),$G$5:$AT$5,"<="&E$5) -> 0 | G28: ='Recast Reported'!G28-SUMIFS('QE Detail - MGMT.'!H:H,'QE Detail - MGMT.'!$A:$A,'Recast Mgmt. Adjusted'!$B28,'QE Detail - MGMT.'!$B:$B,$A28) -> 0 | H28: ='Recast Reported'!H28-SUMIFS('QE Detail - MGMT.'!I:I,'QE Detail - MGMT.'!$A:$A,'Recast Mgmt. Adjusted'!$B28,'QE Detail - MGMT.'!$B:$B,$A28) -> 0 | I28: ='Recast Reported'!I28-SUMIFS('QE Detail - MGMT.'!J:J,'QE Detail - MGMT.'!$A:$A,'Recast Mgmt. Adjusted'!$B28,'QE Detail - MGMT.'!$B:$B,$A28) -> 0 | J28: ='Recast Reported'!J28-SUMIFS('QE Detail - MGMT.'!K:K,'QE Detail - MGMT.'!$A:$A,'Recast Mgmt. Adjusted'!$B28,'QE Detail - MGMT.'!$B:$B,$A28) -> 0 | K28: ='Recast Reported'!K28-SUMIFS('QE Detail - MGMT.'!L:L,'QE Detail - MGMT.'!$A:$A,'Recast Mgmt. Adjusted'!$B28,'QE Detail - MGMT.'!$B:$B,$A28) -> 0 | L28: ='Recast Reported'!L28-SUMIFS('QE Detail - MGMT.'!M:M,'QE Detail - MGMT.'!$A:$A,'Recast Mgmt. Adjusted'!$B28,'QE Detail - MGMT.'!$B:$B,$A28) -> 0 | M28: ='Recast Reported'!M28-SUMIFS('QE Detail - MGMT.'!N:N,'QE Detail - MGMT.'!$A:$A,'Recast Mgmt. Adjusted'!$B28,'QE Detail - MGMT.'!$B:$B,$A28) -> 0 | N28: ='Recast Reported'!N28-SUMIFS('QE Detail - MGMT.'!O:O,'QE Detail - MGMT.'!$A:$A,'Recast Mgmt. Adjusted'!$B28,'QE Detail - MGMT.'!$B:$B,$A28) -> 0 | O28: ='Recast Reported'!O28-SUMIFS('QE Detail - MGMT.'!P:P,'QE Detail - MGMT.'!$A:$A,'Recast Mgmt. Adjusted'!$B28,'QE Detail - MGMT.'!$B:$B,$A28) -> 0 | P28: ='Recast Reported'!P28-SUMIFS('QE Detail - MGMT.'!Q:Q,'QE Detail - MGMT.'!$A:$A,'Recast Mgmt. Adjusted'!$B28,'QE Detail - MGMT.'!$B:$B,$A28) -> 0 | Q28: ='Recast Reported'!Q28-SUMIFS('QE Detail - MGMT.'!R:R,'QE Detail - MGMT.'!$A:$A,'Recast Mgmt. Adjusted'!$B28,'QE Detail - MGMT.'!$B:$B,$A28) -> 0 | R28: ='Recast Reported'!R28-SUMIFS('QE Detail - MGMT.'!S:S,'QE Detail - MGMT.'!$A:$A,'Recast Mgmt. Adjusted'!$B28,'QE Detail - MGMT.'!$B:$B,$A28) -> 0 | S28: ='Recast Reported'!S28-SUMIFS('QE Detail - MGMT.'!T:T,'QE Detail - MGMT.'!$A:$A,'Recast Mgmt. Adjusted'!$B28,'QE Detail - MGMT.'!$B:$B,$A28) -> 0 | T28: ='Recast Reported'!T28-SUMIFS('QE Detail - MGMT.'!U:U,'QE Detail - MGMT.'!$A:$A,'Recast Mgmt. Adjusted'!$B28,'QE Detail - MGMT.'!$B:$B,$A28) -> 0 | U28: ='Recast Reported'!U28-SUMIFS('QE Detail - MGMT.'!V:V,'QE Detail - MGMT.'!$A:$A,'Recast Mgmt. Adjusted'!$B28,'QE Detail - MGMT.'!$B:$B,$A28) -> 0 | V28: ='Recast Reported'!V28-SUMIFS('QE Detail - MGMT.'!W:W,'QE Detail - MGMT.'!$A:$A,'Recast Mgmt. Adjusted'!$B28,'QE Detail - MGMT.'!$B:$B,$A28) -> 0 | W28: ='Recast Reported'!W28-SUMIFS('QE Detail - MGMT.'!X:X,'QE Detail - MGMT.'!$A:$A,'Recast Mgmt. Adjusted'!$B28,'QE Detail - MGMT.'!$B:$B,$A28) -> 0 | X28: ='Recast Reported'!X28-SUMIFS('QE Detail - MGMT.'!Y:Y,'QE Detail - MGMT.'!$A:$A,'Recast Mgmt. Adjusted'!$B28,'QE Detail - MGMT.'!$B:$B,$A28) -> 0 | Y28: ='Recast Reported'!Y28-SUMIFS('QE Detail - MGMT.'!Z:Z,'QE Detail - MGMT.'!$A:$A,'Recast Mgmt. Adjusted'!$B28,'QE Detail - MGMT.'!$B:$B,$A28) -> 0 | Z28: ='Recast Reported'!Z28-SUMIFS('QE Detail - MGMT.'!AA:AA,'QE Detail - MGMT.'!$A:$A,'Recast Mgmt. Adjusted'!$B28,'QE Detail - MGMT.'!$B:$B,$A28) -> 0 | AA28: ='Recast Reported'!AA28-SUMIFS('QE Detail - MGMT.'!AB:AB,'QE Detail - MGMT.'!$A:$A,'Recast Mgmt. Adjusted'!$B28,'QE Detail - MGMT.'!$B:$B,$A28) -> 0 | AB28: ='Recast Reported'!AB28-SUMIFS('QE Detail - MGMT.'!AC:AC,'QE Detail - MGMT.'!$A:$A,'Recast Mgmt. Adjusted'!$B28,'QE Detail - MGMT.'!$B:$B,$A28) -> 0 | AC28: ='Recast Reported'!AC28-SUMIFS('QE Detail - MGMT.'!AD:AD,'QE Detail - MGMT.'!$A:$A,'Recast Mgmt. Adjusted'!$B28,'QE Detail - MGMT.'!$B:$B,$A28) -> 0 | AD28: ='Recast Reported'!AD28-SUMIFS('QE Detail - MGMT.'!AE:AE,'QE Detail - MGMT.'!$A:$A,'Recast Mgmt. Adjusted'!$B28,'QE Detail - MGMT.'!$B:$B,$A28) -> 0 | AE28: ='Recast Reported'!AE28-SUMIFS('QE Detail - MGMT.'!AF:AF,'QE Detail - MGMT.'!$A:$A,'Recast Mgmt. Adjusted'!$B28,'QE Detail - MGMT.'!$B:$B,$A28) -> 0 | AF28: ='Recast Reported'!AF28-SUMIFS('QE Detail - MGMT.'!AG:AG,'QE Detail - MGMT.'!$A:$A,'Recast Mgmt. Adjusted'!$B28,'QE Detail - MGMT.'!$B:$B,$A28) -> 0 | AG28: ='Recast Reported'!AG28-SUMIFS('QE Detail - MGMT.'!AH:AH,'QE Detail - MGMT.'!$A:$A,'Recast Mgmt. Adjusted'!$B28,'QE Detail - MGMT.'!$B:$B,$A28) -> 0 | AH28: ='Recast Reported'!AH28-SUMIFS('QE Detail - MGMT.'!AI:AI,'QE Detail - MGMT.'!$A:$A,'Recast Mgmt. Adjusted'!$B28,'QE Detail - MGMT.'!$B:$B,$A28) -> 0 | AI28: ='Recast Reported'!AI28-SUMIFS('QE Detail - MGMT.'!AJ:AJ,'QE Detail - MGMT.'!$A:$A,'Recast Mgmt. Adjusted'!$B28,'QE Detail - MGMT.'!$B:$B,$A28) -> 0 | AJ28: ='Recast Reported'!AJ28-SUMIFS('QE Detail - MGMT.'!AK:AK,'QE Detail - MGMT.'!$A:$A,'Recast Mgmt. Adjusted'!$B28,'QE Detail - MGMT.'!$B:$B,$A28) -> 0 | AK28: ='Recast Reported'!AK28-SUMIFS('QE Detail - MGMT.'!AL:AL,'QE Detail - MGMT.'!$A:$A,'Recast Mgmt. Adjusted'!$B28,'QE Detail - MGMT.'!$B:$B,$A28) -> 0 | AL28: ='Recast Reported'!AL28-SUMIFS('QE Detail - MGMT.'!AM:AM,'QE Detail - MGMT.'!$A:$A,'Recast Mgmt. Adjusted'!$B28,'QE Detail - MGMT.'!$B:$B,$A28) -> 0 | AM28: ='Recast Reported'!AM28-SUMIFS('QE Detail - MGMT.'!AN:AN,'QE Detail - MGMT.'!$A:$A,'Recast Mgmt. Adjusted'!$B28,'QE Detail - MGMT.'!$B:$B,$A28) -> 0
A29: Other | B29: Computer and Software Expense | C29: =SUMIFS($G29:$BC29,$G$5:$BC$5,"<="&EOMONTH(C$5,0),$G$6:$BC$6,"<="&C$5) -> 0 | D29: =SUMIFS($G29:$AT29,$G$5:$AT$5,">"&EOMONTH(D$5,-12),$G$5:$AT$5,"<="&D$5) -> 0 | E29: =SUMIFS($G29:$AT29,$G$5:$AT$5,">"&EOMONTH(E$5,-12),$G$5:$AT$5,"<="&E$5) -> 0 | G29: ='Recast Reported'!G29-SUMIFS('QE Detail - MGMT.'!H:H,'QE Detail - MGMT.'!$A:$A,'Recast Mgmt. Adjusted'!$B29,'QE Detail - MGMT.'!$B:$B,$A29) -> 0 | H29: ='Recast Reported'!H29-SUMIFS('QE Detail - MGMT.'!I:I,'QE Detail - MGMT.'!$A:$A,'Recast Mgmt. Adjusted'!$B29,'QE Detail - MGMT.'!$B:$B,$A29) -> 0 | I29: ='Recast Reported'!I29-SUMIFS('QE Detail - MGMT.'!J:J,'QE Detail - MGMT.'!$A:$A,'Recast Mgmt. Adjusted'!$B29,'QE Detail - MGMT.'!$B:$B,$A29) -> 0 | J29: ='Recast Reported'!J29-SUMIFS('QE Detail - MGMT.'!K:K,'QE Detail - MGMT.'!$A:$A,'Recast Mgmt. Adjusted'!$B29,'QE Detail - MGMT.'!$B:$B,$A29) -> 0 | K29: ='Recast Reported'!K29-SUMIFS('QE Detail - MGMT.'!L:L,'QE Detail - MGMT.'!$A:$A,'Recast Mgmt. Adjusted'!$B29,'QE Detail - MGMT.'!$B:$B,$A29) -> 0 | L29: ='Recast Reported'!L29-SUMIFS('QE Detail - MGMT.'!M:M,'QE Detail - MGMT.'!$A:$A,'Recast Mgmt. Adjusted'!$B29,'QE Detail - MGMT.'!$B:$B,$A29) -> 0 | M29: ='Recast Reported'!M29-SUMIFS('QE Detail - MGMT.'!N:N,'QE Detail - MGMT.'!$A:$A,'Recast Mgmt. Adjusted'!$B29,'QE Detail - MGMT.'!$B:$B,$A29) -> 0 | N29: ='Recast Reported'!N29-SUMIFS('QE Detail - MGMT.'!O:O,'QE Detail - MGMT.'!$A:$A,'Recast Mgmt. Adjusted'!$B29,'QE Detail - MGMT.'!$B:$B,$A29) -> 0 | O29: ='Recast Reported'!O29-SUMIFS('QE Detail - MGMT.'!P:P,'QE Detail - MGMT.'!$A:$A,'Recast Mgmt. Adjusted'!$B29,'QE Detail - MGMT.'!$B:$B,$A29) -> 0 | P29: ='Recast Reported'!P29-SUMIFS('QE Detail - MGMT.'!Q:Q,'QE Detail - MGMT.'!$A:$A,'Recast Mgmt. Adjusted'!$B29,'QE Detail - MGMT.'!$B:$B,$A29) -> 0 | Q29: ='Recast Reported'!Q29-SUMIFS('QE Detail - MGMT.'!R:R,'QE Detail - MGMT.'!$A:$A,'Recast Mgmt. Adjusted'!$B29,'QE Detail - MGMT.'!$B:$B,$A29) -> 0 | R29: ='Recast Reported'!R29-SUMIFS('QE Detail - MGMT.'!S:S,'QE Detail - MGMT.'!$A:$A,'Recast Mgmt. Adjusted'!$B29,'QE Detail - MGMT.'!$B:$B,$A29) -> 0 | S29: ='Recast Reported'!S29-SUMIFS('QE Detail - MGMT.'!T:T,'QE Detail - MGMT.'!$A:$A,'Recast Mgmt. Adjusted'!$B29,'QE Detail - MGMT.'!$B:$B,$A29) -> 0 | T29: ='Recast Reported'!T29-SUMIFS('QE Detail - MGMT.'!U:U,'QE Detail - MGMT.'!$A:$A,'Recast Mgmt. Adjusted'!$B29,'QE Detail - MGMT.'!$B:$B,$A29) -> 0 | U29: ='Recast Reported'!U29-SUMIFS('QE Detail - MGMT.'!V:V,'QE Detail - MGMT.'!$A:$A,'Recast Mgmt. Adjusted'!$B29,'QE Detail - MGMT.'!$B:$B,$A29) -> 0 | V29: ='Recast Reported'!V29-SUMIFS('QE Detail - MGMT.'!W:W,'QE Detail - MGMT.'!$A:$A,'Recast Mgmt. Adjusted'!$B29,'QE Detail - MGMT.'!$B:$B,$A29) -> 0 | W29: ='Recast Reported'!W29-SUMIFS('QE Detail - MGMT.'!X:X,'QE Detail - MGMT.'!$A:$A,'Recast Mgmt. Adjusted'!$B29,'QE Detail - MGMT.'!$B:$B,$A29) -> 0 | X29: ='Recast Reported'!X29-SUMIFS('QE Detail - MGMT.'!Y:Y,'QE Detail - MGMT.'!$A:$A,'Recast Mgmt. Adjusted'!$B29,'QE Detail - MGMT.'!$B:$B,$A29) -> 0 | Y29: ='Recast Reported'!Y29-SUMIFS('QE Detail - MGMT.'!Z:Z,'QE Detail - MGMT.'!$A:$A,'Recast Mgmt. Adjusted'!$B29,'QE Detail - MGMT.'!$B:$B,$A29) -> 0 | Z29: ='Recast Reported'!Z29-SUMIFS('QE Detail - MGMT.'!AA:AA,'QE Detail - MGMT.'!$A:$A,'Recast Mgmt. Adjusted'!$B29,'QE Detail - MGMT.'!$B:$B,$A29) -> 0 | AA29: ='Recast Reported'!AA29-SUMIFS('QE Detail - MGMT.'!AB:AB,'QE Detail - MGMT.'!$A:$A,'Recast Mgmt. Adjusted'!$B29,'QE Detail - MGMT.'!$B:$B,$A29) -> 0 | AB29: ='Recast Reported'!AB29-SUMIFS('QE Detail - MGMT.'!AC:AC,'QE Detail - MGMT.'!$A:$A,'Recast Mgmt. Adjusted'!$B29,'QE Detail - MGMT.'!$B:$B,$A29) -> 0 | AC29: ='Recast Reported'!AC29-SUMIFS('QE Detail - MGMT.'!AD:AD,'QE Detail - MGMT.'!$A:$A,'Recast Mgmt. Adjusted'!$B29,'QE Detail - MGMT.'!$B:$B,$A29) -> 0 | AD29: ='Recast Reported'!AD29-SUMIFS('QE Detail - MGMT.'!AE:AE,'QE Detail - MGMT.'!$A:$A,'Recast Mgmt. Adjusted'!$B29,'QE Detail - MGMT.'!$B:$B,$A29) -> 0 | AE29: ='Recast Reported'!AE29-SUMIFS('QE Detail - MGMT.'!AF:AF,'QE Detail - MGMT.'!$A:$A,'Recast Mgmt. Adjusted'!$B29,'QE Detail - MGMT.'!$B:$B,$A29) -> 0 | AF29: ='Recast Reported'!AF29-SUMIFS('QE Detail - MGMT.'!AG:AG,'QE Detail - MGMT.'!$A:$A,'Recast Mgmt. Adjusted'!$B29,'QE Detail - MGMT.'!$B:$B,$A29) -> 0 | AG29: ='Recast Reported'!AG29-SUMIFS('QE Detail - MGMT.'!AH:AH,'QE Detail - MGMT.'!$A:$A,'Recast Mgmt. Adjusted'!$B29,'QE Detail - MGMT.'!$B:$B,$A29) -> 0 | AH29: ='Recast Reported'!AH29-SUMIFS('QE Detail - MGMT.'!AI:AI,'QE Detail - MGMT.'!$A:$A,'Recast Mgmt. Adjusted'!$B29,'QE Detail - MGMT.'!$B:$B,$A29) -> 0 | AI29: ='Recast Reported'!AI29-SUMIFS('QE Detail - MGMT.'!AJ:AJ,'QE Detail - MGMT.'!$A:$A,'Recast Mgmt. Adjusted'!$B29,'QE Detail - MGMT.'!$B:$B,$A29) -> 0 | AJ29: ='Recast Reported'!AJ29-SUMIFS('QE Detail - MGMT.'!AK:AK,'QE Detail - MGMT.'!$A:$A,'Recast Mgmt. Adjusted'!$B29,'QE Detail - MGMT.'!$B:$B,$A29) -> 0 | AK29: ='Recast Reported'!AK29-SUMIFS('QE Detail - MGMT.'!AL:AL,'QE Detail - MGMT.'!$A:$A,'Recast Mgmt. Adjusted'!$B29,'QE Detail - MGMT.'!$B:$B,$A29) -> 0 | AL29: ='Recast Reported'!AL29-SUMIFS('QE Detail - MGMT.'!AM:AM,'QE Detail - MGMT.'!$A:$A,'Recast Mgmt. Adjusted'!$B29,'QE Detail - MGMT.'!$B:$B,$A29) -> 0 | AM29: ='Recast Reported'!AM29-SUMIFS('QE Detail - MGMT.'!AN:AN,'QE Detail - MGMT.'!$A:$A,'Recast Mgmt. Adjusted'!$B29,'QE Detail - MGMT.'!$B:$B,$A29) -> 0
A30: Other | B30: Continuing Education | C30: =SUMIFS($G30:$BC30,$G$5:$BC$5,"<="&EOMONTH(C$5,0),$G$6:$BC$6,"<="&C$5) -> 0 | D30: =SUMIFS($G30:$AT30,$G$5:$AT$5,">"&EOMONTH(D$5,-12),$G$5:$AT$5,"<="&D$5) -> 0 | E30: =SUMIFS($G30:$AT30,$G$5:$AT$5,">"&EOMONTH(E$5,-12),$G$5:$AT$5,"<="&E$5) -> 0 | G30: ='Recast Reported'!G30-SUMIFS('QE Detail - MGMT.'!H:H,'QE Detail - MGMT.'!$A:$A,'Recast Mgmt. Adjusted'!$B30,'QE Detail - MGMT.'!$B:$B,$A30) -> 0 | H30: ='Recast Reported'!H30-SUMIFS('QE Detail - MGMT.'!I:I,'QE Detail - MGMT.'!$A:$A,'Recast Mgmt. Adjusted'!$B30,'QE Detail - MGMT.'!$B:$B,$A30) -> 0 | I30: ='Recast Reported'!I30-SUMIFS('QE Detail - MGMT.'!J:J,'QE Detail - MGMT.'!$A:$A,'Recast Mgmt. Adjusted'!$B30,'QE Detail - MGMT.'!$B:$B,$A30) -> 0 | J30: ='Recast Reported'!J30-SUMIFS('QE Detail - MGMT.'!K:K,'QE Detail - MGMT.'!$A:$A,'Recast Mgmt. Adjusted'!$B30,'QE Detail - MGMT.'!$B:$B,$A30) -> 0 | K30: ='Recast Reported'!K30-SUMIFS('QE Detail - MGMT.'!L:L,'QE Detail - MGMT.'!$A:$A,'Recast Mgmt. Adjusted'!$B30,'QE Detail - MGMT.'!$B:$B,$A30) -> 0 | L30: ='Recast Reported'!L30-SUMIFS('QE Detail - MGMT.'!M:M,'QE Detail - MGMT.'!$A:$A,'Recast Mgmt. Adjusted'!$B30,'QE Detail - MGMT.'!$B:$B,$A30) -> 0 | M30: ='Recast Reported'!M30-SUMIFS('QE Detail - MGMT.'!N:N,'QE Detail - MGMT.'!$A:$A,'Recast Mgmt. Adjusted'!$B30,'QE Detail - MGMT.'!$B:$B,$A30) -> 0 | N30: ='Recast Reported'!N30-SUMIFS('QE Detail - MGMT.'!O:O,'QE Detail - MGMT.'!$A:$A,'Recast Mgmt. Adjusted'!$B30,'QE Detail - MGMT.'!$B:$B,$A30) -> 0 | O30: ='Recast Reported'!O30-SUMIFS('QE Detail - MGMT.'!P:P,'QE Detail - MGMT.'!$A:$A,'Recast Mgmt. Adjusted'!$B30,'QE Detail - MGMT.'!$B:$B,$A30) -> 0 | P30: ='Recast Reported'!P30-SUMIFS('QE Detail - MGMT.'!Q:Q,'QE Detail - MGMT.'!$A:$A,'Recast Mgmt. Adjusted'!$B30,'QE Detail - MGMT.'!$B:$B,$A30) -> 0 | Q30: ='Recast Reported'!Q30-SUMIFS('QE Detail - MGMT.'!R:R,'QE Detail - MGMT.'!$A:$A,'Recast Mgmt. Adjusted'!$B30,'QE Detail - MGMT.'!$B:$B,$A30) -> 0 | R30: ='Recast Reported'!R30-SUMIFS('QE Detail - MGMT.'!S:S,'QE Detail - MGMT.'!$A:$A,'Recast Mgmt. Adjusted'!$B30,'QE Detail - MGMT.'!$B:$B,$A30) -> 0 | S30: ='Recast Reported'!S30-SUMIFS('QE Detail - MGMT.'!T:T,'QE Detail - MGMT.'!$A:$A,'Recast Mgmt. Adjusted'!$B30,'QE Detail - MGMT.'!$B:$B,$A30) -> 0 | T30: ='Recast Reported'!T30-SUMIFS('QE Detail - MGMT.'!U:U,'QE Detail - MGMT.'!$A:$A,'Recast Mgmt. Adjusted'!$B30,'QE Detail - MGMT.'!$B:$B,$A30) -> 0 | U30: ='Recast Reported'!U30-SUMIFS('QE Detail - MGMT.'!V:V,'QE Detail - MGMT.'!$A:$A,'Recast Mgmt. Adjusted'!$B30,'QE Detail - MGMT.'!$B:$B,$A30) -> 0 | V30: ='Recast Reported'!V30-SUMIFS('QE Detail - MGMT.'!W:W,'QE Detail - MGMT.'!$A:$A,'Recast Mgmt. Adjusted'!$B30,'QE Detail - MGMT.'!$B:$B,$A30) -> 0 | W30: ='Recast Reported'!W30-SUMIFS('QE Detail - MGMT.'!X:X,'QE Detail - MGMT.'!$A:$A,'Recast Mgmt. Adjusted'!$B30,'QE Detail - MGMT.'!$B:$B,$A30) -> 0 | X30: ='Recast Reported'!X30-SUMIFS('QE Detail - MGMT.'!Y:Y,'QE Detail - MGMT.'!$A:$A,'Recast Mgmt. Adjusted'!$B30,'QE Detail - MGMT.'!$B:$B,$A30) -> 0 | Y30: ='Recast Reported'!Y30-SUMIFS('QE Detail - MGMT.'!Z:Z,'QE Detail - MGMT.'!$A:$A,'Recast Mgmt. Adjusted'!$B30,'QE Detail - MGMT.'!$B:$B,$A30) -> 0 | Z30: ='Recast Reported'!Z30-SUMIFS('QE Detail - MGMT.'!AA:AA,'QE Detail - MGMT.'!$A:$A,'Recast Mgmt. Adjusted'!$B30,'QE Detail - MGMT.'!$B:$B,$A30) -> 0 | AA30: ='Recast Reported'!AA30-SUMIFS('QE Detail - MGMT.'!AB:AB,'QE Detail - MGMT.'!$A:$A,'Recast Mgmt. Adjusted'!$B30,'QE Detail - MGMT.'!$B:$B,$A30) -> 0 | AB30: ='Recast Reported'!AB30-SUMIFS('QE Detail - MGMT.'!AC:AC,'QE Detail - MGMT.'!$A:$A,'Recast Mgmt. Adjusted'!$B30,'QE Detail - MGMT.'!$B:$B,$A30) -> 0 | AC30: ='Recast Reported'!AC30-SUMIFS('QE Detail - MGMT.'!AD:AD,'QE Detail - MGMT.'!$A:$A,'Recast Mgmt. Adjusted'!$B30,'QE Detail - MGMT.'!$B:$B,$A30) -> 0 | AD30: ='Recast Reported'!AD30-SUMIFS('QE Detail - MGMT.'!AE:AE,'QE Detail - MGMT.'!$A:$A,'Recast Mgmt. Adjusted'!$B30,'QE Detail - MGMT.'!$B:$B,$A30) -> 0 | AE30: ='Recast Reported'!AE30-SUMIFS('QE Detail - MGMT.'!AF:AF,'QE Detail - MGMT.'!$A:$A,'Recast Mgmt. Adjusted'!$B30,'QE Detail - MGMT.'!$B:$B,$A30) -> 0 | AF30: ='Recast Reported'!AF30-SUMIFS('QE Detail - MGMT.'!AG:AG,'QE Detail - MGMT.'!$A:$A,'Recast Mgmt. Adjusted'!$B30,'QE Detail - MGMT.'!$B:$B,$A30) -> 0 | AG30: ='Recast Reported'!AG30-SUMIFS('QE Detail - MGMT.'!AH:AH,'QE Detail - MGMT.'!$A:$A,'Recast Mgmt. Adjusted'!$B30,'QE Detail - MGMT.'!$B:$B,$A30) -> 0 | AH30: ='Recast Reported'!AH30-SUMIFS('QE Detail - MGMT.'!AI:AI,'QE Detail - MGMT.'!$A:$A,'Recast Mgmt. Adjusted'!$B30,'QE Detail - MGMT.'!$B:$B,$A30) -> 0 | AI30: ='Recast Reported'!AI30-SUMIFS('QE Detail - MGMT.'!AJ:AJ,'QE Detail - MGMT.'!$A:$A,'Recast Mgmt. Adjusted'!$B30,'QE Detail - MGMT.'!$B:$B,$A30) -> 0 | AJ30: ='Recast Reported'!AJ30-SUMIFS('QE Detail - MGMT.'!AK:AK,'QE Detail - MGMT.'!$A:$A,'Recast Mgmt. Adjusted'!$B30,'QE Detail - MGMT.'!$B:$B,$A30) -> 0 | AK30: ='Recast Reported'!AK30-SUMIFS('QE Detail - MGMT.'!AL:AL,'QE Detail - MGMT.'!$A:$A,'Recast Mgmt. Adjusted'!$B30,'QE Detail - MGMT.'!$B:$B,$A30) -> 0 | AL30: ='Recast Reported'!AL30-SUMIFS('QE Detail - MGMT.'!AM:AM,'QE Detail - MGMT.'!$A:$A,'Recast Mgmt. Adjusted'!$B30,'QE Detail - MGMT.'!$B:$B,$A30) -> 0 | AM30: ='Recast Reported'!AM30-SUMIFS('QE Detail - MGMT.'!AN:AN,'QE Detail - MGMT.'!$A:$A,'Recast Mgmt. Adjusted'!$B30,'QE Detail - MGMT.'!$B:$B,$A30) -> 0
A31: Other | B31: Donations and Contributions | C31: =SUMIFS($G31:$BC31,$G$5:$BC$5,"<="&EOMONTH(C$5,0),$G$6:$BC$6,"<="&C$5) -> 0 | D31: =SUMIFS($G31:$AT31,$G$5:$AT$5,">"&EOMONTH(D$5,-12),$G$5:$AT$5,"<="&D$5) -> 0 | E31: =SUMIFS($G31:$AT31,$G$5:$AT$5,">"&EOMONTH(E$5,-12),$G$5:$AT$5,"<="&E$5) -> 0 | G31: ='Recast Reported'!G31-SUMIFS('QE Detail - MGMT.'!H:H,'QE Detail - MGMT.'!$A:$A,'Recast Mgmt. Adjusted'!$B31,'QE Detail - MGMT.'!$B:$B,$A31) -> 0 | H31: ='Recast Reported'!H31-SUMIFS('QE Detail - MGMT.'!I:I,'QE Detail - MGMT.'!$A:$A,'Recast Mgmt. Adjusted'!$B31,'QE Detail - MGMT.'!$B:$B,$A31) -> 0 | I31: ='Recast Reported'!I31-SUMIFS('QE Detail - MGMT.'!J:J,'QE Detail - MGMT.'!$A:$A,'Recast Mgmt. Adjusted'!$B31,'QE Detail - MGMT.'!$B:$B,$A31) -> 0 | J31: ='Recast Reported'!J31-SUMIFS('QE Detail - MGMT.'!K:K,'QE Detail - MGMT.'!$A:$A,'Recast Mgmt. Adjusted'!$B31,'QE Detail - MGMT.'!$B:$B,$A31) -> 0 | K31: ='Recast Reported'!K31-SUMIFS('QE Detail - MGMT.'!L:L,'QE Detail - MGMT.'!$A:$A,'Recast Mgmt. Adjusted'!$B31,'QE Detail - MGMT.'!$B:$B,$A31) -> 0 | L31: ='Recast Reported'!L31-SUMIFS('QE Detail - MGMT.'!M:M,'QE Detail - MGMT.'!$A:$A,'Recast Mgmt. Adjusted'!$B31,'QE Detail - MGMT.'!$B:$B,$A31) -> 0 | M31: ='Recast Reported'!M31-SUMIFS('QE Detail - MGMT.'!N:N,'QE Detail - MGMT.'!$A:$A,'Recast Mgmt. Adjusted'!$B31,'QE Detail - MGMT.'!$B:$B,$A31) -> 0 | N31: ='Recast Reported'!N31-SUMIFS('QE Detail - MGMT.'!O:O,'QE Detail - MGMT.'!$A:$A,'Recast Mgmt. Adjusted'!$B31,'QE Detail - MGMT.'!$B:$B,$A31) -> 0 | O31: ='Recast Reported'!O31-SUMIFS('QE Detail - MGMT.'!P:P,'QE Detail - MGMT.'!$A:$A,'Recast Mgmt. Adjusted'!$B31,'QE Detail - MGMT.'!$B:$B,$A31) -> 0 | P31: ='Recast Reported'!P31-SUMIFS('QE Detail - MGMT.'!Q:Q,'QE Detail - MGMT.'!$A:$A,'Recast Mgmt. Adjusted'!$B31,'QE Detail - MGMT.'!$B:$B,$A31) -> 0 | Q31: ='Recast Reported'!Q31-SUMIFS('QE Detail - MGMT.'!R:R,'QE Detail - MGMT.'!$A:$A,'Recast Mgmt. Adjusted'!$B31,'QE Detail - MGMT.'!$B:$B,$A31) -> 0 | R31: ='Recast Reported'!R31-SUMIFS('QE Detail - MGMT.'!S:S,'QE Detail - MGMT.'!$A:$A,'Recast Mgmt. Adjusted'!$B31,'QE Detail - MGMT.'!$B:$B,$A31) -> 0 | S31: ='Recast Reported'!S31-SUMIFS('QE Detail - MGMT.'!T:T,'QE Detail - MGMT.'!$A:$A,'Recast Mgmt. Adjusted'!$B31,'QE Detail - MGMT.'!$B:$B,$A31) -> 0 | T31: ='Recast Reported'!T31-SUMIFS('QE Detail - MGMT.'!U:U,'QE Detail - MGMT.'!$A:$A,'Recast Mgmt. Adjusted'!$B31,'QE Detail - MGMT.'!$B:$B,$A31) -> 0 | U31: ='Recast Reported'!U31-SUMIFS('QE Detail - MGMT.'!V:V,'QE Detail - MGMT.'!$A:$A,'Recast Mgmt. Adjusted'!$B31,'QE Detail - MGMT.'!$B:$B,$A31) -> 0 | V31: ='Recast Reported'!V31-SUMIFS('QE Detail - MGMT.'!W:W,'QE Detail - MGMT.'!$A:$A,'Recast Mgmt. Adjusted'!$B31,'QE Detail - MGMT.'!$B:$B,$A31) -> 0 | W31: ='Recast Reported'!W31-SUMIFS('QE Detail - MGMT.'!X:X,'QE Detail - MGMT.'!$A:$A,'Recast Mgmt. Adjusted'!$B31,'QE Detail - MGMT.'!$B:$B,$A31) -> 0 | X31: ='Recast Reported'!X31-SUMIFS('QE Detail - MGMT.'!Y:Y,'QE Detail - MGMT.'!$A:$A,'Recast Mgmt. Adjusted'!$B31,'QE Detail - MGMT.'!$B:$B,$A31) -> 0 | Y31: ='Recast Reported'!Y31-SUMIFS('QE Detail - MGMT.'!Z:Z,'QE Detail - MGMT.'!$A:$A,'Recast Mgmt. Adjusted'!$B31,'QE Detail - MGMT.'!$B:$B,$A31) -> 0 | Z31: ='Recast Reported'!Z31-SUMIFS('QE Detail - MGMT.'!AA:AA,'QE Detail - MGMT.'!$A:$A,'Recast Mgmt. Adjusted'!$B31,'QE Detail - MGMT.'!$B:$B,$A31) -> 0 | AA31: ='Recast Reported'!AA31-SUMIFS('QE Detail - MGMT.'!AB:AB,'QE Detail - MGMT.'!$A:$A,'Recast Mgmt. Adjusted'!$B31,'QE Detail - MGMT.'!$B:$B,$A31) -> 0 | AB31: ='Recast Reported'!AB31-SUMIFS('QE Detail - MGMT.'!AC:AC,'QE Detail - MGMT.'!$A:$A,'Recast Mgmt. Adjusted'!$B31,'QE Detail - MGMT.'!$B:$B,$A31) -> 0 | AC31: ='Recast Reported'!AC31-SUMIFS('QE Detail - MGMT.'!AD:AD,'QE Detail - MGMT.'!$A:$A,'Recast Mgmt. Adjusted'!$B31,'QE Detail - MGMT.'!$B:$B,$A31) -> 0 | AD31: ='Recast Reported'!AD31-SUMIFS('QE Detail - MGMT.'!AE:AE,'QE Detail - MGMT.'!$A:$A,'Recast Mgmt. Adjusted'!$B31,'QE Detail - MGMT.'!$B:$B,$A31) -> 0 | AE31: ='Recast Reported'!AE31-SUMIFS('QE Detail - MGMT.'!AF:AF,'QE Detail - MGMT.'!$A:$A,'Recast Mgmt. Adjusted'!$B31,'QE Detail - MGMT.'!$B:$B,$A31) -> 0 | AF31: ='Recast Reported'!AF31-SUMIFS('QE Detail - MGMT.'!AG:AG,'QE Detail - MGMT.'!$A:$A,'Recast Mgmt. Adjusted'!$B31,'QE Detail - MGMT.'!$B:$B,$A31) -> 0 | AG31: ='Recast Reported'!AG31-SUMIFS('QE Detail - MGMT.'!AH:AH,'QE Detail - MGMT.'!$A:$A,'Recast Mgmt. Adjusted'!$B31,'QE Detail - MGMT.'!$B:$B,$A31) -> 0 | AH31: ='Recast Reported'!AH31-SUMIFS('QE Detail - MGMT.'!AI:AI,'QE Detail - MGMT.'!$A:$A,'Recast Mgmt. Adjusted'!$B31,'QE Detail - MGMT.'!$B:$B,$A31) -> 0 | AI31: ='Recast Reported'!AI31-SUMIFS('QE Detail - MGMT.'!AJ:AJ,'QE Detail - MGMT.'!$A:$A,'Recast Mgmt. Adjusted'!$B31,'QE Detail - MGMT.'!$B:$B,$A31) -> 0 | AJ31: ='Recast Reported'!AJ31-SUMIFS('QE Detail - MGMT.'!AK:AK,'QE Detail - MGMT.'!$A:$A,'Recast Mgmt. Adjusted'!$B31,'QE Detail - MGMT.'!$B:$B,$A31) -> 0 | AK31: ='Recast Reported'!AK31-SUMIFS('QE Detail - MGMT.'!AL:AL,'QE Detail - MGMT.'!$A:$A,'Recast Mgmt. Adjusted'!$B31,'QE Detail - MGMT.'!$B:$B,$A31) -> 0 | AL31: ='Recast Reported'!AL31-SUMIFS('QE Detail - MGMT.'!AM:AM,'QE Detail - MGMT.'!$A:$A,'Recast Mgmt. Adjusted'!$B31,'QE Detail - MGMT.'!$B:$B,$A31) -> 0 | AM31: ='Recast Reported'!AM31-SUMIFS('QE Detail - MGMT.'!AN:AN,'QE Detail - MGMT.'!$A:$A,'Recast Mgmt. Adjusted'!$B31,'QE Detail - MGMT.'!$B:$B,$A31) -> 0
